Workbook
Name listTop: '【103399】クラレ（三ツワフロンテック） 原価一覧'!$E$9
Name TEL: [2]リスト!$C$1:$C$26
Name TEL: [2]リスト!$C$1:$C$26
Name TEL: [2]リスト!$C$1:$C$26
Name TEL: [2]リスト!$C$1:$C$26
Name TEL: '12.10.17 【追加】購入依頼書-5'!$C$1:$C$26
Name TEL: [3]リスト!$C$1:$C$26
Name TEL: [3]リスト!$C$1:$C$26
Name TEL: [3]リスト!$C$1:$C$26
Name TEL: [3]リスト!$C$1:$C$26
Name TEL: '12.11.06 【追加】購入依頼書-5'!$C$1:$C$26
Name TEL: [4]リスト!$C$1:$C$26
Name TEL: [4]リスト!$C$1:$C$26
Name TEL: [4]リスト!$C$1:$C$26
Name TEL: [4]リスト!$C$1:$C$26
Name TEL: '購入依頼書-5'!$C$1:$C$26
Name TEL: '12.10.04 【追加】購入依頼書-5'!$C$1:$C$26
Name あ: #REF!
Name あ: #REF!
Name あ: #REF!
Name あ: #REF!
Name あ: #REF!
Name あ: #REF!
Name あ: #REF!
Name あ: #REF!
Name あ: #REF!
Name あ: #REF!
Name あ: #REF!
Name あ: #REF!
Name あ: #REF!
Name あ: #REF!
Name あ: #REF!
Name あ: #REF!
Name 会社: #REF!
Name 会社: #REF!
Name 会社: #REF!
Name 会社: #REF!
Name 会社: #REF!
Name 会社: #REF!
Name 会社: #REF!
Name 会社: #REF!
Name 会社: #REF!
Name 会社: #REF!
Name 会社: #REF!
Name 会社: #REF!
Name 会社: #REF!
Name 会社: #REF!
Name 会社: #REF!
Name 会社: #REF!
Name 会社名: [2]リスト!$A$1:$A$26
Name 会社名: [2]リスト!$A$1:$A$26
Name 会社名: [2]リスト!$A$1:$A$26
Name 会社名: [2]リスト!$A$1:$A$26
Name 会社名: '12.10.17 【追加】購入依頼書-5'!$A$1:$A$26
Name 会社名: [3]リスト!$A$1:$A$26
Name 会社名: [3]リスト!$A$1:$A$26
Name 会社名: [3]リスト!$A$1:$A$26
Name 会社名: [3]リスト!$A$1:$A$26
Name 会社名: '12.11.06 【追加】購入依頼書-5'!$A$1:$A$26
Name 会社名: [4]リスト!$A$1:$A$26

Sheet 【94485】 NDK 原価一覧1-27出荷
B2: お客先名 | E2: NDK | G2: 合計金額 | J2: =SUM(H:H) -> 5382920
B3: 担当営業 | E3: 青木
B4: 受注番号 | E4: 94485
B5: 希望納期 | E5: 40922
B6: 最終納品
B8: 見積り分類 | C8: メーカー | D8: 仕入先 | E8: 品名 / 型式 | F8: 数量 | G8: 単価 | H8: 金額 | I8: 分類合計 | J8: 詳細 | K8: 備考 | L8: 技術分類 | M8: 発注日 | N8: 発注 | O8: 納期 | P8: 入荷予定日 | Q8: 入荷日
B9: 1 | C9: Asymtek | D9: Asymtek | E9: ZDA-1420510 | F9: 2 | H9: =F9*G9 -> 0
B10: 2 | C10: Asymtek | D10: Asymtek | E10: ZDA-2710370 | F10: 2 | H10: =F10*G10 -> 0
B11: 3 | C11: Asymtek | D11: Asymtek | E11: ZDA-2410321 | F11: 2 | H11: =F11*G11 -> 0
B12: 4 | C12: Asymtek | D12: Asymtek | E12: MT-30005-P67 | F12: 2 | H12: =F12*G12 -> 0
B13: 5 | C13: 蛇の目 | D13: 蛇の目 | E13: JR2203NH | F13: 2 | G13: 400000 | H13: =F13*G13 -> 800000 | K13: 14218 | M13: 40879 | N13: ○ | Q13: 12/19 蛇⇒ｵｼﾞｯｸ
B14: 5 | C14: 蛇の目 | D14: 蛇の目 | E14: 荷造り運賃 | F14: 2 | G14: 10000 | H14: =F14*G14 -> 20000 | K14: 14218 | M14: 40879 | N14: ○ | Q14: 12/19 蛇⇒ｵｼﾞｯｸ
B15: 6 | C15: 蛇の目 | D15: 蛇の目 | E15: COM増設 | F15: 2 | G15: 20000 | H15: =F15*G15 -> 40000 | K15: 14218 | M15: 40879 | N15: ○ | Q15: 12/19 蛇⇒ｵｼﾞｯｸ
B16: 7 | C16: 蛇の目 | D16: 蛇の目 | E16: JR-TB | F16: 2 | G16: 38000 | H16: =F16*G16 -> 76000 | K16: 在庫分使用 | M16: 40879 | N16: ×
B17: 8 | C17: パナソニック | D17: 蛇の目 | E17: A110 | F17: 2 | G17: 155400 | H17: =F17*G17 -> 310800 | J17: ANMA110 | K17: 14217 | L17: Z | M17: 40879 | N17: ○ | Q17: 12/16 蛇⇒ｵｼﾞｯｸ
B18: 8 | C18: パナソニック | D18: 蛇の目 | E18: RS232C | F18: 2 | G18: 12000 | H18: =F18*G18 -> 24000 | J18: 960536106 | K18: 14217 | L18: Z | M18: 40879 | N18: ○ | Q18: 12/16 蛇⇒ｵｼﾞｯｸ
B19: 8 | C19: パナソニック | D19: 蛇の目 | E19: 送料 | F19: 2 | G19: 1000 | H19: =F19*G19 -> 2000 | J19: - | K19: 14217 | L19: Z | M19: 40879 | N19: ○ | Q19: 12/16 蛇⇒ｵｼﾞｯｸ
B20: 9 | C20: パナソニック | D20: 蛇の目 | E20: CSマウントカメラ | F20: 2 | G20: 54600 | H20: =F20*G20 -> 109200 | J20: ANM832 | K20: 14217 | L20: Z | M20: 40879 | N20: ○ | Q20: 12/16 蛇⇒ｵｼﾞｯｸ
B21: 10 | C21: パナソニック | D21: 蛇の目 | E21: 操作キーパット | F21: 2 | G21: 7900 | H21: =F21*G21 -> 15800 | J21: ANM85202 | K21: 14217 | L21: Z | M21: 40879 | N21: ○ | Q21: 12/16 蛇⇒ｵｼﾞｯｸ
B22: 11 | C22: パナソニック | D22: 松下制御テクノ | E22: レンズ | F22: 2 | G22: 23000 | H22: =F22*G22 -> 46000 | J22: ANB846NL | K22: 14216 | L22: Z | M22: 40879 | N22: ○ | P22: 40893 | Q22: 40893
B23: 12 | C23: オプトアート | D23: 都機工 | E23: リアコンバーターレンズ | F23: 2 | G23: 10800 | H23: =F23*G23 -> 21600 | J23: TVR02 | K23: 14215 | L23: Z | M23: 40879 | N23: ○ | Q23: 12/..8
B24: 12 | C24: オプトアート | D24: 都機工 | E24: 送料 | F24: 2 | G24: 1000 | H24: =F24*G24 -> 2000 | J24: - | K24: 14215 | L24: Z | M24: 40879 | N24: ○ | Q24: 12/..8
B25: 12 | C25: VSテクノロジー | D25: VSテクノロジー | E25: 中間リング | F25: 4 | G25: 1380 | H25: =F25*G25 -> 5520 | J25: VS-EXR10 | K25: 14215 | L25: Z | M25: 40879 | N25: ○ | P25: 40904 | Q25: 40904
B26: 13 | C26: CCS | D26: CCS | E26: LED安定照明器 | F26: 2 | G26: 44000 | H26: =F26*G26 -> 88000 | J26: LDR2-32RD | K26: 14213 | L26: Z | M26: 40879 | N26: ○ | P26: 40904 | Q26: 40904
B27: 13 | C27: CCS | D27: CCS | E27: コントローラー | F27: 2 | G27: 13600 | H27: =F27*G27 -> 27200 | J27: PSB-512VL | K27: 14213 | L27: Z | M27: 40879 | N27: ○ | P27: 40904 | Q27: 40904
B28: 13 | C28: CCS | D28: CCS | E28: ケーブル | F28: 2 | G28: 2400 | H28: =F28*G28 -> 4800 | J28: CB-2 | K28: 14213 | L28: Z | M28: 40879 | N28: ○ | P28: 40904 | Q28: 40904
B29: 14 | C29: オジックとダイア | D29: オジックとダイア | E29: 搬送及び制御機構 | F29: 2 | G29: 1895000 | H29: =F29*G29 -> 3790000 | J29: 搬送装置 | K29: 14264 | M29: 40886 | N29: ○ | P29: 40924
B30: 15 | E30: 調整費 | F30: 2 | H30: =F30*G30 -> 0
B31: 16 | E31: 諸経費 | F31: 2 | H31: =F31*G31 -> 0
B32: 17 | E32: 特別値引き

Sheet 【94652】 ビステオン 原価一覧1-31出荷
B2: お客先名 | E2: ﾋﾞｽﾃｵﾝ | G2: 合計金額 | J2: =SUM(H:H) -> 923064
B3: 担当営業 | E3: 本郷
B4: 受注番号 | E4: 94652
B5: 希望納期 | E5: 40927
B6: 最終納品 | E6: 40940
B8: 見積り分類 | C8: メーカー | D8: 仕入先 | E8: 品名 / 型式 | F8: 数量 | G8: 単価 | H8: 金額 | I8: 分類合計 | J8: 詳細 | K8: 備考 | L8: 技術分類 | M8: 発注日 | N8: 発注 | O8: 納期 | P8: 入荷予定日 | Q8: 入荷日
B9: 34 | C9: 遠藤製作所 | D9: 遠藤製作所 | E9: 94652-Y01 | F9: 1 | G9: 6800 | H9: =F9*G9 -> 6800 | J9: ツール取付板 | L9: Y | M9: 40914 | Q9: 40926
B10: 34 | C10: 遠藤製作所 | D10: 遠藤製作所 | E10: SS40077 | F10: 1 | G10: 13800 | H10: =F10*G10 -> 13800 | J10: 725D,725DA用ホルダ（P=25） | L10: Y | M10: 40914 | Q10: 40926
B11: 35 | C11: 遠藤製作所 | D11: 遠藤製作所 | E11: SS3244 | F11: 1 | G11: 7800 | H11: =F11*G11 -> 7800 | J11: タブテーブル（L110) | L11: Y | M11: 40914 | Q11: 40926
B12: 35 | C12: 遠藤製作所 | D12: 遠藤製作所 | E12: SS40564 | F12: 1 | G12: 19500 | H12: =F12*G12 -> 19500 | J12: 新カートリッジホルダ（タブ用） | L12: Y | M12: 40914 | Q12: 40926
B13: 35 | C13: 遠藤製作所 | D13: 遠藤製作所 | E13: 94652-Z01 | F13: 1 | G13: 10500 | H13: =F13*G13 -> 10500 | J13: レギュレータ取付板 | L13: Z | M13: 40914 | Q13: 40926
B14: 3 | C14: 遠藤製作所 | D14: 遠藤製作所 | E14: SS4672 | F14: 1 | G14: 13000 | H14: =F14*G14 -> 13000 | J14: トップシールキャップ改 | L14: Z | M14: 40914 | Q14: 40926
B15: 4 | C15: 遠藤製作所 | D15: 遠藤製作所 | E15: SS4673 | F15: 1 | G15: 8600 | H15: =F15*G15 -> 8600 | J15: シールキャップ | L15: Z | M15: 40914 | Q15: 40926
B16: 5 | C16: 遠藤製作所 | D16: 遠藤製作所 | E16: SS4674 | F16: 1 | G16: 1500 | H16: =F16*G16 -> 1500 | J16: パッド | L16: Z | M16: 40914 | Q16: 40926
B17: 11 | C17: 遠藤製作所 | D17: 遠藤製作所 | E17: SS4675 | F17: 1 | G17: 2000 | H17: =F17*G17 -> 2000 | J17: シールナット | L17: Z | M17: 40914 | Q17: 40926
B18: 14 | C18: 遠藤製作所 | D18: 遠藤製作所 | E18: SS4716 | F18: 1 | G18: 10500 | H18: =F18*G18 -> 10500 | J18: ドロップインアダプタ（特X） | L18: Z | M18: 40914 | Q18: 40926
B19: 15 | C19: 遠藤製作所 | D19: 遠藤製作所 | E19: SS4717 | F19: 1 | G19: 3000 | H19: =F19*G19 -> 3000 | J19: アダプタナット | L19: Z | M19: 40914 | Q19: 40926
B20: 34 | C20: ミスミ | D20: ミスミ | E20: SHAN10 | F20: 1 | G20: 1760 | H20: =F20*G20 -> 1760 | J20: シャフトホルダ | L20: Y | M20: 40914 | P20: 40919 | Q20: 40919
B21: 34 | C21: ミスミ | D21: ミスミ | E21: SLSBF10-28-M6-N4-LKC | F21: 2 | G21: 1150 | H21: =F21*G21 -> 2300 | J21: 六角支柱 | L21: Y | M21: 40914 | P21: 40919 | Q21: 40919
B22: 34 | C22: ミスミ | D22: ミスミ | E22: SLSBG8-24-M4-N4-LKC | F22: 2 | G22: 1210 | H22: =F22*G22 -> 2420 | J22: 六角支柱 | L22: Y | M22: 40914 | P22: 40919 | Q22: 40919
B23: 35 | C23: ミスミ | D23: ミスミ | E23: LRLB5-10 | F23: 1 | G23: 570 | H23: =F23*G23 -> 570 | J23: 長尺ローレット付ボルト | L23: Y | M23: 40914 | P23: 40919 | Q23: 40919
B24: 35 | C24: ミスミ | D24: ミスミ | E24: SUTPB23 | F24: 1 | G24: 150 | H24: =F24*G24 -> 150 | J24: ブッシング | L24: Z | M24: 40914 | P24: 40919 | Q24: 40919
B25: 10 | C25: ミスミ | D25: ミスミ | E25: NPB11 | F25: 1 | G25: 72 | H25: =F25*G25 -> 72 | J25: Oリング | L25: Z | M25: 40914 | P25: 40919 | Q25: 40919
B26: 12 | C26: ミスミ | D26: ミスミ | E26: NPB5 | F26: 1 | G26: 66 | H26: =F26*G26 -> 66 | J26: Oリング | L26: Z | M26: 40914 | P26: 40919 | Q26: 40919
B27: 9 | C27: NOK | D27: ミスミ | E27: CO0517A | F27: 1 | G27: 16 | H27: =F27*G27 -> 16 | J27: Oリング（NOK） | L27: Z | M27: 40914 | P27: 40919 | Q27: 40919
B28: 35 | C28: 日本ピスコ | D28: ミスミ | E28: UB0640-20-B-L10 | F28: 1 | G28: 1000 | H28: =F28*G28 -> 1000 | J28: エアチューブ | L28: Z | M28: 40914 | P28: 40919 | Q28: 40919
B29: 33 | C29: ミスミ | D29: ミスミ | E29: BHDJ-PT-B-37-2 | F29: 1 | G29: 4854 | H29: =F29*G29 -> 4854 | J29: D-subコネクタハーネス | L29: Z | M29: 40914 | P29: 40919 | Q29: 40919
B30: 33 | C30: ミスミ | D30: ミスミ | E30: BHDJ-PT-B-9-2 | F30: 1 | G30: 2037 | H30: =F30*G30 -> 2037 | J30: D-subコネクタハーネス | L30: Z | M30: 40914 | P30: 40919 | Q30: 40919
B31: 33 | C31: ミスミ | D31: ミスミ | E31: ESAW-TCM310-5P | F31: 1 | G31: 3022 | H31: =F31*G31 -> 3022 | J31: コモンブロック端子台 | L31: Z | M31: 40914 | P31: 40919 | Q31: 40919
... B37: 19 | C37: SMC | D37: 都機工 | E37: KQ2U06-00 | F37: 10 | G37: 310 | H37: =F37*G37 -> 3100 | J37: 継手（SMC） | L37: Z | M37: 40914 | P37: 40919 | Q37: 40919
B38: 16 | C38: 機材 | D38: 機材 | E38: DIA-G | F38: 1 | H38: =F38*G38 -> 0 | J38: ガスケット（機材） | L38: Z | M38: 在庫使用
B39: 18 | C39: SMC | D39: 都機工 | E39: KQ2H06-02S | F39: 2 | G39: 154 | H39: =F39*G39 -> 308 | J39: 継手（SMC） | L39: Z | M39: 40914 | P39: 40919 | Q39: 40919
B40: 19 | C40: SMC | D40: 都機工 | E40: KCH06-02S | F40: 10 | G40: 450 | H40: =F40*G40 -> 4500 | J40: 継手（SMC） | L40: Z | M40: 40914 | P40: 40919 | Q40: 40919
B41: 21 | C41: 機材 | D41: 機材 | E41: 580092P | F41: 1 | H41: =F41*G41 -> 0 | J41: キャップシールパッキン | L41: Z | M41: 在庫使用
B42: 22 | C42: 機材 | D42: 機材 | E42: 580091V | F42: 1 | H42: =F42*G42 -> 0 | J42: 300CV用外容器・キャップセット | L42: Z | M42: 在庫使用
B43: 23 | C43: SET | D43: SET | E43: SV35HF | F43: 1 | H43: =F43*G43 -> 0 | J43: ピストンバルブ
B44: 24 | C44: SET | D44: SET | E44: SDP300 | F44: 1 | H44: =F44*G44 -> 0 | J44: ディスペンサ
B45: 25 | C45: 機材 | D45: 機材 | E45: 30-10MC4N-C | F45: 1 | H45: =F45*G45 -> 0 | J45: テフロン継手 | M45: 在庫使用
B46: 26 | C46: 機材 | D46: 機材 | E46: 30-10ME4N-C | F46: 1 | H46: =F46*G46 -> 0 | J46: テフロン継手 | M46: 在庫使用
B47: 27 | C47: 機材 | D47: 機材 | E47: PFA10-8 | F47: 1 | H47: =F47*G47 -> 0 | J47: テフロンホース（1ｍ） | M47: 在庫使用
B48: 28 | C48: SET | D48: SET | E48: SH14TT | F48: 1 | H48: =F48*G48 -> 0 | J48: 14G TTテーパーノズル
B49: 29 | C49: 機材 | D49: 機材 | E49: PFA10-8 | F49: 1 | H49: =F49*G49 -> 0 | J49: テフロンホース（5ｍ） | M49: 在庫使用
B50: 30 | C50: SET | D50: SET | E50: SV3511 | F50: 1 | H50: =F50*G50 -> 0 | J50: SV35用ダイヤフラム
B51: 31 | C51: 蛇の目 | D51: 蛇の目 | E51: JR2404N | F51: 1 | G51: 754000 | H51: =F51*G51 -> 754000 | J51: JR2404N（内部） | M51: 40914 | P51: 40932 | Q51: 40932
B52: 31 | C52: 蛇の目 | D52: 蛇の目 | E52: 荷造り運賃 | F52: 1 | G52: 10000 | H52: =F52*G52 -> 10000 | J52: 荷造り運賃 | M52: 40914 | P52: 40932
B53: 35 | C53: 遠藤製作所 | D53: 遠藤製作所 | E53: 筒 内径 リブ除去 | F53: 1 | G53: 12000 | H53: 12000 | K53: 追加 | M53: 40933 | Q53: 40932
H55: =SUM(H29:H31) -> 9913

Sheet 【94732】舟越製作所 原価一覧1-31出荷
B2: お客先名 | E2: 舟越製作所 | G2: 合計金額 | J2: =SUM(H:H) -> 572984
B3: 担当営業 | E3: 勝田
B4: 受注番号 | E4: 94732
B5: 希望納期 | E5: 40931
B6: 最終納品 | E6: 40939
B8: 見積り分類 | C8: メーカー | D8: 仕入先 | E8: 品名 / 型式 | F8: 数量 | G8: 単価 | H8: 金額 | I8: 分類合計 | J8: 詳細 | K8: 備考 | L8: 技術分類 | M8: 発注日 | N8: 発注 | O8: 納期 | P8: 入荷予定日 | Q8: 入荷日
B9: 1 | C9: 蛇の目 | D9: 蛇の目 | E9: JR2204N | F9: 1 | G9: 465000 | H9: =F9*G9 -> 465000 | M9: 40925 | P9: 40931 | Q9: 40931
B10: 1 | C10: 蛇の目 | D10: 蛇の目 | E10: 荷造り運賃 | F10: 1 | G10: 10000 | H10: =F10*G10 -> 10000 | M10: 40925
H11: =F11*G11 -> 0
H12: =F12*G12 -> 0
B13: 3 | C13: Asymtek | D13: Asymtek | E13: ZDA-1452010 | F13: 1 | H13: =F13*G13 -> 0 | J13: e-starディスペンスヘッド（10cc）
B14: 4 | C14: Asymtek | D14: Asymtek | E14: ZDA-2710370 | F14: 1 | H14: =F14*G14 -> 0 | J14: ACJ-3 CONTROLLER POWER UP（0.1Ω仕様）
B15: 5 | C15: 三ツ矢 | D15: 三ツ矢 | E15: MT-2702-P67 | F15: 1 | G15: 6800 | H15: =F15*G15 -> 6800 | J15: PJノズル27G L-2 | M15: 40925 | P15: 40932 | Q15: 40933
B16: 7 | C16: SET | D16: SET | E16: SDP300 | F16: 1 | H16: =F16*G16 -> 0 | J16: ディスペンサ
B17: 8 | C17: SET | D17: SET | E17: 1000BSH50-6 | F17: 1 | H17: =F17*G17 -> 0 | J17: 10cc シリンジアダプタ 1.8ｍ
B18: 9 | C18: EFD | D18: EFD | E18: 7018417 | F18: 1 | H18: =F18*G18 -> 0 | J18: 5127RTT-B
B19: 10 | C19: SET | D19: SET | E19: SH11LL-B | F19: 1 | H19: =F19*G19 -> 0 | J19: 10cc シリンジ
B20: 11 | C20: 機材 | D20: 機材 | E20: 880001B | F20: 1 | H20: =F20*G20 -> 0 | J20: チューブアダプター | M20: 在庫使用
H21: =F21*G21 -> 0
H22: =F22*G22 -> 0
B23: 6 | C23: ミスミ | D23: ミスミ | E23: SETGR10-25 | F23: 1 | G23: 380 | H23: =F23*G23 -> 380 | J23: 円形支柱 | K23: 発注No：94732（T-SAITO） | L23: Y | M23: 40921 | N23: 済 | P23: 40928 | Q23: 40928
B24: 6 | C24: ミスミ | D24: ミスミ | E24: SCDB-AMW-A37-b30-T20-l20-P10-J10-G10-Z4-F16-W10-M4 | F24: 1 | G24: 3220 | H24: =F24*G24 -> 3220 | J24: シャフトホルダ | K24: 発注No：94732（T-SAITO） | L24: Y | M24: 40921 | N24: 済 | P24: 40928 | Q24: 40928
B25: 6 | C25: ミスミ | D25: ミスミ | E25: SLSBWF7-30-LKC | F25: 4 | G25: 1010 | H25: =F25*G25 -> 4040 | J25: 六角支柱 | K25: 発注No：94732（T-SAITO） | L25: Y | M25: 40921 | N25: 済 | P25: 40928 | Q25: 40928
B26: 6 | C26: ミスミ | D26: ミスミ | E26: XSG25-CR | F26: 1 | G26: 15500 | H26: =F26*G26 -> 15500 | J26: X軸ステージ（リニアボール） | K26: 発注No：94732（T-SAITO） | L26: Y | M26: 40921 | N26: 済 | P26: 40928 | Q26: 40928
B27: 6 | C27: ミスミ | D27: ミスミ | E27: SCB2-5 | F27: 15 | G27: 80 | H27: =F27*G27 -> 1200 | J27: 六角穴付ボルト | K27: 発注No：94732（T-SAITO） | L27: Y | M27: 40921 | N27: 済 | P27: 40928 | Q27: 40928
B28: 6 | C28: ミスミ | D28: ミスミ | E28: CRKB4-10 | F28: 1 | G28: 78 | H28: =F28*G28 -> 78 | J28: 樹脂ローレット | K28: 発注No：94732（T-SAITO） | L28: Y | M28: 40921 | N28: 済 | P28: 40928 | Q28: 40928
B29: 12 | C29: ミスミ | D29: ミスミ | E29: @ECHN-20061106-00010 | F29: 1 | G29: 2814 | H29: =F29*G29 -> 2814 | J29: 特注ハーネス | M29: 技術在庫
B30: 12 | C30: ミスミ | D30: ミスミ | E30: @ECHN-20100219-00022 | F30: 1 | G30: 1933 | H30: =F30*G30 -> 1933 | J30: 特注ハーネス | M30: 技術在庫
B31: 6 | C31: アズワン | D31: 都機工 | E31: No.5 | F31: 1 | G31: 910 | H31: =F31*G31 -> 910 | J31: ミニカップ | M31: 40925 | P31: 40931 | Q31: 40931
B32: 13 | C32: SMC | D32: 都機工 | E32: IR1000-01BG | F32: 1 | G32: 6613 | H32: =F32*G32 -> 6613 | J32: 精密レギュレータ | M32: 40925 | P32: 40931 | Q32: 40931
B33: 13 | C33: SMC | D33: 都機工 | E33: KQ2L04-01S | F33: 2 | G33: 198 | H33: =F33*G33 -> 396 | J33: 継手 | M33: 40925 | P33: 40931 | Q33: 40931
H34: =F34*G34 -> 0
B35: 6 | C35: 遠藤製作所 | D35: 遠藤製作所 | E35: 94732-Y01 | F35: 1 | G35: 3200 | H35: =F35*G35 -> 3200 | J35: ツール取付板 | L35: Y | M35: 40925 | Q35: 40933
B36: 6 | C36: 遠藤製作所 | D36: 遠藤製作所 | E36: 94732-Y02 | F36: 1 | G36: 4800 | H36: =F36*G36 -> 4800 | J36: 25ステージ変換板金 | L36: Y | M36: 40925 | Q36: 40933
B37: 6 | C37: 遠藤製作所 | D37: 遠藤製作所 | E37: 94732-Y03 | F37: 1 | G37: 22200 | H37: =F37*G37 -> 22200 | J37: シリンジホルダ5cc-55cc（POMアダプタ付） | L37: Y | M37: 40925 | Q37: 40933
B38: 6 | C38: 遠藤製作所 | D38: 遠藤製作所 | E38: 94732-Y04 | F38: 1 | G38: 4800 | H38: =F38*G38 -> 4800 | J38: ノズルガイド（5127RTT） | L38: Y | M38: 40925 | Q38: 40933
B39: 6 | C39: 遠藤製作所 | D39: 遠藤製作所 | E39: 94732-Y05 | F39: 1 | G39: 3200 | H39: =F39*G39 -> 3200 | J39: e-star取付変換板 | L39: Y | M39: 40925 | Q39: 40933
B40: 6 | C40: 遠藤製作所 | D40: 遠藤製作所 | E40: 94732-Y06 | F40: 1 | G40: 4200 | H40: =F40*G40 -> 4200 | J40: e-star取付板（ショート） | L40: Y | M40: 40925 | Q40: 40933
B41: 6 | C41: 遠藤製作所 | D41: 遠藤製作所 | E41: 94732-Z01 | F41: 1 | G41: 5800 | H41: =F41*G41 -> 5800 | J41: 捨て打ちカップホルダ | L41: Z | M41: 40925 | Q41: 40933
B42: 6 | C42: 遠藤製作所 | D42: 遠藤製作所 | E42: 94732-Z02 | F42: 1 | G42: 5900 | H42: =F42*G42 -> 5900 | J42: カップ高さ調整板 | L42: Z | M42: 40925 | Q42: 40933
H43: =F43*G43 -> 0
H44: =F44*G44 -> 0
H45: =F45*G45 -> 0
H46: =F46*G46 -> 0

Sheet 【94756】 東亜電気工業（シャープ多気）1-24出荷
B2: お客先名 | E2: 東亜電気 | G2: 合計金額 | J2: =SUM(H:H) -> 1881941
B3: 担当営業 | E3: 真保
B4: 受注番号 | E4: 94756 | G4: 備考 | J4: 本件はタイショーで組立後、客先へ直送しますので、 手配品は入荷次第全てタイショーへ発送願います。
B5: 希望納期 | E5: 40931
B6: 最終納品
B8: 見積り分類 | C8: メーカー | D8: 仕入先 | E8: 品名 / 型式 | F8: 数量 | G8: 単価 | H8: 金額 | I8: 分類合計 | J8: 詳細 | K8: 備考 | L8: 技術分類 | M8: 発注日 | N8: 発注 | O8: 納期 | P8: 入荷予定日 | Q8: 入荷日
B9: 1 | C9: 蛇の目 | D9: 蛇の目 | E9: JR2203N | F9: 3 | G9: 302875 | H9: =F9*G9 -> 908625 | J9: ロボット取付板（P=130mm） | K9: 上野部長手配予定 | L9: - | M9: 在庫使用
B10: 2 | C10: タイショー | D10: タイショー | E10: - | F10: 0 | G10: 0 | H10: =F10*G10 -> 0 | J10: I/Oケーブル | K10: 項目14 SSSTに含まれています。 | L10: Z | O10: 40931
B11: 3 | C11: SET | D11: SET | E11: SDP400-30 | F11: 6 | G11: 18596 | H11: =F11*G11 -> 111576 | L11: -
B12: 4 | C12: タイショー | D12: タイショー | E12: SSST-001-2 | F12: 3 | G12: 4000 | H12: =F12*G12 -> 12000 | J12: ロボット取付板（P=130mm） | L12: Y | M12: 40903 | O12: 40931
B13: 4 | C13: タイショー | D13: タイショー | E13: SSST-002 | F13: 3 | G13: 2800 | H13: =F13*G13 -> 8400 | J13: スペーサーブロック | L13: Y | M13: 40903 | O13: 40931
B14: 4 | C14: タイショー | D14: タイショー | E14: SSST-003 | F14: 3 | G14: 1700 | H14: =F14*G14 -> 5100 | J14: L板金 | L14: Y | M14: 40903 | O14: 40931
B15: 4 | C15: タイショー | D15: タイショー | E15: SSST-004 | F15: 3 | G15: 3100 | H15: =F15*G15 -> 9300 | J15: Y軸変換板 | L15: Y | M15: 40903 | O15: 40931
B16: 4 | C16: タイショー | D16: タイショー | E16: SSST-005-21 | F16: 6 | G16: 3500 | H16: =F16*G16 -> 21000 | J16: シリンジホルダ（10cc） | L16: Y | M16: 40903 | O16: 40931
B17: 4 | C17: タイショー | D17: タイショー | E17: SSST-005-22 | F17: 6 | G17: 3300 | H17: =F17*G17 -> 19800 | J17: シリンジガイド（10cc） | L17: Y | M17: 40903 | O17: 40931
B18: 4 | C18: タイショー | D18: タイショー | E18: SSST-007-2 | F18: 6 | G18: 3700 | H18: =F18*G18 -> 22200 | J18: ノズルガイド（TEC-20N) | L18: Y | M18: 40903 | O18: 40931
B19: 4 | C19: タイショー | D19: タイショー | E19: SSST-008-1 | F19: 3 | G19: 4300 | H19: =F19*G19 -> 12900 | J19: 真空発生ユニット取付板 | L19: Y | M19: 40903 | O19: 40931
B20: 5 | C20: ミスミ | D20: ミスミ | E20: - | F20: 0 | G20: 0 | H20: =F20*G20 -> 0 | J20: 精密ノズルスペーサー | K20: 不要 | L20: - | M20: -
B21: 6 | C21: SMC | D21: 都機工 | E21: SYJ3140-5MZ-M5 | F21: 3 | G21: 5350 | H21: =F21*G21 -> 16050 | J21: 電磁弁 | L21: Z | M21: 40903 | P21: 40921 | Q21: 40919 | R21: 1/13ﾀｲｼｮｰ発送(送No.139598791290）
B22: 7 | C22: SMC | D22: 都機工 | E22: AW10-M5BG | F22: 3 | G22: 3430 | H22: =F22*G22 -> 10290 | J22: レギュレーター | L22: Z | M22: 40903 | P22: 40905 | Q22: 40905
B23: 7 | C23: SMC | D23: 都機工 | E23: MGJ6-5 | F23: 12 | G23: 6000 | H23: =F23*G23 -> 72000 | J23: シリンダ | L23: Z | M23: 40903 | P23: 40905 | Q23: 40905
B24: 7 | C24: SMC | D24: 都機工 | E24: AS1001F-04 | F24: 6 | G24: 770 | H24: =F24*G24 -> 4620 | J24: スピコン | L24: Z | M24: 40903 | P24: 40905 | Q24: 40905
B25: 8 | C25: SET | D25: SET | E25: 1000BSH50-6 | F25: 6 | G25: 495 | H25: =F25*G25 -> 2970 | L25: -
B26: 9 | C26: SET | D26: SET | E26: SH11CP-B | F26: 1 | G26: 705 | H26: =F26*G26 -> 705 | L26: -
B27: 10 | C27: SET | D27: SET | E27: 1000BSH52-6 | F27: 1 | G27: 613 | H27: =F27*G27 -> 613 | L27: -
B28: 11 | C28: SET | D28: SET | E28: SH12CP-B | F28: 1 | G28: 551 | H28: =F28*G28 -> 551 | L28: -
B29: 12 | C29: SET | D29: SET | E29: 7014838 | F29: 1 | G29: 400 | H29: =F29*G29 -> 400 | L29: -
B30: 13 | C30: SET | D30: SET | E30: SPN-20 | F30: 8 | G30: 3500 | H30: =F30*G30 -> 28000 | L30: -
B31: 14 | C31: タイショー | D31: タイショー | E31: SSST | F31: 3 | G31: 35000 | H31: =F31*G31 -> 105000 | J31: 組立設計工数 | L31: Z | M31: 40903 | O31: 40931
B32: 15 | C32: - | D32: - | E32: 特別値引き | H32: =F32*G32 -> 0 | L32: -
B33: 16 | C33: タイショー | D33: タイショー | E33: SSST-0017-2 | F33: 3 | G33: 5600 | H33: =F33*G33 -> 16800 | J33: ワークベース | L33: X | M33: 40903 | O33: 40931
B34: 16 | C34: タイショー | D34: タイショー | E34: SSST-0021-8 | F34: 3 | G34: 19100 | H34: =F34*G34 -> 57300 | J34: ワーク冶具 | L34: X | M34: 40903 | O34: 40931
B35: 16 | C35: タイショー | D35: タイショー | E35: SSST-0022-4 | F35: 12 | G35: 1700 | H35: =F35*G35 -> 20400 | J35: ワーク押さえプレート | L35: X | M35: 40903 | O35: 40931
B36: 16 | C36: タイショー | D36: タイショー | E36: SSST-0025-3(1) | F36: 3 | G36: 2100 | H36: =F36*G36 -> 6300 | J36: サイド板金 | L36: X | M36: 40903 | O36: 40931
B37: 16 | C37: タイショー | D37: タイショー | E37: SSST-0025-3(2) | F37: 3 | G37: 2100 | H37: =F37*G37 -> 6300 | J37: サイド板金 | M37: 40903 | O37: 40931
B38: 16 | C38: タイショー | D38: タイショー | E38: SSST-0028-1 | F38: 12 | G38: 2100 | H38: =F38*G38 -> 25200 | J38: 角押さえアダプター | L38: X | M38: 40903 | O38: 40931
B39: 16 | C39: タイショー | D39: タイショー | E39: SSST-0029-3 | F39: 3 | G39: 8400 | H39: =F39*G39 -> 25200 | J39: リニアガイドプレート | L39: X | M39: 40903 | O39: 40931
B40: 16 | C40: タイショー | D40: タイショー | E40: SSST-0030-6 | F40: 6 | G40: 800 | H40: =F40*G40 -> 4800 | J40: ワーク押さえプレート | L40: X | M40: 40903 | O40: 40931
B41: 16 | C41: タイショー | D41: タイショー | E41: SSST-0030-7 | F41: 24 | G41: 2400 | H41: =F41*G41 -> 57600 | J41: ワーク押さえプレート | K41: 仕様検討中につき、後日発注 | L41: X | M41: 40904 | O41: 40931
B42: 16 | C42: タイショー | D42: タイショー | E42: SSST-0031-1 | F42: 3 | G42: 9600 | H42: =F42*G42 -> 28800 | J42: エアシリンダ冶具（スライド部） | L42: X | M42: 40903 | O42: 40931
B43: 16 | C43: タイショー | D43: タイショー | E43: SSST-0033-1 | F43: 3 | G43: 1200 | H43: =F43*G43 -> 3600 | J43: フロント保護板金 | L43: X | M43: 40903 | O43: 40931
B44: 16 | C44: タイショー | D44: タイショー | E44: φ2.1 | F44: 12 | G44: 180 | H44: =F44*G44 -> 2160 | J44: ワッシャ追加工 | L44: X | M44: 40903 | O44: 40931
B45: 16 | C45: タイショー | D45: タイショー | E45: M2.5*12 | F45: 24 | G45: 35 | H45: =F45*G45 -> 840 | J45: 六角穴付ボルト | L45: X | M45: 40903 | O45: 40931
B46: 16 | C46: ミスミ | D46: ミスミ | E46: AXSH212-VC-1PD2-2EB-3.0-1AC-2DA-F | F46: 3 | G46: 6840 | H46: 20520 | J46: FAｽｲｯﾁﾎﾞｯｸｽ(ｱｾﾝﾌﾞﾙ) | L46: X | M46: 40898 | N46: ○ | P46: 40905 | Q46: 40914 | R46: 佐藤Ｍ渡し済
B47: 16 | C47: ミスミ | D47: ミスミ | E47: CBSTSR3-5 | F47: 24 | G47: 250 | H47: 6000 | J47: ｺﾞｸﾃｲﾄｳﾎﾞﾙﾄ(CBSTSR) | L47: X | M47: 40898 | N47: ○ | P47: 40905 | Q47: 12/28(ﾀ発送） | R47: 送Ｎｏ．139595353811
B48: 16 | C48: ミスミ | D48: ミスミ | E48: CRKB3-10 | F48: 6 | G48: 78 | H48: 468 | J48: ｼﾞｭｼﾛｰﾚｯﾄﾈｼﾞ (CRKB) | L48: X | M48: 40898 | N48: ○ | P48: 40905 | Q48: 40905 | R48: ↑
B49: 16 | C49: ミスミ | D49: ミスミ | E49: DC-37PF-N | F49: 3 | G49: 676 | H49: 2028 | J49: EMID-SUBｺﾈｸﾀ | L49: X | M49: 40898 | N49: ○ | P49: 40905 | Q49: 40905 | R49: ↑
B50: 16 | C50: ミスミ | D50: ミスミ | E50: DC-C8-J13-F41R | F50: 3 | G50: 547 | H50: 1641 | J50: DSUBﾌｰﾄﾞ､ｱｸｾｻﾘｰ | L50: X | M50: 40898 | N50: ○ | P50: 40905 | Q50: 40905 | R50: ↑
B51: 16 | C51: ミスミ | D51: ミスミ | E51: DE-9SF-N | F51: 6 | G51: 350 | H51: 2100 | J51: EMID-SUBｺﾈｸﾀ | L51: X | M51: 40898 | N51: ○ | P51: 40905 | Q51: 40905 | R51: ↑
B52: 16 | C52: ミスミ | D52: ミスミ | E52: DE-C8-J9-F41R | F52: 6 | G52: 448 | H52: 2688 | J52: DSUBﾌｰﾄﾞ､ｱｸｾｻﾘｰ | L52: X | M52: 40898 | N52: ○ | P52: 40905 | Q52: 40905 | R52: ↑
B53: 16 | C53: ミスミ | D53: ミスミ | E53: KBBS4-8 | F53: 36 | G53: 130 | H53: 4680 | J53: ﾃｲﾄｳｼｮｳｹｲﾎﾞﾙﾄ KBBS | L53: X | M53: 40898 | N53: ○ | P53: 40905 | Q53: 40905 | R53: ↑
B54: 16 | C54: ミスミ | D54: ミスミ | E54: KNCLSS4-6-10 | F54: 24 | G54: 189 | H54: 4536 | J54: ｷﾝｿﾞｸｶﾗｰ (KNCLSS) | L54: X | M54: 40898 | N54: ○ | P54: 40905 | Q54: 40905 | R54: ↑
B55: 16 | C55: ミスミ | D55: ミスミ | E55: MJELL4-M5-B | F55: 9 | G55: 210 | H55: 1890 | J55: ﾜﾝﾀｯﾁﾂｷﾞﾃ(MJELL) | L55: X | M55: 40898 | N55: ○ | P55: 40905 | Q55: 40905 | R55: ↑
B56: 16 | C56: ミスミ | D56: ミスミ | E56: MJELL6-M5-B | F56: 3 | G56: 220 | H56: 660 | J56: ﾜﾝﾀｯﾁﾂｷﾞﾃ(MJELL) | L56: X | M56: 40898 | N56: ○ | P56: 40905 | Q56: 40905 | R56: ↑
B57: 16 | C57: ミスミ | D57: ミスミ | E57: MNCNP4-M3 | F57: 36 | G57: 220 | H57: 7920 | J57: ﾐﾆﾁｭｱﾜﾝﾀｯﾁﾂｷﾞﾃ (MNCNP) | L57: X | M57: 40898 | N57: ○ | P57: 40905 | Q57: 40905 | R57: ↑
B58: 16 | C58: ミスミ | D58: ミスミ | E58: MNCNP4-M5 | F58: 6 | G58: 160 | H58: 960 | J58: ﾐﾆﾁｭｱﾜﾝﾀｯﾁﾂｷﾞﾃ (MNCNP) | L58: X | M58: 40898 | N58: ○ | P58: 40905 | Q58: 40905 | R58: ↑
B59: 16 | C59: ミスミ | D59: ミスミ | E59: MNCNP6-M5 | F59: 6 | G59: 170 | H59: 1020 | J59: ﾐﾆﾁｭｱﾜﾝﾀｯﾁﾂｷﾞﾃ (MNCNP) | L59: X | M59: 40898 | N59: ○ | P59: 40905 | Q59: 40905 | R59: ↑
... B68: 16 | C68: ミスミ | D68: ミスミ | E68: XYSG25-CR | F68: 3 | G68: 31000 | H68: 93000 | J68: XYｽﾃｰｼﾞ XYSG | L68: X | M68: 40898 | N68: ○ | P68: 40905 | Q68: 40905 | R68: ↑
C69: ﾐｽﾐ | D69: ﾐｽﾐ | E69: DE-9PF-N | F69: 6 | G69: 350 | H69: 2100 | J69: EMID-SUBｺﾈｸﾀ | M69: 40918 | P69: 40919 | Q69: 40919

Sheet 【94763】 東亜電気工業（シャープ多気）1-24出荷
B2: お客先名 | E2: 東亜電気 | G2: 合計金額 | J2: =SUM(H:H) -> 1856785
B3: 担当営業 | E3: 真保
B4: 受注番号 | E4: 94763 | G4: 備考 | J4: 本件はタイショーで組立後、客先へ直送しますので、 手配品は入荷次第全てタイショーへ発送願います。
B5: 希望納期 | E5: 40931
B6: 最終納品
B8: 見積り分類 | C8: メーカー | D8: 仕入先 | E8: 品名 / 型式 | F8: 数量 | G8: 単価 | H8: 金額 | I8: 分類合計 | J8: 詳細 | K8: 備考 | L8: 技術分類 | M8: 発注日 | N8: 発注 | O8: 納期 | P8: 入荷予定日 | Q8: 入荷日
B9: 1 | C9: 蛇の目 | D9: 蛇の目 | E9: JR2203N | F9: 3 | G9: 302875 | H9: =F9*G9 -> 908625 | J9: ロボット取付板（P=130mm） | K9: 上野部長手配予定 | L9: - | M9: 在庫使用
B10: 2 | C10: タイショー | D10: タイショー | E10: - | F10: 0 | G10: 0 | H10: =F10*G10 -> 0 | J10: I/Oケーブル | K10: 項目14 SSSTに含まれています。 | L10: Z | O10: 40931
B11: 3 | C11: SET | D11: SET | E11: SDP400-30 | F11: 6 | G11: 18596 | H11: =F11*G11 -> 111576 | L11: -
B12: 4 | C12: タイショー | D12: タイショー | E12: SSST-001-2 | F12: 3 | G12: 4000 | H12: =F12*G12 -> 12000 | J12: ロボット取付板（P=130mm） | L12: Y | M12: 40903 | O12: 40931
B13: 4 | C13: タイショー | D13: タイショー | E13: SSST-002 | F13: 3 | G13: 2800 | H13: =F13*G13 -> 8400 | J13: スペーサーブロック | L13: Y | M13: 40903 | O13: 40931
B14: 4 | C14: タイショー | D14: タイショー | E14: SSST-003 | F14: 3 | G14: 1700 | H14: =F14*G14 -> 5100 | J14: L板金 | L14: Y | M14: 40903 | O14: 40931
B15: 4 | C15: タイショー | D15: タイショー | E15: SSST-004 | F15: 3 | G15: 3100 | H15: =F15*G15 -> 9300 | J15: Y軸変換板 | L15: Y | M15: 40903 | O15: 40931
B16: 4 | C16: タイショー | D16: タイショー | E16: SSST-005-21 | F16: 6 | G16: 3500 | H16: =F16*G16 -> 21000 | J16: シリンジホルダ（10cc） | L16: Y | M16: 40903 | O16: 40931
B17: 4 | C17: タイショー | D17: タイショー | E17: SSST-005-22 | F17: 6 | G17: 3300 | H17: =F17*G17 -> 19800 | J17: シリンジガイド（10cc） | L17: Y | M17: 40903 | O17: 40931
B18: 4 | C18: タイショー | D18: タイショー | E18: SSST-007-2 | F18: 6 | G18: 3700 | H18: =F18*G18 -> 22200 | J18: ノズルガイド（TEC-20N) | L18: Y | M18: 40903 | O18: 40931
B19: 4 | C19: タイショー | D19: タイショー | E19: SSST-008-1 | F19: 3 | G19: 4300 | H19: =F19*G19 -> 12900 | J19: 真空発生ユニット取付板 | L19: Y | M19: 40903 | O19: 40931
B20: 5 | C20: ミスミ | D20: ミスミ | E20: - | F20: 0 | G20: 0 | H20: =F20*G20 -> 0 | J20: 精密ノズルスペーサー | K20: 不要 | L20: - | N20: - | O20: - | P20: -
B21: 6 | C21: SMC | D21: 都機工 | E21: SYJ3140-5MZ-M5 | F21: 3 | G21: 5350 | H21: =F21*G21 -> 16050 | J21: 電磁弁 | L21: Z | M21: 40903 | P21: 40921 | Q21: 40919 | R21: 1/13ﾀｲｼｮｰ発送(送No.139598791290)
B22: 7 | C22: SMC | D22: 都機工 | E22: AW10-M5BG | F22: 3 | G22: 3430 | H22: =F22*G22 -> 10290 | J22: レギュレーター | L22: Z | M22: 40903 | P22: 40905 | Q22: 40905
B23: 7 | C23: SMC | D23: 都機工 | E23: MGJ6-5 | F23: 12 | G23: 6000 | H23: =F23*G23 -> 72000 | J23: シリンダ | L23: Z | M23: 40903 | P23: 40905 | Q23: 40905
B24: 7 | C24: SMC | D24: 都機工 | E24: AS1001F-04 | F24: 6 | G24: 770 | H24: =F24*G24 -> 4620 | J24: スピコン | L24: Z | M24: 40903 | P24: 40905 | Q24: 40905
B25: 8 | C25: SET | D25: SET | E25: 1000BSH50-6 | F25: 6 | G25: 495 | H25: =F25*G25 -> 2970 | L25: -
B26: 9 | C26: SET | D26: SET | E26: SH11CP-B | F26: 1 | G26: 705 | H26: =F26*G26 -> 705 | L26: -
B27: 10 | C27: SET | D27: SET | E27: SPN-20 | F27: 8 | G27: 551 | H27: =F27*G27 -> 4408 | L27: -
B28: 11 | C28: タイショー | D28: タイショー | E28: SSST | F28: 3 | G28: 35000 | H28: =F28*G28 -> 105000 | J28: 組立設計工数 | L28: - | M28: 40903 | O28: 40931
B29: 12 | C29: - | D29: - | E29: 特別値引き | H29: =F29*G29 -> 0 | L29: -
B30: 13 | C30: タイショー | D30: タイショー | E30: SSST-0017-2 | F30: 3 | G30: 5600 | H30: =F30*G30 -> 16800 | J30: ワークベース | L30: X | M30: 40903 | O30: 40931
B31: 13 | C31: タイショー | D31: タイショー | E31: SSST-0021-8 | F31: 3 | G31: 19100 | H31: =F31*G31 -> 57300 | J31: ワーク冶具 | L31: X | M31: 40903 | O31: 40931
B32: 13 | C32: タイショー | D32: タイショー | E32: SSST-0022-4 | F32: 12 | G32: 1700 | H32: =F32*G32 -> 20400 | J32: ワーク押さえプレート | L32: X | M32: 40903 | O32: 40931
B33: 13 | C33: タイショー | D33: タイショー | E33: SSST-0025-3(1) | F33: 3 | G33: 2100 | H33: =F33*G33 -> 6300 | J33: サイド板金 | L33: X | M33: 40903 | O33: 40931
B34: 13 | C34: タイショー | D34: タイショー | E34: SSST-0025-3(2) | F34: 3 | G34: 2100 | H34: =F34*G34 -> 6300 | J34: サイド板金 | M34: 40903
B35: 13 | C35: タイショー | D35: タイショー | E35: SSST-0028-1 | F35: 12 | G35: 2100 | H35: =F35*G35 -> 25200 | J35: 角押さえアダプター | L35: X | M35: 40903 | O35: 40931
B36: 13 | C36: タイショー | D36: タイショー | E36: SSST-0029-3 | F36: 3 | G36: 8400 | H36: =F36*G36 -> 25200 | J36: リニアガイドプレート | L36: X | M36: 40903 | O36: 40931
B37: 13 | C37: タイショー | D37: タイショー | E37: SSST-0030-6 | F37: 6 | G37: 800 | H37: =F37*G37 -> 4800 | J37: ワーク押さえプレート | L37: X | M37: 40903 | O37: 40931
B38: 13 | C38: タイショー | D38: タイショー | E38: SSST-0030-7 | F38: 24 | G38: 2400 | H38: =F38*G38 -> 57600 | J38: ワーク押さえプレート | K38: 仕様検討中につき、後日発注 | L38: X | M38: 40904 | O38: 40931
B39: 13 | C39: タイショー | D39: タイショー | E39: SSST-0031-1 | F39: 3 | G39: 9600 | H39: =F39*G39 -> 28800 | J39: エアシリンダ冶具（スライド部） | L39: X | M39: 40903 | O39: 40931
B40: 13 | C40: タイショー | D40: タイショー | E40: SSST-0033-1 | F40: 3 | G40: 1200 | H40: =F40*G40 -> 3600 | J40: フロント保護板金 | L40: X | M40: 40903 | O40: 40931
B41: 13 | C41: タイショー | D41: タイショー | E41: φ2.1 | F41: 12 | G41: 180 | H41: =F41*G41 -> 2160 | J41: ワッシャ追加工 | L41: X | M41: 40903 | O41: 40931
B42: 13 | C42: タイショー | D42: タイショー | E42: M2.5*12 | F42: 24 | G42: 35 | H42: =F42*G42 -> 840 | J42: 六角穴付ボルト | L42: X | M42: 40903 | O42: 40931
B43: 13 | C43: ミスミ | D43: ミスミ | E43: AXSH212-VC-1PD2-2EB-3.0-1AC-2DA-F | F43: 3 | G43: 6840 | H43: 20520 | J43: FAｽｲｯﾁﾎﾞｯｸｽ(ｱｾﾝﾌﾞﾙ) | L43: X | M43: 40898 | N43: ○ | P43: 40905 | Q43: 40914 | R43: 佐藤Ｍ渡し済
B44: 13 | C44: ミスミ | D44: ミスミ | E44: CBSTSR3-5 | F44: 24 | G44: 250 | H44: 6000 | J44: ｺﾞｸﾃｲﾄｳﾎﾞﾙﾄ(CBSTSR) | L44: X | M44: 40898 | N44: ○ | P44: 40905 | Q44: 40905 | R44: 送No.139595353811
B45: 13 | C45: ミスミ | D45: ミスミ | E45: CRKB3-10 | F45: 6 | G45: 78 | H45: 468 | J45: ｼﾞｭｼﾛｰﾚｯﾄﾈｼﾞ (CRKB) | L45: X | M45: 40898 | N45: ○ | P45: 40905 | Q45: 40905 | R45: ↑
B46: 13 | C46: ミスミ | D46: ミスミ | E46: DC-37PF-N | F46: 3 | G46: 676 | H46: 2028 | J46: EMID-SUBｺﾈｸﾀ | L46: X | M46: 40898 | N46: ○ | P46: 40905 | Q46: 40905 | R46: ↑
B47: 13 | C47: ミスミ | D47: ミスミ | E47: DC-C8-J13-F41R | F47: 3 | G47: 547 | H47: 1641 | J47: DSUBﾌｰﾄﾞ､ｱｸｾｻﾘｰ | L47: X | M47: 40898 | N47: ○ | P47: 40905 | Q47: 40905 | R47: ↑
B48: 13 | C48: ミスミ | D48: ミスミ | E48: DE-9SF-N | F48: 6 | G48: 350 | H48: 2100 | J48: EMID-SUBｺﾈｸﾀ | L48: X | M48: 40898 | N48: ○ | P48: 40905 | Q48: 40905 | R48: ↑
B49: 13 | C49: ミスミ | D49: ミスミ | E49: DE-C8-J9-F41R | F49: 6 | G49: 448 | H49: 2688 | J49: DSUBﾌｰﾄﾞ､ｱｸｾｻﾘｰ | L49: X | M49: 40898 | N49: ○ | P49: 40905 | Q49: 40905 | R49: ↑
B50: 13 | C50: ミスミ | D50: ミスミ | E50: KBBS4-8 | F50: 36 | G50: 130 | H50: 4680 | J50: ﾃｲﾄｳｼｮｳｹｲﾎﾞﾙﾄ KBBS | L50: X | M50: 40898 | N50: ○ | P50: 40905 | Q50: 40905 | R50: ↑
B51: 13 | C51: ミスミ | D51: ミスミ | E51: KNCLSS4-6-10 | F51: 24 | G51: 189 | H51: 4536 | J51: ｷﾝｿﾞｸｶﾗｰ (KNCLSS) | L51: X | M51: 40898 | N51: ○ | P51: 40905 | Q51: 40905 | R51: ↑
B52: 13 | C52: ミスミ | D52: ミスミ | E52: MJELL4-M5-B | F52: 9 | G52: 210 | H52: 1890 | J52: ﾜﾝﾀｯﾁﾂｷﾞﾃ(MJELL) | L52: X | M52: 40898 | N52: ○ | P52: 40905 | Q52: 40905 | R52: ↑
B53: 13 | C53: ミスミ | D53: ミスミ | E53: MJELL6-M5-B | F53: 3 | G53: 220 | H53: 660 | J53: ﾜﾝﾀｯﾁﾂｷﾞﾃ(MJELL) | L53: X | M53: 40898 | N53: ○ | P53: 40905 | Q53: 40905 | R53: ↑
B54: 13 | C54: ミスミ | D54: ミスミ | E54: MNCNP4-M3 | F54: 36 | G54: 220 | H54: 7920 | J54: ﾐﾆﾁｭｱﾜﾝﾀｯﾁﾂｷﾞﾃ (MNCNP) | L54: X | M54: 40898 | N54: ○ | P54: 40905 | Q54: 40905 | R54: ↑
... B65: 13 | C65: ミスミ | D65: ミスミ | E65: XYSG25-CR | F65: 3 | G65: 31000 | H65: 93000 | J65: XYｽﾃｰｼﾞ XYSG | L65: X | M65: 40898 | N65: ○ | P65: 40905 | Q65: 40905 | R65: ↑
C66: ﾐｽﾐ | D66: ﾐｽﾐ | E66: DE-9PF-N | F66: 6 | G66: 350 | H66: 2100 | J66: EMID-SUBｺﾈｸﾀ | M66: 40918 | P66: 40919 | Q66: 40919

Sheet 【94857】 クレハ 原価一覧1-24出荷
B2: お客先名 | E2: ㈱クレハ（ニップン） | G2: 合計金額 | J2: =SUM(H:H) -> 68760
B3: 担当営業 | E3: 桑原
B4: 受注番号 | E4: 94857
B5: 希望納期 | E5: 40928
B6: 最終納品 | E6: 40932
B8: 見積り分類 | C8: メーカー | D8: 仕入先 | E8: 品名 / 型式 | F8: 数量 | G8: 単価 | H8: 金額 | I8: 分類合計 | J8: 詳細 | K8: 備考 | L8: 技術分類 | M8: 発注日 | N8: 発注 | O8: 納期 | P8: 入荷予定日 | Q8: 入荷日
B9: 1 | C9: Asymtek | D9: Asymtek | E9: ZDA-1420005 | F9: 2 | H9: =F9*G9 -> 0 | J9: E.STAR SHORT 5cc
B10: 2 | C10: Asymtek | D10: Asymtek | E10: ZDS-1400056 | F10: 2 | H10: =F10*G10 -> 0 | J10: ディスペンスエンジンＨタイプ
B11: 3 | C11: Asymtek | D11: Asymtek | E11: ZDS-1400014 | F11: -2 | H11: =F11*G11 -> 0 | J11: ディスペンスエンジン
B12: 4 | C12: EFD | D12: EFD | E12: 7017798 | F12: -2 | H12: =F12*G12 -> 0 | J12: 5110LL-B 5ccシリンジ
B13: 5 | C13: SET | D13: SET | E13: SH10LL-B | F13: 2 | H13: =F13*G13 -> 0 | J13: 5ccシリンジ
B14: 6 | C14: ミスミ | D14: ミスミ | E14: UJDST4-B | F14: 2 | G14: 220 | H14: =F14*G14 -> 440 | J14: ワンタッチ継手 | K14: 手配済み。 | L14: Z | M14: 40924 | N14: ○ | O14: 40925 | Q14: 40925
B15: 6 | C15: ミスミ | D15: ミスミ | E15: MJCNL6-1-B | F15: 4 | G15: 150 | H15: =F15*G15 -> 600 | J15: ワンタッチ継手 | K15: 手配済み。 | L15: Z | M15: 40924 | N15: ○ | O15: 40925 | Q15: 40925
B16: 6 | C16: ミスミ | D16: ミスミ | E16: SBD-S4-20 | F16: 4 | G16: 320 | H16: =F16*G16 -> 1280 | J16: ダンツキロッカク・ロッカク・パイプスペーサ | K16: 手配済み。 | L16: Z | M16: 40924 | N16: ○ | O16: 40925 | Q16: 40925
B17: 6 | C17: ミスミ | D17: ミスミ | E17: BVHBV6-6 | F17: 2 | G17: 1560 | H17: =F17*G17 -> 3120 | J17: チェンジバルブ | K17: 手配済み。 | L17: Z | M17: 40924 | N17: ○ | O17: 40925 | Q17: 40925
B18: 6 | C18: SMC | D18: 都機工 | E18: AC20A-01E | F18: 2 | G18: 7040 | H18: =F18*G18 -> 14080 | J18: レギュレータ | K18: 都機工 鈴木手配依頼済。注文書発行願います。 | L18: Z | M18: 40924 | N18: ○ | O18: 40928 | P18: 40928 | Q18: 40928
B19: 6 | C19: SMC | D19: 都機工 | E19: Y200T | F19: 2 | G19: 480 | H19: =F19*G19 -> 960 | J19: フィルター | K19: 都機工 鈴木手配依頼済。注文書発行願います。 | L19: Z | M19: 40924 | N19: ○ | O19: 40928 | P19: 40928 | Q19: 40928
B20: 6 | C20: SMC | D20: 都機工 | E20: IR1000-01G-X120 | F20: 2 | G20: 13440 | H20: 26880 | J20: 精密レギュレータ | K20: 都機工 鈴木手配依頼済。注文書発行願います。 | L20: Z | M20: 40924 | N20: ○ | O20: 40928 | P20: 40928 | Q20: 40928
B21: 6 | C21: 遠藤製作所 | D21: 遠藤製作所 | E21: 94857-Z01 | F21: 2 | G21: 3900 | H21: =F21*G21 -> 7800 | J21: ACJ-3 レギュレータ取付板 | K21: SKNP-0001より図番変更。先行依頼済み。 | L21: Z | M21: 40924 | N21: ○ | O21: 40928 | Q21: 40926
B22: 7 | E22: 送料 / 50 | F22: 2 | H22: =F22*G22 -> 0
B23: 8 | C23: Asymtek | D23: Asymtek | E23: ZDA-2710370 | F23: 2 | H23: =F23*G23 -> 0 | J23: ACJ-3 CONTROLLER POWER UP
B24: 9 | C24: 三ツ矢 | D24: 三ツ矢 | E24: MT3003-P67 | F24: 2 | G24: 6800 | H24: =F24*G24 -> 13600 | J24: PJ-Eノズル30G L=3mm | M24: 40924 | P24: 40932 | Q24: 40933
B25: 10 | C25: Asymtek | D25: Asymtek | E25: ZDP-1400200 | F25: 2 | H25: =F25*G25 -> 0 | J25: フルイドボディ
B26: 11 | C26: Asymtek | D26: Asymtek | E26: ZNP-0230060 | F26: 2 | H26: =F26*G26 -> 0 | J26: Ｏリング パープロ IDS6
B27: 12 | C27: Asymtek | D27: Asymtek | E27: ZDP-1400222 | F27: 2 | H27: =F27*G27 -> 0 | J27: シールホルダー
B28: 13 | E28: 995-952 | F28: 2 | H28: =F28*G28 -> 0 | J28: オムニシール 3-7
B29: 14 | E29: ZDP-0100102 | F29: 2 | H29: =F29*G29 -> 0 | J29: プレート
B30: 15 | C30: Asymtek | D30: Asymtek | E30: ZNP-0191215 | F30: 2 | H30: =F30*G30 -> 0 | J30: スプリング
B31: 16 | C31: Asymtek | D31: Asymtek | E31: ZNP-0230100 | F31: 2 | H31: =F31*G31 -> 0 | J31: Ｏリング パープロ IDS10
B32: 17 | C32: Asymtek | D32: Asymtek | E32: ZNP-5390004 | F32: 2 | H32: =F32*G32 -> 0 | J32: ニードルアダプター
B33: 18 | C33: EFD | D33: EFD | E33: 7020903 | F33: 2 | H33: =F33*G33 -> 0 | J33: 72523BP FIT:BARREL to 1/8NPTM ELB BPP
B34: 19 | C34: EFD | D34: EFD | E34: 5ccシリンジアダプター 1.8m / 1000BSH49-6 | F34: 2 | H34: =F34*G34 -> 0 | J34: 5ccシリンジアダプター 1.8m
H35: =F35*G35 -> 0
H37: =F37*G37 -> 0
H38: =F38*G38 -> 0
H39: =F39*G39 -> 0
H40: =F40*G40 -> 0
H41: =F41*G41 -> 0
H42: =F42*G42 -> 0
H43: =F43*G43 -> 0

Sheet 【94974】 アサヒ電子 原価一覧1-25出荷
B2: お客先名 | E2: アサヒ電子 | G2: 合計金額 | J2: =SUM(H:H) -> 732731
B3: 担当営業 | E3: 青木
B4: 受注番号 | E4: 94974
B5: 希望納期 | E5: 40920
B6: 最終納品
B8: 見積り分類 | C8: メーカー | D8: 仕入先 | E8: 品名 / 型式 | F8: 数量 | G8: 単価 | H8: 金額 | I8: 分類合計 | J8: 詳細 | K8: 備考 | L8: 技術分類 | M8: 発注日 | N8: 発注 | O8: 納期 | P8: 入荷予定日 | Q8: 入荷日
B9: 1 | C9: 蛇の目 | D9: 蛇の目 | E9: JR2303N-H | F9: 1 | G9: 546000 | H9: =F9*G9 -> 546000 | J9: ﾄｰﾙﾀｲﾌﾟ内部ｽｲｯﾁ仕様 | K9: 仙台（営）青木依頼分 | M9: 40914 | P9: 40926 | Q9: 40926
B10: 1 | C10: 蛇の目 | D10: 蛇の目 | E10: JR2303N-H追加費用 | F10: 1 | G10: 35000 | H10: =F10*G10 -> 35000 | M10: 40914 | P10: 40926 | Q10: 40926
B11: 1 | C11: 蛇の目 | D11: 蛇の目 | E11: IO-1増設ｹｰﾌﾞﾙ | F11: 1 | G11: 8400 | H11: =F11*G11 -> 8400 | M11: 40914 | P11: 40926 | Q11: 40926
B12: 1 | C12: 蛇の目 | D12: 蛇の目 | E12: 荷造り運賃 | F12: 1 | G12: 10000 | M12: 40914 | P12: 40926 | Q12: 40926
B13: 3 | C13: 蛇の目 | D13: 蛇の目 | E13: JR-TB | H13: =F13*G13 -> 0 | J13: ティーチングペンダント | M13: 在庫使用
B14: 5 | H14: =F14*G14 -> 0
B15: 5 | H15: =F15*G15 -> 0
B16: 6 | C16: 遠藤製作所 | D16: 遠藤製作所 | E16: ﾌﾞﾗｹｯﾄﾍﾞｰｽ/ 94974-X001 | F16: 1 | G16: 9500 | H16: =F16*G16 -> 9500 | M16: 40914 | Q16: 40920
B17: 6 | C17: 遠藤製作所 | D17: 遠藤製作所 | E17: ﾊﾞﾙﾌﾞ受けﾌﾞﾗｹﾄ/ 94974-X002 | F17: 1 | G17: 4500 | H17: =F17*G17 -> 4500 | M17: 40914 | Q17: 40920
B18: 6 | C18: 遠藤製作所 | D18: 遠藤製作所 | E18: ﾊﾞﾙﾌﾞ受け Ａ側/ 94974-X003 | F18: 1 | G18: 10500 | H18: =F18*G18 -> 10500 | M18: 40914 | Q18: 40920
B19: 6 | C19: 遠藤製作所 | D19: 遠藤製作所 | E19: ﾊﾞﾙﾌﾞ受け B側/ 94974-X004 | F19: 1 | G19: 12000 | H19: =F19*G19 -> 12000 | M19: 40914 | Q19: 40920
B20: 7 | H20: =F20*G20 -> 0
B21: 4 | C21: タカチ電機 | D21: 都機工 | E21: FCWS400-150-100KGSS加工組立 | F21: 1 | G21: 26550 | H21: =F21*G21 -> 26550 | J21: フリーサイズケース | K21: 見積書No.499264 | L21: Z | M21: 40914 | P21: 40932 | Q21: 40932
B22: 4 | C22: タカチ電機 | D22: 都機工 | E22: FCSC400-150-1加工組立 | F22: 1 | G22: 7990 | H22: =F22*G22 -> 7990 | J22: フリーサイズケース | K22: 見積書No.499264 | L22: Z | M22: 40914 | P22: 40932 | Q22: 40932
B23: 4 | C23: ミスミ | D23: ミスミ | E23: MRB350 | F23: 1 | G23: 1080 | H23: =F23*G23 -> 1080 | J23: DINレール | L23: Z | M23: 40914 | P23: 40919 | Q23: 40919
B24: 4 | C24: ミスミ | D24: ミスミ | E24: MWS-DS37A-HT37 | F24: 1 | G24: 3350 | H24: =F24*G24 -> 3350 | J24: D-Subコネクタ端子台 | L24: Z | M24: 40914 | P24: 40919 | Q24: 40919
B25: 4 | C25: ミスミ | D25: ミスミ | E25: MWS-DS25A-HT25 | F25: 1 | G25: 2490 | H25: =F25*G25 -> 2490 | J25: D-Subコネクタ端子台 | L25: Z | M25: 40914 | P25: 40919 | Q25: 40919
B26: 4 | C26: ミスミ | D26: ミスミ | E26: ESAW-TCM310-5P | F26: 1 | G26: 3022 | H26: =F26*G26 -> 3022 | J26: コモンブロック端子台 | L26: Z | M26: 40914 | P26: 40919 | Q26: 40919
B27: 4 | C27: ミスミ | D27: ミスミ | E27: NEDJ-PS-SB-37-1.5 | F27: 1 | G27: 5719 | H27: =F27*G27 -> 5719 | J27: D-Subコネクタハーネス | L27: Z | M27: 40914 | P27: 40919 | Q27: 40919
B28: 4 | C28: ミスミ | D28: ミスミ | E28: NEDJ-SS-SB-25-1.5 | F28: 1 | G28: 4293 | H28: =F28*G28 -> 4293 | J28: D-Subコネクタハーネス | L28: Z | M28: 40914 | P28: 40919 | Q28: 40919
B29: 4 | C29: ミスミ | D29: ミスミ | E29: F1.25-M3 | F29: 1 | G29: 460 | H29: =F29*G29 -> 460 | J29: 圧着端子（Y型） | L29: Z | M29: 40914 | P29: 40919 | Q29: 40919
B30: 4 | C30: ミスミ | D30: ミスミ | E30: AXSH212-VC-1PD2-2EB-1.5-1AC-2DA-F | F30: 1 | G30: 6615 | H30: =F30*G30 -> 6615 | J30: 外部ｽｲｯﾁBOX | L30: Z | M30: 40914 | P30: 40919 | Q30: 40919
B31: 6 | C31: 遠藤製作所 | D31: 遠藤製作所 | E31: ﾌﾞﾗｹｯﾄﾍﾞｰｽ/ 94974-X001-1 | F31: 1 | G31: 12000 | H31: =F31*G31 -> 12000 | M31: 40920 | Q31: 40926
B32: 6 | C32: 遠藤製作所 | D32: 遠藤製作所 | E32: ﾌﾞﾗｹﾄﾍﾞｰｽﾛﾝｸﾞ/ 94974-X005 | F32: 1 | G32: 15000 | H32: =F32*G32 -> 15000 | M32: 40920 | Q32: 40926
B33: 6 | C33: 遠藤製作所 | D33: 遠藤製作所 | E33: ﾊﾞﾙﾌﾞ受け Ａ側/ 94974-X006 | F33: 1 | G33: 4200 | H33: =F33*G33 -> 4200 | M33: 40920 | Q33: 40926
B34: 6 | C34: 遠藤製作所 | D34: 遠藤製作所 | E34: ﾊﾞﾙﾌﾞ受け B側/ 94974-X007 | F34: 1 | G34: 5200 | H34: =F34*G34 -> 5200 | M34: 40920 | Q34: 40926
B35: 6 | C35: ミスミ | D35: ミスミ | E35: MS3-15 | F35: 76 | G35: 19 | H35: =F35*G35 -> 1444 | J35: ノックﾋﾟﾝ | M35: 40920 | P35: 40921 | Q35: 40921
B36: 6 | C36: ミスミ | D36: ミスミ | E36: MS3-20 | F36: 24 | G36: 39 | H36: =F36*G36 -> 936 | J36: ノックﾋﾟﾝ | M36: 40920 | P36: 40921 | Q36: 40921
B37: 4 | C37: ミスミ | D37: ミスミ | E37: UL1007-24-BE-305 | F37: 1 | G37: 2060 | H37: =F37*G37 -> 2060 | J37: 単芯電線 | M37: 40920 | P37: 40924 | Q37: 40925
B38: 4 | C38: ミスミ | D38: ミスミ | E38: VTUB3.2-W-10 | F38: 1 | G38: 622 | H38: =F38*G38 -> 622 | J38: ﾏｰｸﾁｭｰﾌﾞ | M38: 40920 | P38: 40921 | Q38: 40921
B39: 1 | C39: 蛇の目 | D39: 蛇の目 | E39: 品番：961053015 | F39: 2 | G39: 1400 | H39: =F39*G39 -> 2800 | J39: Ｚ軸強化ばね(6.3kgf）JR2303N用 | M39: 40921 | P39: 40927 | Q39: 40927
B40: 1 | C40: 蛇の目 | D40: 蛇の目 | E40: 品番：961053015 送料 | F40: 1 | G40: 1000 | H40: =F40*G40 -> 1000 | M40: 40921

Sheet 【95000】 コーセル 原価一覧1-31出荷
B2: お客先名 | E2: コーセル | G2: 合計金額 | J2: =SUM(H:H) -> 701001
B3: 担当営業 | E3: 桑原
B4: 受注番号 | E4: 95000
B5: 希望納期 | E5: 40927
B6: 最終納品
B8: 見積り分類 | C8: メーカー | D8: 仕入先 | E8: 品名 / 型式 | F8: 数量 | G8: 単価 | H8: 金額 | I8: 分類合計 | J8: 詳細 | K8: 備考 | L8: 技術分類 | M8: 発注日 | N8: 発注 | O8: 納期 | P8: 入荷予定日 | Q8: 入荷日
B9: 1 | C9: 蛇の目 | D9: 蛇の目 | E9: JR2403N | F9: 1 | G9: 607000 | H9: 607000 | J9: JR2403N | M9: 40914 | P9: 40931 | Q9: 40931
B10: 2 | C10: 蛇の目 | D10: 蛇の目 | E10: JR-TB | F10: 1 | J10: ティーチングペンダント | M10: 在庫使用
B11: 3 | C11: SET | D11: SET | E11: SV97MS | F11: 1 | J11: スプレーバルブMS
B12: 4 | C12: SET | D12: SET | E12: SVC600 | F12: 1 | J12: スプレーバルブコントローラ
B13: 6 | C13: 機材 | D13: 機材 | E13: 30-10ME4N-C | F13: 1 | J13: テフロン継手φ10 L型 | M13: 在庫使用
B14: 7 | C14: 機材 | D14: 機材 | E14: 30-10MC4N-C | F14: 1 | J14: テフロン継手φ10 ストレート型 | M14: 在庫使用
B15: 8 | C15: 機材 | D15: 機材 | E15: 7014868 | F15: 1 | J15: 2197A異型継手 | M15: 在庫使用
B16: 12 | C16: SET | D16: SET | E16: SH22-0.25-B | F16: 1 | J16: 22G GPニードル
B17: 13 | C17: 機材 | D17: 機材 | E17: PFA10-8 | F17: 1 | J17: φ10テフロンホース | M17: 在庫使用
B18: 9 | C18: 遠藤製作所 | D18: 遠藤製作所 | E18: 95000-Y01 | F18: 1 | G18: 5900 | H18: =F18*G18 -> 5900 | J18: ツール板 | L18: Y | M18: 40914 | Q18: 40926
B19: 9 | C19: 遠藤製作所 | D19: 遠藤製作所 | E19: SS40079 | F19: 1 | G19: 13800 | H19: =F19*G19 -> 13800 | J19: 740,725,780用ホルダ（P=25） | L19: Y | M19: 40914 | Q19: 40926
B20: 11 | C20: 遠藤製作所 | D20: 遠藤製作所 | E20: 95000-Z01 | F20: 1 | G20: 7500 | H20: =F20*G20 -> 7500 | J20: ノズル洗浄カップ | L20: Z | M20: 40914 | Q20: 40926
B21: 11 | C21: 遠藤製作所 | D21: 遠藤製作所 | E21: 95000-Z02 | F21: 1 | G21: 5900 | H21: =F21*G21 -> 5900 | J21: カップ固定板金 | L21: Z | M21: 40914 | Q21: 40926
B22: 11 | C22: 遠藤製作所 | D22: 遠藤製作所 | E22: 95000-Z03 | F22: 1 | G22: 4800 | H22: =F22*G22 -> 4800 | J22: カップ固定ブロック | L22: Z | M22: 40914 | Q22: 40926
B23: 11 | C23: 遠藤製作所 | D23: 遠藤製作所 | E23: 95000-Z04 | F23: 1 | G23: 9000 | H23: =F23*G23 -> 9000 | J23: 端子台取付板 | L23: Z | M23: 40914 | Q23: 40931
B24: 5 | C24: SMC | D24: 都機工 | E24: CDM2L32-250-C73C | F24: 1 | G24: 9460 | H24: =F24*G24 -> 9460 | J24: シリンダー | M24: 40914 | P24: 40924 | Q24: 1/16(1/17大阪発送) | R24: 入荷後大阪（営）桑原さんに送付
B25: 5 | C25: SMC | D25: 都機工 | E25: AS2201F-01-06 | F25: 2 | G25: 880 | H25: =F25*G25 -> 1760 | J25: スピコン | M25: 40914 | P25: 40919 | Q25: 1/11(1/17大阪発送) | R25: 入荷後大阪（営）桑原さんに送付
B26: 5 | C26: SMC | D26: 都機工 | E26: AN103-01 | F26: 2 | G26: 270 | H26: =F26*G26 -> 540 | J26: サイレンサー | M26: 40914 | P26: 40919 | Q26: 1/11(1/17大阪発送) | R26: 入荷後大阪（営）桑原さんに送付
B27: 5 | C27: SMC | D27: 都機工 | E27: VZM450-01-34R | F27: 1 | G27: 7290 | H27: =F27*G27 -> 7290 | J27: 5ポートメカニカルバルブ | M27: 40914 | P27: 40919 | Q27: 1/11(1/17大阪発送) | R27: 入荷後大阪（営）桑原さんに送付
B28: 5 | C28: SMC | D28: 都機工 | E28: KQ2L06-01 | F28: 10 | G28: 192 | H28: =F28*G28 -> 1920 | J28: 継手 | M28: 40914 | P28: 40919 | Q28: 1/11(1/17大阪発送) | R28: 入荷後大阪（営）桑原さんに送付
B29: 11 | C29: SMC | D29: 都機工 | E29: AW20-01BE-R | F29: 1 | G29: 4340 | H29: =F29*G29 -> 4340 | J29: フィルターレギュレータ | L29: Z | M29: 40914 | P29: 40919 | Q29: 40919
B30: 11 | C30: SMC | D30: 都機工 | E30: SYJ514-5MZ-01 | F30: 1 | G30: 4420 | H30: =F30*G30 -> 4420 | J30: 電磁弁 | L30: Z | M30: 40914 | P30: 40919 | Q30: 40919
B31: 11 | C31: アズワン | D31: 都機工 | E31: No.60 | F31: 1 | G31: 2180 | H31: =F31*G31 -> 2180 | J31: ミニカップ | M31: 40914 | P31: 40921 | Q31: 40921
B32: 11 | C32: ミスミ | D32: ミスミ | E32: MRB300 | F32: 1 | G32: 930 | H32: =F32*G32 -> 930 | J32: DINレール | L32: Z | M32: 40914 | P32: 40919 | Q32: 40919
B33: 11 | C33: ミスミ | D33: ミスミ | E33: MWS-DS37A-HT37 | F33: 1 | G33: 3350 | H33: =F33*G33 -> 3350 | J33: D-Subコネクタ端子台 | L33: Z | M33: 40914 | P33: 40919 | Q33: 40919
B34: 11 | C34: ミスミ | D34: ミスミ | E34: ESAW-TCM310-5P | F34: 1 | G34: 3022 | H34: =F34*G34 -> 3022 | J34: コモンブロック端子台 | L34: Z | M34: 40914 | P34: 40919 | Q34: 40919
B35: 11 | C35: ミスミ | D35: ミスミ | E35: NEDJ-PS-SB-37-2 | F35: 1 | G35: 5869 | H35: =F35*G35 -> 5869 | J35: D-Subコネクタハーネス | L35: Z | M35: 40914 | P35: 40919 | Q35: 40919
B36: 11 | C36: ミスミ | D36: ミスミ | E36: NEDJ-P-SB-9-2 | F36: 1 | G36: 1560 | H36: =F36*G36 -> 1560 | J36: D-Subコネクタハーネス | L36: Z | M36: 40914 | P36: 40919 | Q36: 40919
B37: 11 | C37: ミスミ | D37: ミスミ | E37: F1.25-M3 | F37: 1 | G37: 460 | H37: =F37*G37 -> 460 | J37: 圧着端子（Y型） | L37: Z | M37: 40914 | P37: 40919 | Q37: 40919
H38: =F38*G38 -> 0
H39: =F39*G39 -> 0
H40: =F40*G40 -> 0
H41: =F41*G41 -> 0
H42: =F42*G42 -> 0
H43: =F43*G43 -> 0
H44: =F44*G44 -> 0

Sheet 【95034】 東亜電気工業（シャープ多気）1-5出荷
B2: お客先名 | E2: 東亜電気工業 | G2: 合計金額 | J2: =SUM(H:H) -> 303389
B3: 担当営業 | E3: 真保
B4: 受注番号 | E4: 95034 | G4: 備考 | J4: 琶麗出荷品
B5: 希望納期 | E5: -
B6: 最終納品
B8: 見積り分類 | C8: メーカー | D8: 仕入先 | E8: 品名 / 型式 | F8: 数量 | G8: 単価 | H8: 金額 | I8: 分類合計 | J8: 詳細 | K8: 備考 | L8: 技術分類 | M8: 発注日 | N8: 発注 | O8: 納期 | P8: 入荷予定日 | Q8: 入荷日
B9: 1 | C9: 蛇の目 | D9: 蛇の目 | E9: JRV2203 | F9: 11 | H9: =F9*G9 -> 0 | L9: - | M9: 在庫使用
B10: 2 | C10: - | D10: - | E10: I/Oケーブル | F10: 11 | G10: 0 | H10: =F10*G10 -> 0 | J10: I/Oケーブル | L10: -
B11: 3 | C11: 蛇の目 | D11: 蛇の目 | E11: JRV-TB | F11: 2 | H11: =F11*G11 -> 0 | J11: JRV-TB | L11: - | M11: 在庫使用
B12: 4 | C12: 蛇の目 | D12: 蛇の目 | E12: PC編集ソフト | F12: 1 | J12: PC編集ソフト | L12: - | M12: 在庫使用
B13: 5 | C13: ミスミ | D13: ミスミ | E13: PNUIC-REX-USB60F-R | F13: 1 | G13: 5200 | H13: 5200 | J13: PC通信ケーブル | L13: - | M13: 40904 | N13: ○ | P13: 40914 | Q13: 1/6(佐藤Ｍ渡済)
B14: 5 | C14: ミスミ | D14: ミスミ | E14: DGC-9SS | F14: 1 | G14: 203 | H14: 203 | J14: PC通信ケーブル | L14: - | M14: 40904 | N14: ○ | P14: 40914 | Q14: 1/6(佐藤Ｍ渡済)
B15: 6 | C15: SET | D15: SET | E15: SDP400-30 | F15: 22 | L15: -
B16: 7 | C16: SET | D16: SET | E16: 1000BSH50-6 | F16: 22 | L16: -
B17: 8 | C17: SET | D17: SET | E17: SH11CP-B | F17: 11 | L17: -
B18: 9 | C18: SET | D18: SET | E18: SPN-20 | F18: 22 | L18: -
B19: 10 | C19: - | D19: - | E19: 組立工賃 | F19: 11 | L19: -
B20: 11 | C20: - | D20: - | E20: 送料 | F20: 11 | L20: -
B21: その他 | C21: SMC | D21: 都機工 | E21: MGJ6-5 | F21: 44 | G21: 5460 | H21: 240240 | M21: 40903 | P21: 40914 | Q21: ..1/...5
B22: その他 | C22: ﾐｽﾐ | D22: ﾐｽﾐ | E22: CBSTSR3-5 | F22: 100 | G22: 150 | H22: 15000 | M22: 40903 | P22: 40905 | Q22: 40905
B23: その他 | C23: ﾐｽﾐ | D23: ﾐｽﾐ | E23: KNCLSS4-6-10 | F23: 90 | G23: 178 | H23: 16020 | M23: 40903 | P23: 40905 | Q23: 40905
B24: その他 | C24: ﾐｽﾐ | D24: ﾐｽﾐ | E24: SHCDG4-16 | F24: 50 | G24: 165 | H24: 8250 | M24: 40903 | P24: 40905 | Q24: 40905
B25: その他 | C25: ﾐｽﾐ | D25: ﾐｽﾐ | E25: DE-9PF-N | F25: 22 | G25: 350 | H25: 7700 | M25: 40904 | P25: 40914 | Q25: 1/6(佐藤Ｍ渡済)
B26: その他 | C26: ﾐｽﾐ | D26: ﾐｽﾐ | E26: DE-C8-J9-F41R | F26: 22 | G26: 448 | H26: 9856 | M26: 40904 | P26: 40914 | Q26: 1/6(佐藤Ｍ渡済)
B27: その他 | C27: 秋月電子 | D27: 秋月電子 | E27: D-SUBコネクタ（オス） | F27: 23 | G27: 40 | H27: =F27*G27 -> 920 | M27: 直接購入 | N27: - | O27: - | P27: - | Q27: -

Sheet 【95126】 東亜電気工業（シャープ多気）1-16出荷
B2: お客先名 | E2: 東亜電気工業 | G2: 合計金額 | J2: =SUM(H:H) -> 23436
B3: 担当営業 | E3: 真保
B4: 受注番号 | E4: 95126 | G4: 備考 | J4: 琶麗出荷品
B5: 希望納期 | E5: -
B6: 最終納品
B8: 見積り分類 | C8: メーカー | D8: 仕入先 | E8: 品名 / 型式 | F8: 数量 | G8: 単価 | H8: 金額 | I8: 分類合計 | J8: 詳細 | K8: 備考 | L8: 技術分類 | M8: 発注日 | N8: 発注 | O8: 納期 | P8: 入荷予定日 | Q8: 入荷日
B9: 1 | C9: 蛇の目 | D9: 蛇の目 | E9: JRV2203 | F9: 1 | L9: - | M9: 在庫使用
B10: 2 | C10: - | D10: - | E10: I/Oケーブル | F10: 1 | J10: I/Oケーブル | L10: -
B11: 3 | C11: SET | D11: SET | E11: SDP400-30 | F11: 2
B12: 4 | C12: SET | D12: SET | E12: 1000BSH50-6 | F12: 2
B13: 5 | C13: SET | D13: SET | E13: SH11CP-B | F13: 1
B14: 6 | C14: SET | D14: SET | E14: SPN-20 | F14: 2
B15: 7 | C15: - | D15: - | E15: 組立工賃 | F15: 1 | L15: -
B16: 8 | C16: - | D16: - | E16: 送料 | F16: 1 | L16: -
B17: その他 | C17: SMC | D17: 都機工 | E17: MGJ6-5 | F17: 4 | G17: 5460 | H17: =F17*G17 -> 21840 | M17: 40913 | P17: 40919 | Q17: 40919 | R17: 1/13ﾀｲｼｮｰ発送(送No.139598791290)
B18: その他 | C18: ミスミ | D18: ミスミ | E18: DE-9PF-N | F18: 2 | G18: 350 | H18: =F18*G18 -> 700 | M18: 40913 | P18: 40918 | Q18: 40918
B19: その他 | C19: ミスミ | D19: ミスミ | E19: DE-C8-J9-F41R | F19: 2 | G19: 448 | H19: =F19*G19 -> 896 | M19: 40913 | P19: 40918 | Q19: 40918

Sheet 【95200】 ケイマック 原価一覧1-30出荷
B2: お客先名 | E2: ケイ・マック | G2: 合計金額 | J2: =SUM(H:H) -> 228200
B3: 担当営業 | E3: 桑原
B4: 受注番号 | E4: 95200
B5: 希望納期 | E5: 40928
B6: 最終納品 | E6: 40934
B8: 見積り分類 | C8: メーカー | D8: 仕入先 | E8: 品名 / 型式 | F8: 数量 | G8: 単価 | H8: 金額 | I8: 分類合計 | J8: 詳細 | K8: 備考 | L8: 技術分類 | M8: 発注日 | N8: 発注 | O8: 納期 | P8: 入荷予定日 | Q8: 入荷日
B9: 3 | C9: 遠藤製作所 | D9: 遠藤製作所 | E9: 95200-Y01 | F9: 2 | G9: 7500 | H9: =F9*G9 -> 15000 | J9: ロボット取付板（リニアボール3D用） | L9: Y | M9: 40920 | P9: 40933
B10: 3 | C10: 遠藤製作所 | D10: 遠藤製作所 | E10: 94301-Y02 | F10: 2 | G10: 3800 | H10: =F10*G10 -> 7600 | J10: ステージ固定板（リニアボール3D用） | L10: Y | M10: 40920 | P10: 40933
B11: 3 | C11: 遠藤製作所 | D11: 遠藤製作所 | E11: 94301-Y03 | F11: 2 | G11: 2500 | H11: =F11*G11 -> 5000 | J11: シリンジ+バルブ取付上板（リニアボール3D用） | L11: Y | M11: 40920 | P11: 40933
B12: 3 | C12: 遠藤製作所 | D12: 遠藤製作所 | E12: 95200-Y04 | F12: 2 | G12: 2400 | H12: =F12*G12 -> 4800 | J12: シリンジ+バルブ取付下板（リニアボール3D用） | L12: Y | M12: 40920 | P12: 40933
B13: 3 | C13: 遠藤製作所 | D13: 遠藤製作所 | E13: SS40705 | F13: 2 | G13: 22200 | H13: =F13*G13 -> 44400 | J13: シリンジアダプタ5CC-55CC （POMアダプタ付） | L13: Y | M13: 40920 | P13: 40933
B14: 3 | C14: ミスミ | D14: ミスミ | E14: XYZSSG40-CU | F14: 2 | G14: 54000 | H14: =F14*G14 -> 108000 | J14: XYZステージ（リニアボール） | L14: Y | M14: 40919 | P14: 40926 | Q14: 40926
B15: 4,5 | C15: ミスミ | D15: ミスミ | E15: %WRFH-4050-120110-15 | F15: 2 | G15: 21700 | H15: =F15*G15 -> 43400 | J15: 特注ハーネス | L15: Z | M15: 40919 | P15: 40933 | Q15: 40933
B16: 1 | C16: 蛇の目 | D16: 蛇の目 | E16: JR2203-SET03 | F16: 2 | H16: =F16*G16 -> 0 | J16: 2203N | M16: 在庫使用
B17: 2 | C17: 蛇の目 | D17: 蛇の目 | E17: JR-TB | F17: 2 | H17: =F17*G17 -> 0 | J17: ティーチングボックス | M17: 在庫使用
B18: 6 | C18: SET | D18: SET | E18: SDP300 | F18: 2 | H18: =F18*G18 -> 0 | J18: ディスペンサ
B19: 7 | C19: SET | D19: SET | E19: SH13CP-B | F19: 2 | H19: =F19*G19 -> 0 | J19: 55ccシリンジ/ピストン
B20: 8 | C20: SET | D20: SET | E20: 1000BSH52 | F20: 2 | H20: =F20*G20 -> 0 | J20: 30/55ccシリンジアダプタ
B21: 9 | E21: 搬入調整費 | F21: 2 | H21: =F21*G21 -> 0
H22: =F22*G22 -> 0

Sheet 【95446】キヤノン電子 原価一覧1-31出荷
B2: お客先名 | E2: キヤノン電子 | G2: 合計金額 | J2: =SUM(H:H) -> 2355982
B3: 担当営業 | E3: 勝田
B4: 受注番号 | E4: 95446
B5: 希望納期 | E5: 40933
B6: 最終納品 | E6: 40938
B8: 見積り分類 | C8: メーカー | D8: 仕入先 | E8: 品名 / 型式 | F8: 数量 | G8: 単価 | H8: 金額 | I8: 分類合計 | J8: 詳細 | K8: 備考 | L8: 技術分類 | M8: 発注日 | N8: 発注 | O8: 納期 | P8: 入荷予定日 | Q8: 入荷日
B9: 1 | C9: 蛇の目 | D9: 蛇の目 | E9: JR2203NH | F9: 6 | G9: 305000 | H9: =F9*G9 -> 1830000 | M9: 40925 | P9: 40928 | Q9: 40928
B10: 1 | C10: 蛇の目 | D10: 蛇の目 | E10: 荷造り運賃 | F10: 6 | G10: 10000 | H10: =F10*G10 -> 60000 | M10: 40925
B11: 3 | C11: 蛇の目 | D11: 蛇の目 | E11: JR-TB | F11: 1 | H11: =F11*G11 -> 0 | K11: 在庫品 | M11: 在庫使用
H13: =F13*G13 -> 0
B14: 4 | C14: Asymtek | D14: Asymtek | E14: ZDA-1420010 | F14: 6 | H14: =F14*G14 -> 0 | J14: e-starディスペンスヘッド（10cc）
B15: 5 | C15: Asymtek | D15: Asymtek | E15: ZDS-1420021 | F15: -6 | H15: =F15*G15 -> 0 | J15: アキュバルブキット（ショート）
B16: 6 | C16: Asymtek | D16: Asymtek | E16: ZDS-1450201 | F16: 6 | H16: =F16*G16 -> 0 | J16: コニカルバルブ
B17: 7 | C17: Asymtek | D17: Asymtek | E17: ZDA-2710370 | F17: 6 | H17: =F17*G17 -> 0 | J17: ACJ-3 CONTROLLER POWER UP（0.1Ω仕様）
B18: 8 | C18: 三ツ矢 | D18: 三ツ矢 | E18: MT-2701-P67 | F18: 12 | G18: 5800 | H18: =F18*G18 -> 69600 | J18: PJノズル27G L-1 | M18: 40925 | P18: 40933 | Q18: 40933
B19: 9 | C19: アズワン | D19: 都機工 | E19: HS-50E-B | F19: 6 | G19: 19800 | H19: =F19*G19 -> 118800 | J19: シリンジ撹拌システム | K19: 型式変更 | M19: 40925
B20: 10 | C20: SMC | D20: 都機工 | E20: IR1000-01BG | F20: 6 | G20: 6613 | H20: =F20*G20 -> 39678 | J20: レギュレータ | M20: 40925 | P20: 40931 | Q20: 40933
B21: 13 | C21: ミスミ | D21: ミスミ | E21: HXCW12-8-2 | F21: 18 | G21: 490 | H21: =F21*G21 -> 8820 | J21: マグネットリングタイプ | M21: 40925 | P21: 40931 | Q21: 40931
B22: 14 | C22: SET | D22: SET | E22: SH11LL-B | F22: 3 | H22: =F22*G22 -> 0 | J22: 10ｃｃシリンジ
B23: 15 | E23: 7017976 | F23: 1 | H23: =F23*G23 -> 0 | J23: 5113-B
B24: 16 | C24: SMC | D24: 都機工 | E24: KQ2H04-01S | F24: 12 | G24: 128 | H24: =F24*G24 -> 1536 | J24: 継手 | M24: 40925 | P24: 40931 | Q24: 40933
H25: =F25*G25 -> 0
H26: =F26*G26 -> 0
B27: 10 | C27: ミスミ | D27: ミスミ | E27: SETGS12-60-SC10-M5-N5 | F27: 24 | G27: 910 | H27: =F27*G27 -> 21840 | J27: 円形支柱 | L27: Y | M27: 40925 | P27: 40931 | Q27: 40931
B28: 10 | C28: ミスミ | D28: ミスミ | E28: SLSBWF7-24 | F28: 24 | G28: 500 | H28: =F28*G28 -> 12000 | J28: 六角支柱 | L28: Y | M28: 40925 | P28: 40931 | Q28: 40931
B29: 10 | C29: ミスミ | D29: ミスミ | E29: @ECHN-20100219-00022 | F29: 6 | G29: 1933 | H29: =F29*G29 -> 11598 | J29: 特注ハーネス | K29: 購入依頼書にて、在庫品として発注済 | L29: Z | M29: 技術在庫 | N29: ○ | P29: 40935
B30: 10 | C30: アズワン | D30: 都機工 | E30: No.5 | F30: 1 | G30: 910 | H30: =F30*G30 -> 910 | J30: ミニカップ | L30: Z | M30: 40925 | P30: 40931 | Q30: 40933
H32: =F32*G32 -> 0
B33: 10 | C33: 遠藤製作所 | D33: 遠藤製作所 | E33: SS40635 | F33: 6 | G33: 6200 | H33: =F33*G33 -> 37200 | J33: ツール取付板 | L33: Y | M33: 40925 | Q33: 40934
B34: 10 | C34: 遠藤製作所 | D34: 遠藤製作所 | E34: SS3193 | F34: 6 | G34: 9800 | H34: =F34*G34 -> 58800 | J34: ベース板 | L34: X | M34: 40925 | Q34: 40934
B35: 10 | C35: 遠藤製作所 | D35: 遠藤製作所 | E35: SS3194 | F35: 6 | G35: 7200 | H35: =F35*G35 -> 43200 | J35: スターラ台 | L35: Z | M35: 40925 | Q35: 40934
B36: 10 | C36: 遠藤製作所 | D36: 遠藤製作所 | E36: SS40636 | F36: 6 | G36: 2800 | H36: =F36*G36 -> 16800 | J36: 捨て打ちベース板 | L36: Z | M36: 40925 | Q36: 40934
B37: 10 | C37: 遠藤製作所 | D37: 遠藤製作所 | E37: SS40637 | F37: 6 | G37: 4200 | H37: =F37*G37 -> 25200 | J37: カップ押え | L37: Z | M37: 40925 | Q37: 40934
H38: =F38*G38 -> 0
H39: =F39*G39 -> 0
H40: =F40*G40 -> 0
H41: =F41*G41 -> 0
H42: =F42*G42 -> 0
H43: =F43*G43 -> 0
H44: =F44*G44 -> 0

Sheet 【95600】  (有)仲田屋　原価一覧1-25出荷
B2: お客先名 | E2: (有)仲田屋 | G2: 合計金額 | J2: =SUM(H:H) -> 193000
B3: 担当営業 | E3: 青木
B4: 受注番号 | E4: 95600
B5: 希望納期 | E5: 40932
B6: 最終納品
B8: 見積り分類 | C8: メーカー | D8: 仕入先 | E8: 品名 / 型式 | F8: 数量 | G8: 単価 | H8: 金額 | I8: 分類合計 | J8: 詳細 | K8: 備考 | L8: 技術分類 | M8: 発注日 | N8: 発注 | O8: 納期 | P8: 入荷予定日 | Q8: 入荷日
B9: 1 | C9: SET | D9: SET | E9: SV３５ＨＦ | F9: 1 | H9: =F9*G9 -> 0 | J9: ﾊｲﾌﾛｰﾋﾟｽﾄﾝﾊﾞﾙﾌﾞ
B10: 2 | D10: ﾘｷｯﾄﾞｼｽﾃﾑ | E10: SVF-2035 | F10: 1 | G10: 112000 | H10: 112000 | J10: ｽﾃﾝﾚｽﾍﾞｯｾﾙ(内容器11.8リットル） | M10: 40920 | P10: 40935 | Q10: 40928
B11: 3 | D11: ﾘｷｯﾄﾞｼｽﾃﾑ | E11: ＡＲＧ－0.7Ｍ | F11: 1 | G11: 5950 | H11: 5950 | J11: ﾚｷﾞｭﾚｰﾀ-(高圧） | M11: 40920 | P11: 40935 | Q11: 40928
B12: 4 | D12: ﾘｷｯﾄﾞｼｽﾃﾑ | E12: SRV-0.6MS | F12: 1 | G12: 9600 | H12: 9600 | J12: SUSﾘﾘｰﾌ弁 | M12: 40920 | P12: 40935 | Q12: 40928
B13: 5 | D13: ﾘｷｯﾄﾞｼｽﾃﾑ | E13: 5 | F13: 1 | G13: 9300 | H13: 9300 | J13: φ１２ｻｸｼｮﾝﾊﾟｲﾌﾟ・継ぎ手 | M13: 40920 | P13: 40935 | Q13: 40928
B14: 6 | D14: ﾘｷｯﾄﾞｼｽﾃﾑ | E14: 5 | F14: 1 | G14: 28000 | H14: 28000 | J14: φ173.5ﾌｫﾛｰﾌﾟﾚｰﾄ | M14: 40920 | P14: 40935 | Q14: 40928
B15: 7 | C15: SET | D15: SET | E15: SDP300 | F15: 1 | H15: =+G15*F15 -> 0 | J15: ﾃﾞｨｽﾍﾟﾝｻ
B16: 8 | C16: 機材 | D16: 機材 | E16: PFA12-10 | F16: 1 | H16: =+G16*F16 -> 0 | J16: φ12mmﾃﾌﾛﾝﾎｰｽ 3m | M16: 在庫使用
B17: 9 | C17: 遠藤製作所 | D17: 遠藤製作所 | E17: SV35-HF用継ぎ手（ｾﾒﾀﾞｲﾝ） | F17: 2 | G17: 9000 | H17: 18000 | J17: ﾉｽﾞﾙｱﾀﾞﾌﾟﾀｰ（POM材使用） | M17: 40931 | Q17: 40931
B18: 10 | D18: 日本ｽｳｪ-ｼﾞﾛｯｸ | E18: SS-12M0-2-4 | F18: 1 | G18: 2630 | H18: 2630 | J18: おすｴﾙﾎﾞｰφ12×NPT1/4 ＃SS12-E | M18: 40931 | P18: 40932 | Q18: 40932
B19: 11 | E19: 1 | F19: 1 | H19: =+G19*F19 -> 0 | J19: 出精値引き
B20: 12 | E20: 1 | F20: 1 | H20: =+G20*F20 -> 0 | J20: 特別値引き
B30: 15 | E30: 調整費
B31: 16 | E31: 諸経費
B32: 17 | E32: 特別値引き
B33: 1 | C33: ﾘｷﾂﾄ | D33: ﾘｷｯﾄ | E33: 5 | F33: 1 | G33: 7000 | H33: 7000 | J33: φ17,.φ14ﾊｰﾌﾕﾆｵﾝ,pt3/8ｿｹｯﾄ | M33: 40928 | P33: 40928 | Q33: 40928
B34: 10 | C34: ﾐｽﾐ | D34: ﾐｽﾐ | E34: FWRBN-D30-V22-T4 | F34: 2 | G34: 260 | H34: 520 | J34: ゴムワッシャ | M34: 40931 | P34: 40938 | Q34: 40938

Sheet 【94615】 NDK 原価一覧
B2: お客先名 | E2: NDK | G2: 合計金額 | J2: =SUM(H:H) -> 7954380
B3: 担当営業 | E3: 青木
B4: 受注番号 | E4: 94615
B5: 希望納期 | E5: 40954
B6: 最終納品
B8: 見積り分類 | C8: メーカー | D8: 仕入先 | E8: 品名 / 型式 | F8: 数量 | G8: 単価 | H8: 金額 | I8: 分類合計 | J8: 詳細 | K8: 備考 | L8: 技術分類 | M8: 発注日 | N8: 発注 | O8: 納期 | P8: 入荷予定日 | Q8: 入荷日
B9: 1 | C9: Asymtek | D9: Asymtek | E9: ZDA-1420510 | F9: 3 | H9: =F9*G9 -> 0
B10: 2 | C10: Asymtek | D10: Asymtek | E10: ZDA-2710370 | F10: 3 | H10: =F10*G10 -> 0
B11: 3 | C11: Asymtek | D11: Asymtek | E11: ZDA-2410321 | F11: 3 | H11: =F11*G11 -> 0
B12: 4 | C12: Asymtek | D12: Asymtek | E12: MT-30005-P67 | F12: 3 | H12: =F12*G12 -> 0
B13: 5 | C13: 蛇の目 | D13: 蛇の目 | E13: JR2203NH | F13: 3 | G13: 360000 | H13: =F13*G13 -> 1080000 | K13: 14307 | M13: 40892 | N13: ○ | O13: ﾀﾞｲﾔ直送
B14: 5 | C14: 蛇の目 | D14: 蛇の目 | E14: 荷造り運賃 | F14: 3 | G14: 10000 | H14: =F14*G14 -> 30000 | K14: 14307 | M14: 40892 | N14: ○
B15: 6 | C15: 蛇の目 | D15: 蛇の目 | E15: COM増設 | F15: 3 | G15: 20000 | H15: =F15*G15 -> 60000 | K15: 14307 | M15: 40892 | N15: ○ | O15: ﾀﾞｲﾔ直送
B16: 7 | C16: 蛇の目 | D16: 蛇の目 | E16: JR-TB | F16: 3 | G16: 38000 | H16: =F16*G16 -> 114000 | M16: 在庫使用 | N16: ×
B17: 8 | C17: パナソニック | D17: 蛇の目 | E17: A110 | F17: 3 | G17: 155400 | H17: =F17*G17 -> 466200 | J17: ANMA110 | K17: 14308 | L17: Z | M17: 40892 | N17: ○ | O17: ﾀﾞｲﾔ直送
B18: 8 | C18: パナソニック | D18: 蛇の目 | E18: RS232C | F18: 3 | G18: 12000 | H18: =F18*G18 -> 36000 | J18: 960536106 | K18: 14308 | L18: Z | M18: 40892 | N18: ○ | O18: ﾀﾞｲﾔ直送
B19: 8 | C19: パナソニック | D19: 蛇の目 | E19: 送料 | F19: 3 | G19: 1000 | H19: =F19*G19 -> 3000 | J19: - | K19: 14308 | L19: Z | M19: 40892 | N19: ○
B20: 9 | C20: パナソニック | D20: 蛇の目 | E20: CSマウントカメラ | F20: 3 | G20: 54600 | H20: =F20*G20 -> 163800 | J20: ANM832 | K20: 14308 | L20: Z | M20: 40892 | N20: ○ | O20: ﾀﾞｲﾔ直送
B21: 10 | C21: パナソニック | D21: 蛇の目 | E21: 操作キーパット | F21: 3 | G21: 7900 | H21: =F21*G21 -> 23700 | J21: ANM85202 | K21: 14308 | L21: Z | M21: 40892 | N21: ○ | O21: ﾀﾞｲﾔ直送
B22: 11 | C22: パナソニック | D22: 松下制御テクノ | E22: レンズ | F22: 3 | G22: 23000 | H22: =F22*G22 -> 69000 | J22: ANB846NL | K22: 14305 | L22: Z | M22: 40892 | N22: ○ | P22: 40919 | Q22: 40919
B23: 12 | C23: オプトアート | D23: 都機工 | E23: リアコンバーターレンズ | F23: 3 | G23: 10800 | H23: =F23*G23 -> 32400 | J23: TVR02 | K23: 14306 | L23: Z | M23: 40892 | N23: ○ | O23: 40928 | P23: 2011/12/28(残１ヶ) | Q23: 12/26 2ヶ 12/28 1ヶ
B24: 12 | C24: オプトアート | D24: 都機工 | E24: 送料 | F24: 3 | G24: 1000 | H24: =F24*G24 -> 3000 | J24: - | K24: 14306 | L24: Z | M24: 40892 | N24: ○
B25: 12 | C25: VSテクノロジー | D25: VSテクノロジー | E25: 中間リング | F25: 6 | G25: 1380 | H25: =F25*G25 -> 8280 | J25: SV-EXR10 | K25: 14304 | L25: Z | M25: 40892 | N25: ○ | P25: 40897 | Q25: 40897
B26: 13 | C26: CCS | D26: CCS | E26: LED安定照明器 | F26: 3 | G26: 44000 | H26: =F26*G26 -> 132000 | J26: LDR2-32RD | K26: 14303 | L26: Z | M26: 40892 | N26: ○ | P26: 40928
B27: 13 | C27: CCS | D27: CCS | E27: コントローラー | F27: 3 | G27: 13600 | H27: =F27*G27 -> 40800 | J27: PSB-512VL | K27: 14303 | L27: Z | M27: 40892 | N27: ○ | P27: 40928
B28: 13 | C28: CCS | D28: CCS | E28: ケーブル | F28: 3 | G28: 2400 | H28: =F28*G28 -> 7200 | J28: CB-2 | K28: 14303 | L28: Z | M28: 40892 | N28: ○ | P28: 40928
B29: 14 | C29: オジックとダイア | D29: オジックとダイア | E29: 搬送及び制御機構 | F29: 3 | G29: 1895000 | H29: =F29*G29 -> 5685000 | J29: 搬送装置 | K29: 14264 | M29: 40892 | N29: ○ | P29: 2月中旬
B30: 15 | E30: 調整費 | F30: 3 | H30: =F30*G30 -> 0
B31: 16 | E31: 諸経費 | F31: 3 | H31: =F31*G31 -> 0
B32: 17 | E32: 特別値引き | F32: 3

Sheet 12.01.05 【95113】 スエヒロ通商 原価一覧2-7
B2: お客先名 | E2: スエヒロ通商㈱ | G2: 合計金額 | J2: =SUM(H:H) -> 35792
B3: 担当営業 | E3: 青木
B4: 受注番号 | E4: 95113
B5: 希望納期 | E5: 40927
B6: 最終納品
B8: 見積り分類 | C8: メーカー | D8: 仕入先 | E8: 品名 / 型式 | F8: 数量 | G8: 単価 | H8: 金額 | I8: 分類合計 | J8: 詳細 | K8: 備考 | L8: 技術分類 | M8: 発注日 | N8: 発注 | O8: 納期 | P8: 入荷予定日 | Q8: 入荷日
B9: 1 | C9: SET | D9: SET | E9: SV97MS | F9: 2 | J9: スプレーバルブMS
B10: 2 | C10: SET | D10: SET | E10: SS-6MO-2-2 | F10: 2 | J10: おすｴﾙﾎﾞｰ φ6×NPT 1/8 | P10: 40931
B11: 3 | C11: SET | D11: SET | E11: SVC600 | F11: 2 | J11: スプレーバルブコントローラ
B12: 4 | C12: 機材 | D12: 機材 | E12: 200F755 | F12: 2 | J12: ﾌｨﾙﾀｰ/REG 5MICRON | M12: 在庫使用
B13: 5 | C13: 機材 | D13: 機材 | E13: KQ2H06-02S | F13: 4 | J13: 継手ﾊｰﾌﾕﾆｵﾝ φ6× 1/4PT | M13: 在庫使用
B14: 6 | C14: 機材 | D14: 機材 | E14: PFA6-4 | F14: 1 | J14: φ6mmﾃﾌﾛﾝﾎｰｽ ※3ｍ×2本 (TOTAL 6m） | M14: 在庫使用
B15: 7 | C15: 機材 | D15: 機材 | E15: 5 | F15: 2 | J15: SV0830:SVF-0197-STA ﾀﾝｸ | M15: 在庫使用
B16: 8 | C16: SET | D16: SET | E16: SH30-B | F16: 2 | J16: 30G GPﾆｰﾄﾞﾙﾉｽﾞﾙ12.7mm(ﾗﾍﾞﾝﾀﾞｰ）50入り
B18: 9 | C18: 遠藤製作所 | D18: 遠藤製作所 | E18: 95113-X001 | F18: 1 | G18: 8900 | H18: =F18*G18 -> 8900 | J18: SV97用受けブラケット | L18: Y | M18: 40921 | Q18: 40933
B19: 9 | C19: 遠藤製作所 | D19: 遠藤製作所 | E19: 95113-X002 | F19: 2 | G19: 5800 | H19: =F19*G19 -> 11600 | J19: SV97ﾊﾞﾙﾌﾞ受け Ａ | L19: Y | M19: 40921 | Q19: 40926
B20: 9 | C20: 遠藤製作所 | D20: 遠藤製作所 | E20: 95113-X003 | F20: 2 | G20: 6200 | H20: =F20*G20 -> 12400 | J20: SV97ﾊﾞﾙﾌﾞ受け B | L20: Y | M20: 40921 | Q20: 40926
B21: 9 | C21: ミスミ | D21: ミスミ | E21: MS3-20 | F21: 6 | G21: 39 | H21: =F21*G21 -> 234 | J21: ﾉｯｸﾋﾟﾝφ3-20mm | L21: Y | M21: 40921 | P21: 40924 | Q21: 40924
B22: 9 | C22: ミスミ | D22: ミスミ | E22: MS3-15 | F22: 42 | G22: 39 | H22: =F22*G22 -> 1638 | J22: ﾉｯｸﾋﾟﾝφ3-15mm | L22: Y | M22: 40921 | P22: 40924 | Q22: 40924
B23: 9 | C23: ミスミ | D23: ミスミ | E23: SCB-4-40 | F23: 4 | G23: 95 | H23: =F23*G23 -> 380 | J23: 六角穴付ﾎﾞﾙﾄ(M4×40mm） | L23: Y | M23: 40921 | P23: 40924 | Q23: 40924
B24: 9 | C24: ミスミ | D24: ミスミ | E24: SCB-4-14 | F24: 8 | G24: 80 | H24: =F24*G24 -> 640 | J24: 六角穴付ﾎﾞﾙﾄ(M4×14mm） | L24: Y | M24: 40921 | P24: 40924 | Q24: 40924
H25: =F25*G25 -> 0
H26: =F26*G26 -> 0
H27: =F27*G27 -> 0
H28: =F28*G28 -> 0
H29: =F29*G29 -> 0
H30: =F30*G30 -> 0
H31: =F31*G31 -> 0
H32: =F32*G32 -> 0
H33: =F33*G33 -> 0
H34: =F34*G34 -> 0
H35: =F35*G35 -> 0
H36: =F36*G36 -> 0
... H44: =F44*G44 -> 0

Sheet 12.01.24 【95331】住友電装 原価一覧2-4出荷
B2: お客先名 | E2: 住友電装 | G2: 合計金額 | J2: =SUM(H:H) -> 74794
B3: 担当営業 | E3: 真保
B4: 受注番号 | E4: 95331
B5: 希望納期 | E5: 40939
B6: 最終納品 | E6: 40943
B8: 見積り分類 | C8: メーカー | D8: 仕入先 | E8: 品名 / 型式 | F8: 数量 | G8: 単価 | H8: 金額 | I8: 分類合計 | J8: 詳細 | K8: 備考 | L8: 技術分類 | M8: 発注日 | N8: 発注 | O8: 納期 | P8: 入荷予定日 | Q8: 入荷日
B9: 1 | C9: ミスミ | D9: ミスミ | E9: XYZEG40 | F9: 1 | G9: 33800 | H9: =F9*G9 -> 33800 | J9: 3軸ステージ | K9: 見積No：WOSM0039798A | L9: Y | M9: 40932 | P9: 40938 | Q9: 40938
B10: 1 | C10: ミスミ | D10: ミスミ | E10: SLSBWRK7-25 | F10: 2 | G10: 280 | H10: =F10*G10 -> 560 | J10: 六角支柱 | K10: 見積No：WOSM0039798A | L10: Y | M10: 40932 | P10: 40938 | Q10: 40938
B11: 1 | C11: ミスミ | D11: ミスミ | E11: SCB3-10 | F11: 20 | G11: 25 | H11: =F11*G11 -> 500 | J11: 六角穴付ボルト | K11: 見積No：WOSM0039798A | L11: Y | M11: 40932 | P11: 40938 | Q11: 40938
B12: 1 | C12: ミスミ | D12: ミスミ | E12: SCB3-15 | F12: 20 | G12: 25 | H12: =F12*G12 -> 500 | J12: 六角穴付ボルト | K12: 見積No：WOSM0039798A | L12: Y | M12: 40932 | P12: 40938 | Q12: 40938
B13: 1 | C13: ミスミ | D13: ミスミ | E13: SCB4-10 | F13: 20 | G13: 25 | H13: =F13*G13 -> 500 | J13: 六角穴付ボルト | K13: 見積No：WOSM0039798A | L13: Y | M13: 40932 | P13: 40938 | Q13: 40938
B14: 1 | C14: ミスミ | D14: ミスミ | E14: SCB4-15 | F14: 20 | G14: 30 | H14: =F14*G14 -> 600 | J14: 六角穴付ボルト | K14: 見積No：WOSM0039798A | L14: Y | M14: 40932 | P14: 40938 | Q14: 40938
B15: 1 | C15: ミスミ | D15: ミスミ | E15: SCB4-35 | F15: 2 | G15: 88 | H15: =F15*G15 -> 176 | J15: 六角穴付ボルト | K15: 見積No：WOSM0039798A | L15: Y | M15: 40932 | P15: 40938 | Q15: 40938
B16: 4 | C16: ミスミ | D16: ミスミ | E16: NEDJ-PT-SB-9-2 | F16: 1 | G16: 2098 | H16: =F16*G16 -> 2098 | J16: D-subコネクタハーネス | K16: 見積No：WOSM0039798A | L16: Z | M16: 40932 | P16: 40938 | Q16: 40938
B17: 4 | C17: ミスミ | D17: ミスミ | E17: F1.25-M3 | F17: 1 | G17: 460 | H17: =F17*G17 -> 460 | J17: 圧着端子（Y型） | K17: 見積No：WOSM0039798A | L17: Z | M17: 40932 | P17: 40938 | Q17: 40938
B18: 1 | C18: 遠藤製作所 | D18: 遠藤製作所 | E18: 95331-Y01 | F18: 1 | G18: 3400 | H18: =F18*G18 -> 3400 | J18: ツール板（3軸アリ） | L18: Y | M18: 40932 | Q18: 40939
B19: 1 | C19: 遠藤製作所 | D19: 遠藤製作所 | E19: 95331-Y02 | F19: 1 | G19: 3200 | H19: =F19*G19 -> 3200 | J19: 揺れ防止板 | L19: Y | M19: 40932 | Q19: 40939
B20: 1 | C20: 遠藤製作所 | D20: 遠藤製作所 | E20: 95331-Y03 | F20: 1 | G20: 3600 | H20: =F20*G20 -> 3600 | J20: 揺れ防止ステー板金 | L20: Y | M20: 40932 | Q20: 40939
B21: 1 | C21: 遠藤製作所 | D21: 遠藤製作所 | E21: 95331-Y04 | F21: 1 | G21: 1500 | H21: =F21*G21 -> 1500 | J21: 3軸アリ取付スペーサ | L21: Y | M21: 40932 | Q21: 40940
B22: 1 | C22: 遠藤製作所 | D22: 遠藤製作所 | E22: 95331-Y05 | F22: 1 | G22: 3200 | H22: =F22*G22 -> 3200 | J22: バルブ取付板金スペーサ | L22: Y | M22: 40932 | Q22: 40939
B23: 1 | C23: 遠藤製作所 | D23: 遠藤製作所 | E23: SS40079 | F23: 1 | G23: 13800 | H23: =F23*G23 -> 13800 | J23: 740,752,780用ホルダ（P=25） | L23: Y | M23: 40932 | Q23: 40939
B24: 1 | C24: 遠藤製作所 | D24: 遠藤製作所 | E24: SS40143 | F24: 1 | G24: 2400 | H24: =F24*G24 -> 2400 | J24: バルブ取付板 | L24: Y | M24: 40932 | Q24: 40939
B25: 1 | C25: 遠藤製作所 | D25: 遠藤製作所 | E25: SS40144 | F25: 1 | G25: 4500 | H25: =F25*G25 -> 4500 | J25: シリンジガイド | L25: Y | M25: 40932 | Q25: 40939

Sheet 12.01.24 【95354】協栄電気（新電元） 原価一覧
B2: お客先名 | E2: 協栄電気（新電元） | G2: 合計金額 | J2: =SUM(H:H) -> 40481
B3: 担当営業 | E3: 勝田
B4: 受注番号 | E4: 95354
B5: 希望納期 | E5: 40939
B6: 最終納品 | E6: 40942
B8: 見積り分類 | C8: メーカー | D8: 仕入先 | E8: 品名 / 型式 | F8: 数量 | G8: 単価 | H8: 金額 | I8: 分類合計 | J8: 詳細 | K8: 備考 | L8: 技術分類 | M8: 発注日 | N8: 発注 | O8: 納期 | P8: 入荷予定日 | Q8: 入荷日
B9: 8 | C9: ミスミ | D9: ミスミ | E9: C1-SCDB-12045740 | F9: 1 | G9: 3820 | H9: =F9*G9 -> 3820 | J9: シャフトホルダ | K9: 受注No：WOSC00E94247 | L9: Y | M9: 40932 | N9: 済 | P9: 40939 | Q9: 40939
B10: 8 | C10: ミスミ | D10: ミスミ | E10: NEDU-PS-SB-9-3.0 | F10: 1 | G10: 2935 | H10: =F10*G10 -> 2935 | J10: Dsubハーネス | K10: 受注No：WOSC00E94247 | L10: Y | M10: 40932 | N10: 済 | P10: 40939 | Q10: 40939
B11: 8 | C11: ミスミ | D11: ミスミ | E11: HD-LN-4-40-05 | F11: 1 | G11: 226 | H11: =F11*G11 -> 226 | J11: Dsubロック金具 | K11: 受注No：WOSC00E94247 | L11: Y | M11: 40932 | N11: 済 | P11: 40939 | Q11: 40939
H12: =F12*G12 -> 0
H13: =F13*G13 -> 0
B14: 7 | C14: 遠藤製作所 | D14: 遠藤製作所 | E14: 95354-Y01 | F14: 1 | G14: 19000 | H14: =F14*G14 -> 19000 | J14: ツール板 | L14: Y | M14: 40933 | Q14: 40939
B15: 7 | C15: 遠藤製作所 | D15: 遠藤製作所 | E15: 95354-Y02 | F15: 1 | G15: 14500 | H15: =F15*G15 -> 14500 | J15: SV91バルブホルダ（ピン付） | L15: Y | M15: 40933 | Q15: 40941

Sheet 12.01.27 【95875】 白河オリンパス 原価一覧
B2: お客先名 | E2: ㈱ｲｲﾀﾞ様(白河ｵﾘﾝﾊﾟｽ) | G2: 合計金額 | J2: =SUM(H:H) -> 12000
B3: 担当営業 | E3: 青木
B4: 受注番号 | E4: 95875
B5: 希望納期 | E5: 40935
B6: 最終納品
B8: 見積り分類 | C8: メーカー | D8: 仕入先 | E8: 品名 / 型式 | F8: 数量 | G8: 単価 | H8: 金額 | I8: 分類合計 | J8: 詳細 | K8: 備考 | L8: 技術分類 | M8: 発注日 | N8: 発注 | O8: 納期 | P8: 入荷予定日 | Q8: 入荷日
B9: 1 | C9: 遠藤製作所 | D9: 遠藤製作所 | E9: ﾆｰﾄﾞﾙｶﾞｲﾄﾞﾛﾝｸﾞ 95875-Y001 | F9: 1 | G9: 12000 | H9: =F9*G9 -> 12000 | I9: Ｙ | J9: ﾉｽﾞﾙｶﾞｲﾄﾞ10mm延長 | K9: 遠藤製作所図面渡し済み | M9: 40947 | Q9: 40954

Sheet 12.01.31 【95480】大津屋（旭電器工業） 原価一覧
B2: お客先名 | E2: 大津屋（旭電器工業） | G2: 合計金額 | J2: =SUM(H:H) -> 99831
B3: 担当営業 | E3: 真保
B4: 受注番号 | E4: 95480
B5: 希望納期 | E5: 40947
B6: 最終納品
B8: 見積り分類 | C8: メーカー | D8: 仕入先 | E8: 品名 / 型式 | F8: 数量 | G8: 単価 | H8: 金額 | I8: 分類合計 | J8: 詳細 | K8: 備考 | L8: 技術分類 | M8: 発注日 | N8: 発注 | O8: 納期 | P8: 入荷予定日 | Q8: 入荷日
B9: 2 | C9: 蛇の目 | D9: 蛇の目 | E9: I/O（1）ケーブル | F9: 1 | G9: 3500 | H9: =F9*G9 -> 3500 | J9: JR2203N用 | L9: Z | M9: 40939 | P9: 40947 | Q9: 40947
B10: 2 | C10: 蛇の目 | D10: 蛇の目 | E10: 荷造り運賃 | F10: 1 | G10: 1000 | H10: =F10*G10 -> 1000 | L10: Z | M10: 40939
H11: =F11*G11 -> 0
B12: 4 | C12: ミスミ | D12: ミスミ | E12: NEDJ-PT-SB-37-1 | F12: 1 | G12: 4172 | H12: =F12*G12 -> 4172 | J12: Dsubコネクタハーネス | L12: Z | M12: 40939 | P12: 40945 | Q12: 40945
B13: 4 | C13: ミスミ | D13: ミスミ | E13: NEDJ-ST-SB-25-1 | F13: 1 | G13: 3095 | H13: =F13*G13 -> 3095 | J13: Dsubコネクタハーネス | L13: Z | M13: 40939 | P13: 40945 | Q13: 40945
H14: =F14*G14 -> 0
B15: 7 | C15: ミスミ | D15: ミスミ | E15: XYZEG25 | F15: 1 | G15: 30900 | H15: =F15*G15 -> 30900 | J15: XYZステージ（アリ式） | L15: Y | M15: 40939 | P15: 40945 | Q15: 40945
B16: 7 | C16: ミスミ | D16: ミスミ | E16: SCB4-35 | F16: 2 | G16: 88 | H16: =F16*G16 -> 176 | J16: 六角穴付ボルト | L16: Y | M16: 40939 | P16: 40945 | Q16: 40945
B17: 7 | C17: ミスミ | D17: ミスミ | E17: SCB2-10 | F17: 10 | G17: 85 | H17: =F17*G17 -> 850 | J17: 六角穴付ボルト | L17: Y | M17: 40939 | P17: 40945 | Q17: 40945
B18: 7 | C18: 遠藤製作所 | D18: 遠藤製作所 | E18: 95480-Y01 | F18: 1 | G18: 6800 | H18: =F18*G18 -> 6800 | J18: ツール板 | L18: Y | M18: 40939 | Q18: 40947
B19: 7 | C19: 遠藤製作所 | D19: 遠藤製作所 | E19: 95480-Y02 | F19: 1 | G19: 2300 | H19: =F19*G19 -> 2300 | J19: サイド取付板 | L19: Y | M19: 40939 | Q19: 40947
B20: 7 | C20: 遠藤製作所 | D20: 遠藤製作所 | E20: 95480-Y03 | F20: 1 | G20: 2800 | H20: =F20*G20 -> 2800 | J20: XYZE25変換板 | L20: Y | M20: 40939 | Q20: 40947
B21: 13 | C21: 遠藤製作所 | D21: 遠藤製作所 | E21: 95480-Z01 | F21: 1 | G21: 5200 | H21: =F21*G21 -> 5200 | J21: カップ板金 | L21: Z | M21: 40939 | Q21: 40947
B22: 13 | C22: 遠藤製作所 | D22: 遠藤製作所 | E22: 95480-Z02 | F22: 1 | G22: 5200 | H22: =F22*G22 -> 5200 | J22: カップ高さ調整板金 | L22: Z | M22: 40939 | Q22: 40947
B23: 13 | C23: 遠藤製作所 | D23: 遠藤製作所 | E23: 95480-Z03 | F23: 5 | G23: 1500 | H23: =F23*G23 -> 7500 | J23: カップ（POM） | L23: Z | M23: 40939 | Q23: 40947
B24: 13 | C24: 遠藤製作所 | D24: 遠藤製作所 | E24: 95480-Z04 | F24: 3 | G24: 1800 | H24: =F24*G24 -> 5400 | J24: カップ（POM）蓋 | K24: 追加分 | L24: Z | M24: 40946 | Q24: 本社着
B25: 7 | C25: 遠藤製作所 | D25: 遠藤製作所 | E25: SS40079 | F25: 1 | G25: 13800 | H25: =F25*G25 -> 13800 | J25: 740,752,780用ホルダ（P=25） | L25: Y | M25: 40939 | Q25: 40947
B27: 8 | C27: SMC | D27: 都機工 | E27: IR1000-01BG | F27: 1 | G27: 6613 | H27: 6613 | J27: 精密レギュレータ | L27: Z | M27: 40940 | P27: 40945 | Q27: 40945
B28: 8 | C28: SMC | D28: SMC | E28: KQ2H06-01S | F28: 1 | J28: 継手 | L28: Z | M28: 在庫使用
B29: 8 | C29: 機材 | D29: 機材 | E29: 2197A | F29: 1 | J29: 継手（EFD） | L29: Z | M29: 在庫使用
B30: 8 | C30: 機材 | D30: 機材 | E30: 2004C | F30: 1 | J30: 継手（EFD） | L30: Z | M30: 在庫使用
B32: 4 | C32: ミスミ | D32: ミスミ | E32: DB-9SP | F32: 1 | G32: 365 | H32: 365 | J32: Dsubコネクタ 9P(オス） | L32: Z | M32: 40955 | P32: 40956 | Q32: 40956
B33: 4 | C33: ミスミ | D33: ミスミ | E33: DE-C8-J9-F21R | F33: 1 | G33: 160 | H33: 160 | J33: Dsubコネクタフード 9P | L33: Z | M33: 40955 | P33: 40956 | Q33: 40956

Sheet 12.02.01 【95679】コニカミノルタ 原価一覧
B2: お客先名 | E2: コニカミノルタ | G2: 合計金額 | J2: =SUM(H:H) -> 563334
B3: 担当営業 | E3: 神田
B4: 受注番号 | E4: 95679
B5: 希望納期 | E5: 40949
B6: 最終納品
B8: 見積り分類 | C8: メーカー | D8: 仕入先 | E8: 品名 / 型式 | F8: 数量 | G8: 単価 | H8: 金額 | I8: 分類合計 | J8: 詳細 | K8: 備考 | L8: 技術分類 | M8: 発注日 | N8: 発注 | O8: 納期 | P8: 入荷予定日 | Q8: 入荷日
B9: 4 | C9: ミスミ | D9: ミスミ | E9: SCDB-AMW-A37-b30-T20-l20-P10-J10-G10-Z4-F16-W10-M4 | F9: 1 | G9: 3220 | H9: =F9*G9 -> 3220 | J9: シャフトホルダ | K9: Cストーク適用 | L9: Y | M9: 40940 | P9: 40947 | Q9: 40947
B10: 4 | C10: ミスミ | D10: ミスミ | E10: SCB2-5 | F10: 10 | G10: 80 | H10: =F10*G10 -> 800 | J10: 六角穴付ボルト | L10: Y | M10: 40940 | P10: 40942 | Q10: 40942
B11: 3 | C11: ミスミ | D11: ミスミ | E11: @ECHN-20061106-00010 | F11: 1 | G11: 2814 | H11: =F11*G11 -> 2814 | J11: 特注ハーネス | K11: 技術課在庫品使用 | L11: Z | M11: 技術在庫
H12: =F12*G12 -> 0
B13: 4 | C13: 遠藤製作所 | D13: 遠藤製作所 | E13: SS4590 | F13: 1 | G13: 3900 | H13: =F13*G13 -> 3900 | J13: プレート1 | L13: Y | M13: 40940 | Q13: 40947
B14: 4 | C14: 遠藤製作所 | D14: 遠藤製作所 | E14: 95679-Y01 | F14: 1 | G14: 5800 | H14: =F14*G14 -> 5800 | J14: プレート2 | L14: Y | M14: 40940 | Q14: 40947
B15: 4 | C15: 遠藤製作所 | D15: 遠藤製作所 | E15: 95679-Y02 | F15: 1 | G15: 18200 | H15: =F15*G15 -> 18200 | J15: シリンジウケ10cc（M2付） | L15: Y | M15: 40940 | Q15: 40947
B16: 4 | C16: 遠藤製作所 | D16: 遠藤製作所 | E16: 95679-Y03 | F16: 1 | G16: 5200 | H16: =F16*G16 -> 5200 | J16: ノズルガイド（SH33CH） | L16: Y | M16: 40940 | Q16: 40947
B17: 4 | C17: 遠藤製作所 | D17: 遠藤製作所 | E17: 95679-Y04 | F17: 1 | G17: 5200 | H17: =F17*G17 -> 5200 | J17: ノズルガイド（SPN） | L17: Y | M17: 40940 | Q17: 40947
B18: 4 | C18: 遠藤製作所 | D18: 遠藤製作所 | E18: 95679-Y05 | F18: 1 | G18: 5200 | H18: =F18*G18 -> 5200 | J18: ノズルガイド（SSN） | L18: Y | M18: 40940 | Q18: 40947
H19: =F19*G19 -> 0
B20: 1 | C20: 蛇の目 | D20: 蛇の目 | E20: JR2204N | F20: 1 | G20: 465000 | H20: =F20*G20 -> 465000 | K20: 大阪（営） 神田分 | M20: 40940 | P20: 40948 | Q20: 40948
B21: 1 | C21: 蛇の目 | D21: 蛇の目 | E21: 荷造り運賃 | F21: 1 | G21: 10000 | H21: =F21*G21 -> 10000 | K21: 大阪（営） 神田分 | M21: 40940
B22: 2 | C22: 蛇の目 | D22: 蛇の目 | E22: ティーチングペンダント | F22: 1 | G22: 38000 | H22: =F22*G22 -> 38000 | J22: JR-TB | K22: 機材在庫品使用 | M22: 在庫使用

Sheet 12.02.02 【95226】TDK由利本庄 原価一覧
B2: お客先名 | E2: TDK由利本庄 | G2: 合計金額 | J2: =SUM(H:H) -> 108225
B3: 担当営業 | E3: 平山（米山）
B4: 受注番号 | E4: 95226
B5: 希望納期 | E5: 40954
B6: 最終納品
B8: 見積り分類 | C8: メーカー | D8: 仕入先 | E8: 品名 / 型式 | F8: 数量 | G8: 単価 | H8: 金額 | I8: 分類合計 | J8: 詳細 | K8: 備考 | L8: 技術分類 | M8: 発注日 | N8: 発注 | O8: 納期 | P8: 入荷予定日 | Q8: 入荷日
B9: 14 | C9: ミスミ | D9: ミスミ | E9: NEDJ-PT-E-9-3 | F9: 1 | G9: 2341 | H9: =F9*G9 -> 2341 | J9: Dsubハーネス（9P） | M9: 40941 | P9: 40948 | Q9: 40948
B10: 14 | C10: ミスミ | D10: ミスミ | E10: PS7D-37V3A | F10: 1 | G10: 5270 | H10: =F10*G10 -> 5270 | J10: 端子台 | M10: 40941 | P10: 40948 | Q10: 40948
B11: 14 | C11: ミスミ | D11: ミスミ | E11: NEDJ-PS-SB-37-2 | F11: 1 | G11: 5869 | H11: =F11*G11 -> 5869 | J11: Dsubハーネス（37P） | M11: 40941 | P11: 40948 | Q11: 40948
B12: 14 | C12: ミスミ | D12: ミスミ | E12: PCN-3H-25A | F12: 1 | G12: 4080 | H12: =F12*G12 -> 4080 | J12: 端子台 | M12: 40941 | P12: 40948 | Q12: 40948
B13: 14 | C13: ミスミ | D13: ミスミ | E13: MRB-500 | F13: 1 | G13: 670 | H13: =F13*G13 -> 670 | J13: DINレール | M13: 40941 | P13: 40948 | Q13: 2/9.
B14: 14 | C14: ミスミ | D14: ミスミ | E14: ESAW-TCM310-5P | F14: 1 | G14: 3022 | H14: =F14*G14 -> 3022 | J14: 端子台 | M14: 40941 | P14: 40948 | Q14: 40948
B15: 10 | C15: ミスミ | D15: ミスミ | E15: XSG40-CZ | F15: 1 | G15: 16000 | H15: =F15*G15 -> 16000 | J15: X軸ステージ | M15: 40941 | P15: 40948 | Q15: 40948
B16: 10 | C16: ミスミ | D16: ミスミ | E16: SLSBWF7-73 | F16: 4 | G16: 610 | H16: =F16*G16 -> 2440 | J16: 六角支柱 | M16: 40941 | P16: 40948 | Q16: 40948
B17: 14 | C17: ミスミ | D17: ミスミ | E17: NEDJ-SS-E-25-2 | F17: 1 | G17: 4483 | H17: =F17*G17 -> 4483 | J17: Dsubハーネス（25P） | M17: 40941 | P17: 40946 | Q17: 40946
H18: =F18*G18 -> 0
B19: 10 | C19: タイショー | D19: タイショー | E19: SS40077 | F19: 1 | G19: 8200 | H19: 8200 | J19: 725D,725DA用ホルダ（P＝25） | M19: 40941 | Q19: 40952
B20: 10 | C20: タイショー | D20: タイショー | E20: SS40298 | F20: 1 | G20: 3900 | H20: 3900 | J20: CCD取付板K | M20: 40941 | Q20: 40952
B21: 10 | C21: タイショー | D21: タイショー | E21: SS40702 | F21: 1 | G21: 2800 | H21: 2800 | J21: 3方弁取付板 | M21: 40941 | Q21: 40952
B22: 10 | C22: タイショー | D22: タイショー | E22: YHTKS-0001 | F22: 1 | G22: 18200 | H22: 18200 | J22: ﾛﾎﾞｯﾄ取付板 | M22: 40941 | Q22: 40952
B23: 10 | C23: タイショー | D23: タイショー | E23: YHTKS-0002 | F23: 1 | G23: 2400 | H23: 2400 | J23: LEDリング取付板金 | M23: 40941 | Q23: 40952
B24: 10 | C24: タイショー | D24: タイショー | E24: YHTKS-0003 | F24: 1 | G24: 4600 | H24: 4600 | J24: 残量検知センサーブロック | M24: 40941 | Q24: 40952
B25: 10 | C25: タイショー | D25: タイショー | E25: YHTKS-0004 | F25: 1 | G25: 2600 | H25: 2600 | J25: スペーサブロック | M25: 40941 | Q25: 40952
H26: =F26*G26 -> 0
B27: 1 | C27: 蛇の目 | D27: 蛇の目 | E27: COM2増設ケーブル | F27: 1 | G27: 2500 | H27: =F27*G27 -> 2500 | J27: JR2503N用 | K27: （平山依頼分） | M27: 40942 | P27: 40954 | Q27: 40954
B28: 2 | C28: 蛇の目 | D28: 蛇の目 | E28: I/O（1）増設ケーブル | F28: 1 | G28: 7350 | H28: =F28*G28 -> 7350 | J28: JR2503N用 | K28: （平山依頼分） | M28: 40942 | P28: 40954 | Q28: 40954
B29: 16 | C29: 蛇の目 | D29: 蛇の目 | E29: JR2503N用ヘッドカバー SETﾛｺﾞ入り | F29: 1 | G29: 10500 | H29: =F29*G29 -> 10500 | J29: JR2503N用 | K29: （平山依頼分） | M29: 40942 | P29: 40954 | Q29: 40954
B30: 1.2.16 | C30: 蛇の目 | D30: 蛇の目 | E30: 荷造り運賃 | F30: 1 | G30: 1000 | H30: =F30*G30 -> 1000 | J30: JR2503N用 | K30: （平山依頼分） | M30: 40942

Sheet 12.02.14 【96385】フルハン 原価一覧
B2: お客先名 | E2: フルハン | G2: 合計金額 | J2: =SUM(H:H) -> 36556
B3: 担当営業 | E3: 田中
B4: 受注番号 | E4: 96385
B5: 希望納期 | E5: 40963
B6: 最終納品
B8: 見積り分類 | C8: メーカー | D8: 仕入先 | E8: 品名 / 型式 | F8: 数量 | G8: 単価 | H8: 金額 | I8: 分類合計 | J8: 詳細 | K8: 備考 | L8: 技術分類 | M8: 発注日 | N8: 発注 | O8: 納期 | P8: 入荷予定日 | Q8: 入荷日
B9: 5 | C9: 遠藤製作所 | D9: 遠藤製作所 | E9: SS40286 | F9: 2 | G9: 18200 | H9: =F9*G9 -> 36400 | J9: 30cc＆55cc-G付（M2） シリンジウケ | M9: 40954 | P9: 40963 | Q9: 40962
B10: 5 | C10: ミスミ | D10: ミスミ | E10: CRKB4-10 | F10: 2 | G10: 78 | H10: =F10*G10 -> 156 | J10: 樹脂ローレットねじ | M10: 40954 | P10: 40956 | Q10: 40956
H11: =F11*G11 -> 0
H12: =F12*G12 -> 0
H13: =F13*G13 -> 0
H14: =F14*G14 -> 0
H15: =F15*G15 -> 0
H16: =F16*G16 -> 0
H17: =F17*G17 -> 0
H18: =F18*G18 -> 0
H19: =F19*G19 -> 0
H20: =F20*G20 -> 0
H21: =F21*G21 -> 0
H22: =F22*G22 -> 0
... H30: =F30*G30 -> 0

Sheet 【95831】 相模産業㈱（日立オートモティブシステム）
B2: お客先名 | E2: 東亜電気 | G2: 合計金額 | J2: =SUM(H:H) -> 770455
B4: お客先名 | E4: 相模産業(日立ｵｰﾄﾓﾃｨﾌﾞｼｽﾃﾑ) | G4: 合計金額 | J4: =SUM(H:H) -> 770455
B5: 担当営業 | E5: 町田
B6: 受注番号 | E6: 95831 | G6: 備考
B7: 希望納期 | E7: 40962
B8: 最終納品
B10: 見積り分類 | C10: メーカー | D10: 仕入先 | E10: 品名 / 型式 | F10: 数量 | G10: 単価 | H10: 金額 | I10: 分類合計 | J10: 詳細 | K10: 備考 | L10: 技術分類 | M10: 発注日 | N10: 発注 | O10: 納期 | P10: 入荷予定日 | Q10: 入荷日
B11: 1 | C11: 蛇の目 | D11: 蛇の目 | E11: JR2203NH | F11: 1 | G11: 400000 | H11: =F11*G11 -> 400000 | L11: - | N11: 40954 | Q11: 40960
B12: 1 | C12: 蛇の目 | D12: 蛇の目 | E12: 荷造り運賃 | F12: 1 | G12: 10000 | H12: =F12*G12 -> 10000 | L12: - | N12: 40954
B13: 3 | C13: 蛇の目 | D13: 蛇の目 | E13: JR-TB | F13: 1 | G13: 38000 | H13: =F13*G13 -> 38000 | J13: ティーチングペンダント | L13: - | N13: 在庫使用
B14: 4 | C14: ミスミ | D14: ミスミ | E14: %WRFH-4050-120110-15 | F14: 1 | G14: 21700 | H14: =F14*G14 -> 21700 | J14: 特注ハーネス | L14: - | N14: 40955 | P14: 40969 | Q14: 40969
B15: 5 | C15: SET | D15: SET | E15: SDP300 | F15: 1 | G15: 15939 | H15: =F15*G15 -> 15939 | J15: ﾃﾞｲｽﾍﾟﾝｻｰｺﾝﾄﾛｰﾗ | L15: -
B16: 6 | C16: SET | D16: SET | E16: ATP300A | F16: 1 | G16: 30000 | H16: =F16*G16 -> 30000 | J16: 300ＣＶ用 ｶﾞｲﾖｳｷ | L16: -
B17: 7 | C17: SET | D17: SET | E17: SV35HF | F17: 1 | G17: 21000 | H17: =F17*G17 -> 21000 | J17: SV35用ﾊｲﾌﾛｰﾄﾋﾟｽﾄﾝﾊﾞﾙﾌﾞ | L17: -
B18: 8 | C18: ﾌﾛｳｴﾙ | D18: ｱﾗﾑ | E18: 30-12MC4N-C | F18: 1 | G18: 1624 | H18: =F18*G18 -> 1624 | J18: φ１２－10テフロンホース・継手(ｽﾄﾚｰﾄ） | L18: - | N18: 40959 | P18: 40983
B19: 9 | C19: ミスミ | D19: ミスミ | E19: ｲﾝﾀｰﾛｯｸ機構付安全ｶﾊﾞｰｾｯﾄ | F19: 1 | G19: 111948 | H19: =F19*G19 -> 111948 | J19: ■ミスミ図番：M1202-2165-2（1000mm) | L19: - | N19: 済 | P19: 40966 | Q19: 40966
B20: 9 | C20: ミスミ | D20: ミスミ | E20: FALC-AM-T3.0-A30-B40-L25-X12.5-H20-N5-Y12.5-S25-NA4-K10 | F20: 4 | G20: 1500 | H20: =F20*G20 -> 6000 | J20: L曲げブラケット 凡用タイプ | L20: - | N20: 40955 | P20: 40962 | Q20: 40962
B21: 9 | C21: ミスミ | D21: ミスミ | E21: ＨＮＴＵ５－５ | F21: 4 | G21: 47 | H21: =F21*G21 -> 188 | J21: 先入れバネナット | L21: - | N21: 40955 | P21: 40962 | Q21: 40962
B22: 10 | C22: 遠藤製作所 | D22: 遠藤製作所 | E22: 95831-Y001 | F22: 1 | G22: 8500 | H22: =F22*G22 -> 8500 | J22: ATD300ツール板 | K22: 図面送付済み | L22: Y | N22: 40954 | P22: 40962 | Q22: 40962
B23: 10 | C23: 遠藤製作所 | D23: 遠藤製作所 | E23: SS3244 | F23: 1 | G23: 7800 | H23: =F23*G23 -> 7800 | J23: タブテーブル（L110） | L23: Ｙ | N23: 40954 | P23: 40962 | Q23: 40962
B24: 10 | C24: 遠藤製作所 | D24: 遠藤製作所 | E24: SS40077 | F24: 1 | G24: 13800 | H24: =F24*G24 -> 13800 | J24: 725D,725DA用バルブホルダ（P=25） | L24: Ｙ | N24: 40954 | P24: 40962 | Q24: 40962
B25: 10 | C25: 遠藤製作所 | D25: 遠藤製作所 | E25: SS40564 | F25: 1 | G25: 19500 | H25: =F25*G25 -> 19500 | J25: 新カートリッジホルダ（タブ用） | L25: Ｙ | N25: 40954 | P25: 40962 | Q25: 40962
B26: 10 | C26: 遠藤製作所 | D26: 遠藤製作所 | E26: 95831-Y002 | F26: 1 | G26: 15200 | H26: =F26*G26 -> 15200 | J26: X軸ステージ変換板 | K26: 図面送付済み | L26: Ｙ | N26: 40954 | P26: 40962 | Q26: 40962
B27: 10 | C27: ミスミ | D27: ミスミ | E27: XSG40-CZ | F27: 1 | G27: 16000 | H27: =F27*G27 -> 16000 | J27: リニアボールX軸ステージ | L27: Ｙ | N27: 40955 | P27: 40962 | Q27: 40962
B28: 10 | C28: ミスミ | D28: ミスミ | E28: LRLB5-10 | F28: 1 | G28: 570 | H28: =F28*G28 -> 570 | J28: 長尺ローレット付ボルト | L28: Ｙ | N28: 40955 | P28: 40962 | Q28: 40962
B29: 10 | C29: ミスミ | D29: ミスミ | E29: BVHVU6-3 | F29: 1 | G29: 780 | H29: =F29*G29 -> 780 | J29: ハンドバルブ | L29: Ｙ | N29: 40955 | P29: 40962 | Q29: 40962
B30: 10 | C30: ミスミ | D30: ミスミ | E30: @ECHN-20061106-00010 | F30: 1 | G30: 2181 | H30: =F30*G30 -> 2181 | J30: JRN-1400/1500/7040(L=1000mm) | L30: Ｙ | N30: 40955 | P30: 40966 | Q30: 40966
B31: 10 | C31: ミスミ | D31: ミスミ | E31: ＭＳ３－１０ | F31: 57 | G31: 19 | H31: =F31*G31 -> 1083 | J31: ﾉｯｸﾋﾟﾝ | L31: Ｙ | N31: 40955 | P31: 40962 | Q31: 40962
B32: 11 | C32: 遠藤製作所 | D32: 遠藤製作所 | E32: 95831-X001 | F32: 1 | G32: 14800 | H32: =F32*G32 -> 14800 | J32: ﾜｰｸ固定冶具用ﾍﾞｰｽ板(ﾜｰｸﾍﾞｰｽ） | K32: 図面送付済み | L32: X | N32: 40954 | P32: 40962 | Q32: 40962
B33: 11 | C33: ミスミ | D33: ミスミ | E33: GJPRBB5-6 | F33: 4 | G33: 470 | H33: =F33*G33 -> 1880 | J33: 位置決めピン | L33: X | N33: 40955 | P33: 40962 | Q33: 40962
B34: 12 | C34: SET | D34: SET | E34: SH16TT－B | F34: 1 | G34: 385 | H34: =F34*G34 -> 385 | J34: 16G ＴＴﾃｰﾊﾟｰﾉｽﾞﾙ（ｸﾞﾚｰ） 50ｹ入り
B35: 13 | C35: SET | D35: SET | E35: 7016948 | F35: 1 | G35: 425 | H35: =F35*G35 -> 425 | J35: 2186P ｶｰﾄﾘｯｼﾞﾙｱﾛｯｸ
B36: 15 | E36: 組立調整費 | F36: 1 | H36: =F36*G36 -> 0
B37: 16 | E37: 輸送梱包費 | F37: 1 | H37: =F37*G37 -> 0
B38: 9 | C38: ミスミ | D38: ミスミ | E38: 六角穴付皿ﾎﾞﾙﾄ ＳＨＦＢＳ５－１０ | F38: 8 | G38: 73 | H38: 584 | N38: 41002 | P38: 41003 | Q38: 41004
B39: 9 | C39: ミスミ | D39: ミスミ | E39: 片ﾘﾌﾞﾌﾞﾗｹｯﾄ HBFLSL5-C-SSP | F39: 8 | G39: 63 | H39: 504 | N39: 41002 | P39: 41003 | Q39: 41004
B40: 9 | C40: ミスミ | D40: ミスミ | E40: 十字穴付ﾄﾗｽ小ﾈｼﾞ SHCBM5-10 | F40: 8 | G40: 33 | H40: 264 | N40: 41002 | P40: 41003 | Q40: 41004
B41: 9 | C41: 遠藤製作所 | D41: 遠藤製作所 | E41: 95831-Z001 安全ｶﾊﾞｰ(前後ｱﾝﾀﾞｰ部) | F41: 2 | G41: 4900 | H41: 9800 | N41: 41002 | Q41: 41003

Sheet 【96979キヤノン化成 原価一覧
B2: お客先名 | E2: キヤノン化成 | G2: 合計金額 | J2: =SUM(H:H) -> 222140
B3: 担当営業 | E3: 勝田
B4: 受注番号 | E4: 96979
B5: 希望納期 | E5: 40991
B6: 最終納品 | E6: 40994
B8: 見積り分類 | C8: メーカー | D8: 仕入先 | E8: 品名 / 型式 | F8: 数量 | G8: 単価 | H8: 金額 | I8: 分類合計 | J8: 詳細 | K8: 備考 | L8: 技術分類 | M8: 発注日 | N8: 発注 | O8: 納期 | P8: 入荷予定日 | Q8: 入荷日
C9: ケイ･テック･アート | E9: 液剤チャンバー/SS3255 | F9: 1 | G9: 93500 | H9: =F9*G9 -> 93500 | M9: 40973 | P9: 40991 | Q9: 3/22本社着
C10: ケイ･テック･アート | E10: ピストン/SS40754 | F10: 1 | G10: 7800 | H10: =F10*G10 -> 7800 | M10: 40973 | P10: 40991 | Q10: 3/22本社着
C11: ケイ･テック･アート | E11: ニードル/SS40755 | F11: 1 | G11: 22000 | H11: =F11*G11 -> 22000 | M11: 40973 | P11: 40991 | Q11: 3/22本社着
C12: ケイ･テック･アート | E12: プレートカバー/SS40756 | F12: 2 | G12: 17000 | H12: =F12*G12 -> 34000 | M12: 40973 | P12: 40991 | Q12: 3/22本社着
C13: ケイ･テック･アート | E13: エアキャップ/SS40513 | F13: 1 | G13: 13800 | H13: =F13*G13 -> 13800 | M13: 40973 | P13: 40991 | Q13: 3/22本社着
C14: ケイ･テック･アート | E14: ノズルボディ/SS40628 | F14: 1 | G14: 18500 | H14: =F14*G14 -> 18500 | M14: 40973 | P14: 40991 | Q14: 3/22本社着
H15: =F15*G15 -> 0
C16: 矢星製作所 | E16: ノズル32G/SS40629 | F16: 1 | G16: 24500 | H16: =F16*G16 -> 24500 | M16: 40973 | P16: 40991
H17: =F17*G17 -> 0
C18: ミスミ | E18: パッキン/FREP8H1-A54-B35-W38-V18-F23-G13.5-N3 | F18: 2 | G18: 1140 | H18: =F18*G18 -> 2280 | J18: YS12008 | M18: 40970 | P18: 40975 | Q18: 3/7本社着
C19: ミスミ | E19: ガラスプレート角/FGLKF3-41-22 | F19: 2 | G19: 2640 | H19: =F19*G19 -> 5280 | J19: YS12008 | M19: 40970 | P19: 40975 | Q19: 3/7本社着
C20: ミスミ | E20: Oリング/NPEG9 | F20: 1 | G20: 100 | H20: =F20*G20 -> 100 | J20: YS12008 | M20: 40970 | P20: 40975 | Q20: 3/7本社着
H21: =F21*G21 -> 0
C22: ウィルコ | E22: 六角アプセット子ネジ/UAP-0310 | F22: 10 | G22: 8 | H22: =F22*G22 -> 80 | M22: 40973 | P22: 40975 | Q22: 3/7本社着
E23: 送料 | F23: 1 | G23: 300 | H23: 300 | M23: 40973
H24: =F24*G24 -> 0
H25: =F25*G25 -> 0
H26: =F26*G26 -> 0
H27: =F27*G27 -> 0
H28: =F28*G28 -> 0
H29: =F29*G29 -> 0
H30: =F30*G30 -> 0

Sheet 【97137】タイコエレクトロニクス（9号機） 原価一覧
B2: お客先名 | E2: タイコエレクトロニクス | G2: 合計金額 | J2: =SUM(H:H) -> 757756
B3: 担当営業 | E3: 平山
B4: 受注番号 | E4: 97137
B5: 希望納期
B6: 最終納品
B8: 見積り分類 | C8: メーカー | D8: 仕入先 | E8: 品名 / 型式 | F8: 数量 | G8: 単価 | H8: 金額 | I8: 分類合計 | J8: 詳細 | K8: 備考 | L8: 技術分類 | M8: 発注日 | N8: 発注 | O8: 納期 | P8: 入荷予定日 | Q8: 入荷日
B9: 1 | C9: 蛇の目 | D9: 蛇の目 | E9: JR2303N（外部）JR2303N-SW-C | F9: 1 | G9: 546000 | H9: =F9*G9 -> 546000 | K9: 平山案件 | M9: 40980 | P9: 41002 | Q9: 41002
B10: 1 | C10: 蛇の目 | D10: 蛇の目 | E10: 外部操作スイッチ | F10: 1 | G10: 19000 | H10: =F10*G10 -> 19000 | K10: 平山案件 | M10: 40980 | P10: 41002
B11: 1 | C11: 蛇の目 | D11: 蛇の目 | E11: COM2増設費用 | F11: 1 | G11: 20000 | H11: =F11*G11 -> 20000 | K11: 平山案件 | M11: 40980
B12: 1 | C12: 蛇の目 | D12: 蛇の目 | E12: 荷造り運賃 | F12: 1 | G12: 10000 | H12: =F12*G12 -> 10000 | K12: 平山案件 | M12: 40980
H13: =F13*G13 -> 0
B14: 3 | C14: ミスミ | D14: ミスミ | E14: SLSBWRK7-70 | F14: 4 | G14: 300 | H14: =F14*G14 -> 1200 | J14: 六角支柱 | L14: Y | M14: 40980 | P14: 40984 | Q14: 40984
B15: 3 | C15: ミスミ | D15: ミスミ | E15: SBD-S4-8 | F15: 2 | G15: 320 | H15: =F15*G15 -> 640 | J15: 段付六角スペーサ | L15: Y | M15: 40980 | P15: 40984 | Q15: 40984
B16: 3 | C16: ミスミ | D16: ミスミ | E16: SP-S4-8 | F16: 2 | G16: 220 | H16: =F16*G16 -> 440 | J16: パイプスペーサ | L16: Y | M16: 40980 | P16: 40984 | Q16: 40984
B17: 20 | C17: ミスミ | D17: ミスミ | E17: KBBS3-10 | F17: 2 | G17: 380 | H17: =F17*G17 -> 760 | J17: 極低頭六角穴付ねじ | L17: Z | M17: 40980 | P17: 40984 | Q17: 40984
B18: 20 | C18: ミスミ | D18: ミスミ | E18: SETGS10-45-SC6-M4-N4-LKC | F18: 5 | G18: 1430 | H18: =F18*G18 -> 7150 | J18: 円形支柱 | L18: X | M18: 40980 | P18: 40984 | Q18: 40984
B19: 17 | C19: ミスミ | D19: ミスミ | E19: FSAW-K-12680-788-101005-0057 | F19: 1 | G19: 20560 | H19: =F19*G19 -> 20560 | J19: Web設計ボックス | L19: Z | M19: 40980 | P19: 40984 | Q19: 40984
B20: 17 | C20: ミスミ | D20: ミスミ | E20: PMUF4H5-120-120-1-10-4.5 | F20: 1 | G20: 2050 | H20: =F20*G20 -> 2050 | J20: パンチングメタル | L20: Z | M20: 40980 | P20: 40984 | Q20: 40984
B21: 17 | C21: ミスミ | D21: ミスミ | E21: MRB-260 | F21: 1 | G21: 930 | H21: =F21*G21 -> 930 | J21: DINレール | L21: Z | M21: 40980 | P21: 40984 | Q21: 40984
B22: 17 | C22: ミスミ | D22: ミスミ | E22: C06N-09MS-09FS-CROSS-ES05 | F22: 1 | G22: 2367 | H22: =F22*G22 -> 2367 | J22: RS232Cハーネス | L22: Z | M22: 40980 | P22: 40984 | Q22: 40984
B23: 17 | C23: ミスミ | D23: ミスミ | E23: HD-LN-4-40-05 | F23: 1 | G23: 226 | H23: =F23*G23 -> 226 | J23: Dsubロック金具 | L23: Z | M23: 40980 | P23: 40984 | Q23: 40984
B24: 17 | C24: ミスミ | D24: ミスミ | E24: PSSFGT15-100-M5 | F24: 1 | G24: 960 | H24: =F24*G24 -> 960 | J24: SUS汎用シャフト | L24: Z | M24: 40980 | P24: 40984 | Q24: 40984
B25: 14 | C25: ミスミ | D25: ミスミ | E25: KNCLSS4-8-20 | F25: 2 | G25: 290 | H25: =F25*G25 -> 580 | J25: 金属カラー | L25: Z | M25: 40980 | P25: 40984 | Q25: 40984
... B48: 20 | C48: ミスミ | D48: ミスミ | E48: SCBS4-8 | F48: 2 | G48: 38 | H48: =F48*G48 -> 76 | J48: 座金組込み六角穴付ボルト | L48: X | M48: 40980 | P48: 40984 | Q48: 40984
B50: 3 | C50: 遠藤製作所 | D50: 遠藤製作所 | E50: SS3163 | F50: 1 | G50: 8600 | H50: 8600 | J50: ロボット取付板 | L50: Y | M50: 40980 | P50: 41003 | Q50: 41003
B51: 15 | C51: 遠藤製作所 | D51: 遠藤製作所 | E51: SS3164-01 | F51: 1 | G51: 10800 | H51: =F51*G51 -> 10800 | J51: スターラー台 | L51: Z | M51: 40980 | P51: 41003 | Q51: 41003
B52: 20 | C52: 遠藤製作所 | D52: 遠藤製作所 | E52: SS3165-01 | F52: 1 | G52: 10800 | H52: =F52*G52 -> 10800 | J52: ワーク冶具ベース | L52: X | M52: 40980 | P52: 41003 | Q52: 41003
B53: 14 | C53: 遠藤製作所 | D53: 遠藤製作所 | E53: SS3170 | F53: 1 | G53: 5400 | H53: =F53*G53 -> 5400 | J53: ACJ-3 精密RG取付板 | L53: Z | M53: 40980 | P53: 41003 | Q53: 41003
B54: 3 | C54: 遠藤製作所 | D54: 遠藤製作所 | E54: SS40576 | F54: 1 | G54: 2900 | H54: =F54*G54 -> 2900 | J54: CCD取付板（K） | L54: Y | M54: 40980 | P54: 41003 | Q54: 41003
B55: 3 | C55: 遠藤製作所 | D55: 遠藤製作所 | E55: SS40577 | F55: 1 | G55: 3400 | H55: =F55*G55 -> 3400 | J55: 照明取付板（CA-DRW8M） | L55: Y | M55: 40980 | P55: 41003 | Q55: 41003
B56: 20 | C56: 遠藤製作所 | D56: 遠藤製作所 | E56: SS40578 | F56: 1 | G56: 1980 | H56: =F56*G56 -> 1980 | J56: 位置決めピンΦ8 | L56: X | M56: 40980 | P56: 41003 | Q56: 41003
B57: 20 | C57: 遠藤製作所 | D57: 遠藤製作所 | E57: SS40579 | F57: 1 | G57: 1980 | H57: =F57*G57 -> 1980 | J57: 位置決めピンΦ6 | L57: X | M57: 40980 | P57: 41003 | Q57: 41003
B58: 17 | C58: 遠藤製作所 | D58: 遠藤製作所 | E58: SS40585-01 | F58: 1 | G58: 3800 | H58: =F58*G58 -> 3800 | J58: シャフト板金 | L58: Z | M58: 40980 | P58: 41003 | Q58: 41003
B59: 3 | C59: 遠藤製作所 | D59: 遠藤製作所 | E59: SS40613 | F59: 1 | G59: 3400 | H59: =F59*G59 -> 3400 | J59: CCD取付板（K） ノズル用 | L59: Y | M59: 40980 | P59: 41003 | Q59: 41003
B60: 20 | C60: 遠藤製作所 | D60: 遠藤製作所 | E60: SS40614-03 | F60: 1 | G60: 7800 | H60: =F60*G60 -> 7800 | J60: ノズル位置合わせカメラ用ベース | L60: Z | M60: 40980 | P60: 41003 | Q60: 41003
B61: 20 | C61: 遠藤製作所 | D61: 遠藤製作所 | E61: SS40615 | F61: 2 | G61: 1400 | H61: =F61*G61 -> 2800 | J61: プリズム横押え板金 | L61: Z | M61: 40980 | P61: 41003 | Q61: 41003
B62: 15 | C62: 遠藤製作所 | D62: 遠藤製作所 | E62: 96429-Z01 | F62: 1 | G62: 9800 | H62: =F62*G62 -> 9800 | J62: スターラースペーサ(SW-101N) | L62: Z | M62: 40980 | P62: 41003 | Q62: 41003
B63: 20 | C63: 遠藤製作所 | D63: 遠藤製作所 | E63: SS40618 | F63: 1 | G63: 5900 | H63: 5900 | J63: 捨て打ちﾍﾞｰｽ | L63: Z | M63: 40980 | P63: 41003 | Q63: 41003
B64: 20 | C64: 遠藤製作所 | D64: 遠藤製作所 | E64: SS40619 | F64: 1 | G64: 1900 | H64: 1900 | J64: 捨て打ちﾍﾞｰｽ連結板 | L64: Z | M64: 40980 | P64: 41003 | Q64: 41003
B65: 20 | C65: 遠藤製作所 | D65: 遠藤製作所 | E65: SS40641 | F65: 1 | G65: 5200 | H65: 5200 | J65: ﾌﾟﾘｽﾞﾑ取付板2 | L65: Z | M65: 40980 | P65: 41003 | Q65: 41003
B67: 17 | C67: ニットクエンジニヤリング | D67: ニットクエンジニヤリング | E67: 制御盤組立配線費 | F67: 1 | G67: 22500 | H67: =F67*G67 -> 22500 | K67: 見積りNo：12-02666-2 | L67: Z | M67: 40996 | Q67: 斉藤氏引取
B68: 17 | C68: ニットクエンジニヤリング | D68: ニットクエンジニヤリング | E68: 出精値引き | F68: 1 | G68: -500 | H68: =F68*G68 -> -500 | K68: 見積りNo：12-02666-2 | L68: Z | M68: 40996

Sheet 【97138】タイコエレクトロニクス（10号機） 原価一覧
B2: お客先名 | E2: タイコエレクトロニクス | G2: 合計金額 | J2: =SUM(H:H) -> 757756
B3: 担当営業 | E3: 平山
B4: 受注番号 | E4: 97138
B5: 希望納期
B6: 最終納品
B8: 見積り分類 | C8: メーカー | D8: 仕入先 | E8: 品名 / 型式 | F8: 数量 | G8: 単価 | H8: 金額 | I8: 分類合計 | J8: 詳細 | K8: 備考 | L8: 技術分類 | M8: 発注日 | N8: 発注 | O8: 納期 | P8: 入荷予定日 | Q8: 入荷日
B9: 1 | C9: 蛇の目 | D9: 蛇の目 | E9: JR2303N（外部） JR2303N-SW-C | F9: 1 | G9: 546000 | H9: =F9*G9 -> 546000 | K9: 平山案件 | M9: 40980 | P9: 41002 | Q9: 41002
B10: 1 | C10: 蛇の目 | D10: 蛇の目 | E10: 外部操作スイッチ | F10: 1 | G10: 19000 | H10: =F10*G10 -> 19000 | K10: 平山案件 | M10: 40980 | P10: 41002
B11: 1 | C11: 蛇の目 | D11: 蛇の目 | E11: COM2増設費用 | F11: 1 | G11: 20000 | H11: =F11*G11 -> 20000 | K11: 平山案件 | M11: 40980
B12: 1 | C12: 蛇の目 | D12: 蛇の目 | E12: 荷造り運賃 | F12: 1 | G12: 10000 | H12: =F12*G12 -> 10000 | K12: 平山案件 | M12: 40980
H13: =F13*G13 -> 0
B14: 3 | C14: ミスミ | D14: ミスミ | E14: SLSBWRK7-70 | F14: 4 | G14: 300 | H14: =F14*G14 -> 1200 | J14: 六角支柱 | L14: Y | M14: 40980 | P14: 40984 | Q14: 40984
B15: 3 | C15: ミスミ | D15: ミスミ | E15: SBD-S4-8 | F15: 2 | G15: 320 | H15: =F15*G15 -> 640 | J15: 段付六角スペーサ | L15: Y | M15: 40980 | P15: 40984 | Q15: 40984
B16: 3 | C16: ミスミ | D16: ミスミ | E16: SP-S4-8 | F16: 2 | G16: 220 | H16: =F16*G16 -> 440 | J16: パイプスペーサ | L16: Y | M16: 40980 | P16: 40984 | Q16: 40984
B17: 20 | C17: ミスミ | D17: ミスミ | E17: KBBS3-10 | F17: 2 | G17: 380 | H17: =F17*G17 -> 760 | J17: 極低頭六角穴付ねじ | L17: Z | M17: 40980 | P17: 40984 | Q17: 40984
B18: 20 | C18: ミスミ | D18: ミスミ | E18: SETGS10-45-SC6-M4-N4-LKC | F18: 5 | G18: 1430 | H18: =F18*G18 -> 7150 | J18: 円形支柱 | L18: X | M18: 40980 | P18: 40984 | Q18: 40984
B19: 17 | C19: ミスミ | D19: ミスミ | E19: FSAW-K-12680-788-101005-0057 | F19: 1 | G19: 20560 | H19: =F19*G19 -> 20560 | J19: Web設計ボックス | L19: Z | M19: 40980 | P19: 40984 | Q19: 40984
B20: 17 | C20: ミスミ | D20: ミスミ | E20: PMUF4H5-120-120-1-10-4.5 | F20: 1 | G20: 2050 | H20: =F20*G20 -> 2050 | J20: パンチングメタル | L20: Z | M20: 40980 | P20: 40984 | Q20: 40984
B21: 17 | C21: ミスミ | D21: ミスミ | E21: MRB-260 | F21: 1 | G21: 930 | H21: =F21*G21 -> 930 | J21: DINレール | L21: Z | M21: 40980 | P21: 40984 | Q21: 40984
B22: 17 | C22: ミスミ | D22: ミスミ | E22: C06N-09MS-09FS-CROSS-ES05 | F22: 1 | G22: 2367 | H22: =F22*G22 -> 2367 | J22: RS232Cハーネス | L22: Z | M22: 40980 | P22: 40984 | Q22: 40984
B23: 17 | C23: ミスミ | D23: ミスミ | E23: HD-LN-4-40-05 | F23: 1 | G23: 226 | H23: =F23*G23 -> 226 | J23: Dsubロック金具 | L23: Z | M23: 40980 | P23: 40984 | Q23: 40984
B24: 17 | C24: ミスミ | D24: ミスミ | E24: PSSFGT15-100-M5 | F24: 1 | G24: 960 | H24: =F24*G24 -> 960 | J24: SUS汎用シャフト | L24: Z | M24: 40980 | P24: 40984 | Q24: 40984
B25: 14 | C25: ミスミ | D25: ミスミ | E25: KNCLSS4-8-20 | F25: 2 | G25: 290 | H25: =F25*G25 -> 580 | J25: 金属カラー | L25: Z | M25: 40980 | P25: 40984 | Q25: 40984
... B48: 20 | C48: ミスミ | D48: ミスミ | E48: SCBS4-8 | F48: 2 | G48: 38 | H48: =F48*G48 -> 76 | J48: 座金組込み六角穴付ボルト | L48: X | M48: 40980 | P48: 40984 | Q48: 40984
B50: 3 | C50: 遠藤製作所 | D50: 遠藤製作所 | E50: SS3163 | F50: 1 | G50: 8600 | H50: 8600 | J50: ロボット取付板 | L50: Y | M50: 40980 | P50: 41003 | Q50: 41003
B51: 15 | C51: 遠藤製作所 | D51: 遠藤製作所 | E51: SS3164-01 | F51: 1 | G51: 10800 | H51: =F51*G51 -> 10800 | J51: スターラー台 | L51: Z | M51: 40980 | P51: 41003 | Q51: 41003
B52: 20 | C52: 遠藤製作所 | D52: 遠藤製作所 | E52: SS3165-01 | F52: 1 | G52: 10800 | H52: =F52*G52 -> 10800 | J52: ワーク冶具ベース | L52: X | M52: 40980 | P52: 41003 | Q52: 41003
B53: 14 | C53: 遠藤製作所 | D53: 遠藤製作所 | E53: SS3170 | F53: 1 | G53: 5400 | H53: =F53*G53 -> 5400 | J53: ACJ-3 精密RG取付板 | L53: Z | M53: 40980 | P53: 41003 | Q53: 41003
B54: 3 | C54: 遠藤製作所 | D54: 遠藤製作所 | E54: SS40576 | F54: 1 | G54: 2900 | H54: =F54*G54 -> 2900 | J54: CCD取付板（K） | L54: Y | M54: 40980 | P54: 41003 | Q54: 41003
B55: 3 | C55: 遠藤製作所 | D55: 遠藤製作所 | E55: SS40577 | F55: 1 | G55: 3400 | H55: =F55*G55 -> 3400 | J55: 照明取付板（CA-DRW8M） | L55: Y | M55: 40980 | P55: 41003 | Q55: 41003
B56: 20 | C56: 遠藤製作所 | D56: 遠藤製作所 | E56: SS40578 | F56: 1 | G56: 1980 | H56: =F56*G56 -> 1980 | J56: 位置決めピンΦ8 | L56: X | M56: 40980 | P56: 41003 | Q56: 41003
B57: 20 | C57: 遠藤製作所 | D57: 遠藤製作所 | E57: SS40579 | F57: 1 | G57: 1980 | H57: =F57*G57 -> 1980 | J57: 位置決めピンΦ6 | L57: X | M57: 40980 | P57: 41003 | Q57: 41003
B58: 17 | C58: 遠藤製作所 | D58: 遠藤製作所 | E58: SS40585-01 | F58: 1 | G58: 3800 | H58: =F58*G58 -> 3800 | J58: シャフト板金 | L58: Z | M58: 40980 | P58: 41003 | Q58: 41003
B59: 3 | C59: 遠藤製作所 | D59: 遠藤製作所 | E59: SS40613 | F59: 1 | G59: 3400 | H59: =F59*G59 -> 3400 | J59: CCD取付板（K） ノズル用 | L59: Y | M59: 40980 | P59: 41003 | Q59: 41003
B60: 20 | C60: 遠藤製作所 | D60: 遠藤製作所 | E60: SS40614-03 | F60: 1 | G60: 7800 | H60: =F60*G60 -> 7800 | J60: ノズル位置合わせカメラ用ベース | L60: Z | M60: 40980 | P60: 41003 | Q60: 41003
B61: 20 | C61: 遠藤製作所 | D61: 遠藤製作所 | E61: SS40615 | F61: 2 | G61: 1400 | H61: =F61*G61 -> 2800 | J61: プリズム横押え板金 | L61: Z | M61: 40980 | P61: 41003 | Q61: 41003
B62: 15 | C62: 遠藤製作所 | D62: 遠藤製作所 | E62: 96429-Z01 | F62: 1 | G62: 9800 | H62: =F62*G62 -> 9800 | J62: スターラースペーサ(SW-101N) | L62: Z | M62: 40980 | P62: 41003 | Q62: 41003
B63: 20 | C63: 遠藤製作所 | D63: 遠藤製作所 | E63: SS40618 | F63: 1 | G63: 5900 | H63: 5900 | J63: 捨て打ちﾍﾞｰｽ | L63: Z | M63: 40980 | P63: 41003 | Q63: 41003
B64: 20 | C64: 遠藤製作所 | D64: 遠藤製作所 | E64: SS40619 | F64: 1 | G64: 1900 | H64: 1900 | J64: 捨て打ちﾍﾞｰｽ連結板 | L64: Z | M64: 40980 | P64: 41003 | Q64: 41003
B65: 20 | C65: 遠藤製作所 | D65: 遠藤製作所 | E65: SS40641 | F65: 1 | G65: 5200 | H65: 5200 | J65: ﾌﾟﾘｽﾞﾑ取付板2 | L65: Z | M65: 40980 | P65: 41003 | Q65: 41003
B67: 17 | C67: ニットクエンジニヤリング | D67: ニットクエンジニヤリング | E67: 制御盤組立配線費 | F67: 1 | G67: 22500 | H67: =F67*G67 -> 22500 | K67: 見積りNo：12-02666-2 | L67: Z | P67: 40996 | Q67: 斉藤氏引取
B68: 17 | C68: ニットクエンジニヤリング | D68: ニットクエンジニヤリング | E68: 出精値引き | F68: 1 | G68: -500 | H68: =F68*G68 -> -500 | K68: 見積りNo：12-02666-2 | L68: Z | P68: 40996

Sheet 【97185】 ソニーEMCS美濃加茂 原価一覧
B2: お客先名 | E2: ソニー美濃加茂 | G2: 合計金額 | J2: =SUM(H:H) -> 2590
B3: 担当営業 | E3: 真保
B4: 受注番号 | E4: 97185
B5: 希望納期 | E5: 40991
B6: 最終納品
B8: 見積り分類 | C8: メーカー | D8: 仕入先 | E8: 品名 / 型式 | F8: 数量 | G8: 単価 | H8: 金額 | I8: 分類合計 | J8: 詳細 | K8: 備考 | L8: 技術分類 | M8: 発注日 | N8: 発注 | O8: 納期 | P8: 入荷予定日 | Q8: 入荷日
B9: 4,5 | C9: ミスミ | D9: ミスミ | E9: NEDJ-PT-SB-9-1 | F9: 1 | G9: 1990 | H9: =F9*G9 -> 1990 | J9: Dsubコネクタハーネス | L9: Z | M9: 40987 | P9: 40990 | Q9: 40990
B10: 4,5 | C10: 三和コネクタ研究所 | D10: スズデン | E10: SCK-1604A | F10: 1 | G10: 600 | H10: =F10*G10 -> 600 | J10: コネクタ | L10: Z | M10: 40987 | P10: 40991 | Q10: 40991
H11: =F11*G11 -> 0
H12: =F12*G12 -> 0
H13: =F13*G13 -> 0
H14: =F14*G14 -> 0
H15: =F15*G15 -> 0
H16: =F16*G16 -> 0
H17: =F17*G17 -> 0
H18: =F18*G18 -> 0
H19: =F19*G19 -> 0
H20: =F20*G20 -> 0
H21: =F21*G21 -> 0
H22: =F22*G22 -> 0
... H35: =F35*G35 -> 0

Sheet 【97487】ホシデン（松本正） 原価一覧
B2: お客先名 | E2: ホシデン（松本正） | G2: 合計金額 | J2: =SUM(H:H) -> 146933
B3: 担当営業 | E3: 神田
B4: 受注番号 | E4: 97487
B5: 希望納期 | E5: 41005
B6: 最終納品
B8: 見積り分類 | C8: メーカー | D8: 仕入先 | E8: 品名 / 型式 | F8: 数量 | G8: 単価 | H8: 金額 | I8: 分類合計 | J8: 詳細 | K8: 備考 | L8: 技術分類 | M8: 発注日 | N8: 発注 | O8: 納期 | P8: 入荷予定日 | Q8: 入荷日
C9: ミスミ | D9: ミスミ | E9: XSG25-CR | F9: 2 | G9: 15500 | H9: =F9*G9 -> 31000 | J9: Xステージ（リニアボール） | L9: Y | M9: 40995 | P9: 41002 | Q9: 41002
C10: ミスミ | D10: ミスミ | E10: FWSSS-D7-V2-T2 | F10: 4 | G10: 280 | H10: =F10*G10 -> 1120 | J10: フリーワッシャ | L10: Y | M10: 40995 | P10: 41002 | Q10: 41002
C11: ミスミ | D11: ミスミ | E11: SP-S3-10 | F11: 2 | G11: 210 | H11: =F11*G11 -> 420 | J11: パイプスペーサ | L11: X | M11: 40995 | P11: 41002 | Q11: 41002
C12: ミスミ | D12: ミスミ | E12: KBBS4-10 | F12: 10 | G12: 220 | H12: =F12*G12 -> 2200 | J12: 小径頭ボルト | L12: Y | M12: 40995 | P12: 41002 | Q12: 41002
C13: ミスミ | D13: ミスミ | E13: SCB2-6 | F13: 10 | G13: 80 | H13: =F13*G13 -> 800 | J13: 六角穴付ボルト | L13: Y | M13: 40995 | P13: 41002 | Q13: 41002
C14: ミスミ | D14: ミスミ | E14: SCB2-10 | F14: 10 | G14: 85 | H14: =F14*G14 -> 850 | J14: 六角穴付ボルト | L14: Y | M14: 40995 | P14: 41002 | Q14: 41002
C15: ミスミ | D15: ミスミ | E15: AXSH212-VC-1PD2-2EB-1.5-1AC-2DA-F | F15: 1 | G15: 6615 | H15: =F15*G15 -> 6615 | J15: FAスイッチBOX | K15: 納品済 | L15: Z | M15: 在庫使用
C16: ミスミ | D16: ミスミ | E16: @ECHN-20061106-00010 | F16: 2 | G16: 2814 | H16: =F16*G16 -> 5628 | J16: Webハーネス | K16: 納品済 | L16: Z | M16: 在庫使用
H17: =F17*G17 -> 0
C18: タイショー | D18: タイショー | E18: 97487-X01 | F18: 1 | G18: 28900 | H18: =F18*G18 -> 28900 | J18: ロボットベース | L18: X | M18: 40995 | Q18: 41008
C19: タイショー | D19: タイショー | E19: 97487-X02 | F19: 1 | G19: 2100 | H19: =F19*G19 -> 2100 | J19: ノズル突き当て板 | L19: X | M19: 40995 | Q19: 41008
C20: タイショー | D20: タイショー | E20: 97487-Y01 | F20: 1 | G20: 8700 | H20: =F20*G20 -> 8700 | J20: ロボット取付板 | L20: Y | M20: 40995 | Q20: 41008
C21: タイショー | D21: タイショー | E21: SS40570-作業20 | F21: 2 | G21: 9400 | H21: =F21*G21 -> 18800 | J21: ノズルガイド | L21: Y | M21: 40995 | Q21: 41008
C22: タイショー | D22: タイショー | E22: SS40586 | F22: 1 | G22: 3600 | H22: =F22*G22 -> 3600 | J22: マイクロスペーサブロック | L22: Y | M22: 40995 | Q22: 41008
C23: タイショー | D23: タイショー | E23: SS40587 | F23: 2 | G23: 12500 | H23: =F23*G23 -> 25000 | J23: シリンジホルダ（2168用）W25 | L23: Y | M23: 40995 | Q23: 41008
C24: タイショー | D24: タイショー | E24: SSST002 | F24: 1 | G24: 4200 | H24: =F24*G24 -> 4200 | J24: スペーサブロック | L24: Y | M24: 40995 | Q24: 41008
C25: タイショー | D25: タイショー | E25: SSST003 | F25: 1 | G25: 2100 | H25: =F25*G25 -> 2100 | J25: L板金 | L25: Y | M25: 40995 | Q25: 41008
C26: タイショー | D26: タイショー | E26: SSST004 | F26: 1 | G26: 4900 | H26: =F26*G26 -> 4900 | J26: Y軸変換板 | L26: Y | M26: 40995 | Q26: 41008
H27: =F27*G27 -> 0
C28: SET | D28: SET | E28: 2168 | F28: 2 | H28: =F28*G28 -> 0 | J28: ルアフィッティング | K28: 機材在庫品 | L28: Y
H29: =F29*G29 -> 0
H30: =F30*G30 -> 0
H31: =F31*G31 -> 0
H32: =F32*G32 -> 0
H33: =F33*G33 -> 0
H34: =F34*G34 -> 0
H35: =F35*G35 -> 0
H36: =F36*G36 -> 0
H37: =F37*G37 -> 0
H38: =F38*G38 -> 0
H39: =F39*G39 -> 0
H40: =F40*G40 -> 0
... H67: =F67*G67 -> 0

Sheet 12 02 21【96674】 NDK 原価一覧
B2: お客先名 | E2: NDK | G2: 合計金額 | J2: =SUM(H:H) -> 5302920
B3: 担当営業 | E3: 青木
B4: 受注番号 | E4: 96674
B5: 希望納期 | E5: 40982
B6: 最終納品
B8: 見積り分類 | C8: メーカー | D8: 仕入先 | E8: 品名 / 型式 | F8: 数量 | G8: 単価 | H8: 金額 | I8: 分類合計 | J8: 詳細 | K8: 備考 | L8: 技術分類 | M8: 発注日 | N8: 発注 | O8: 納期 | P8: 入荷予定日 | Q8: 入荷日
B9: 1 | C9: Asymtek | D9: Asymtek | E9: ZDA-1420510 | F9: 2 | H9: =F9*G9 -> 0
B10: 2 | C10: Asymtek | D10: Asymtek | E10: ZDA-2710370 | F10: 2 | H10: =F10*G10 -> 0
B11: 3 | C11: Asymtek | D11: Asymtek | E11: ZDA-2410321 | F11: 2 | H11: =F11*G11 -> 0
B12: 4 | C12: Asymtek | D12: Asymtek | E12: MT-30005-P67 | F12: 2 | H12: =F12*G12 -> 0
B13: 5 | C13: 蛇の目 | D13: 蛇の目 | E13: JR2203NH | F13: 2 | G13: 360000 | H13: =F13*G13 -> 720000 | K13: ﾀﾞｲﾔ直送(3/7着） | M13: 40960
B14: 5 | C14: 蛇の目 | D14: 蛇の目 | E14: 荷造り運賃 | F14: 2 | G14: 10000 | H14: =F14*G14 -> 20000 | M14: 40960
B15: 6 | C15: 蛇の目 | D15: 蛇の目 | E15: COM2増設 | F15: 2 | G15: 20000 | H15: =F15*G15 -> 40000 | M15: 40960
B16: 7 | C16: 蛇の目 | D16: 蛇の目 | E16: JR-TB | F16: 2 | G16: 38000 | H16: =F16*G16 -> 76000 | K16: ﾀﾞｲﾔ直送 | M16: 在庫使用
B17: 8 | C17: パナソニック | D17: 蛇の目 | E17: A110 | F17: 2 | G17: 155400 | H17: =F17*G17 -> 310800 | J17: ANMA110 | K17: ﾀﾞｲﾔ直送(3/7着） | L17: Z | M17: 40960
B18: 8 | C18: パナソニック | D18: 蛇の目 | E18: RS232C | F18: 2 | G18: 12000 | H18: =F18*G18 -> 24000 | J18: 960536106 | K18: ﾀﾞｲﾔ直送(3/7着） | L18: Z | M18: 40960
B19: 8 | C19: パナソニック | D19: 蛇の目 | E19: 送料 | F19: 2 | G19: 1000 | H19: =F19*G19 -> 2000 | J19: - | L19: Z | M19: 40960
B20: 9 | C20: パナソニック | D20: 蛇の目 | E20: CSマウントカメラ | F20: 2 | G20: 54600 | H20: =F20*G20 -> 109200 | J20: ANM832 | K20: ﾀﾞｲﾔ直送(3/7着） | L20: Z | M20: 40960
B21: 10 | C21: パナソニック | D21: 蛇の目 | E21: 操作キーパット | F21: 2 | G21: 7900 | H21: =F21*G21 -> 15800 | J21: ANM85202 | K21: ﾀﾞｲﾔ直送(3/7着） | L21: Z | M21: 40960
B22: 11 | C22: パナソニック | D22: 松下制御テクノ | E22: レンズ | F22: 2 | G22: 23000 | H22: =F22*G22 -> 46000 | J22: ANB846NL | L22: Z | M22: 40960 | P22: 40966 | Q22: 40966
B23: 12 | C23: オプトアート | D23: 都機工 | E23: リアコンバーターレンズ | F23: 2 | G23: 10800 | H23: =F23*G23 -> 21600 | J23: TVR02 | L23: Z | M23: 40960 | P23: 40967 | Q23: 40967
B24: 12 | C24: オプトアート | D24: 都機工 | E24: 送料 | F24: 2 | G24: 1000 | H24: =F24*G24 -> 2000 | J24: - | L24: Z | M24: 40960 | P24: 40967
B25: 12 | C25: VSテクノロジー | D25: VSテクノロジー | E25: 中間リング | F25: 4 | G25: 1380 | H25: =F25*G25 -> 5520 | J25: SV-EXR10 | L25: Z | M25: 40960 | P25: 40973 | Q25: 40973
B26: 13 | C26: CCS | D26: CCS | E26: LED安定照明器 | F26: 2 | G26: 44000 | H26: =F26*G26 -> 88000 | J26: LDR2-32RD | L26: Z | M26: 40960 | P26: 40973 | Q26: 40973
B27: 13 | C27: CCS | D27: CCS | E27: コントローラー | F27: 2 | G27: 13600 | H27: =F27*G27 -> 27200 | J27: PSB-512VL | L27: Z | M27: 40960 | P27: 40973 | Q27: 40973
B28: 13 | C28: CCS | D28: CCS | E28: ケーブル | F28: 2 | G28: 2400 | H28: =F28*G28 -> 4800 | J28: CB-2 | L28: Z | M28: 40960 | P28: 40973 | Q28: 40973
B29: 14 | C29: オジックとダイア | D29: オジックとダイア | E29: 搬送及び制御機構 | F29: 2 | G29: 1895000 | H29: =F29*G29 -> 3790000 | J29: 搬送装置 | K29: アシストより発注依頼 | M29: 40960 | P29: 41001
B30: 15 | E30: 調整費 | F30: 2 | H30: =F30*G30 -> 0
B31: 16 | E31: 諸経費 | F31: 2 | H31: =F31*G31 -> 0
B32: 17 | E32: 特別値引き | F32: 2

Sheet 12.01.20【94175】 NDK 原価一覧
B2: お客先名 | E2: NDK | G2: 合計金額 | J2: =SUM(H:H) -> 5302920
B3: 担当営業 | E3: 青木
B4: 受注番号 | E4: 94175
B5: 希望納期 | E5: 40955
B6: 最終納品
B8: 見積り分類 | C8: メーカー | D8: 仕入先 | E8: 品名 / 型式 | F8: 数量 | G8: 単価 | H8: 金額 | I8: 分類合計 | J8: 詳細 | K8: 備考 | L8: 技術分類 | M8: 発注日 | N8: 発注 | O8: 納期 | P8: 入荷予定日 | Q8: 入荷日
B9: 1 | C9: Asymtek | D9: Asymtek | E9: ZDA-1420510 | F9: 2 | H9: =F9*G9 -> 0
B10: 2 | C10: Asymtek | D10: Asymtek | E10: ZDA-2710370 | F10: 2 | H10: =F10*G10 -> 0
B11: 3 | C11: Asymtek | D11: Asymtek | E11: ZDA-2410321 | F11: 2 | H11: =F11*G11 -> 0
B12: 4 | C12: Asymtek | D12: Asymtek | E12: MT-30005-P67 | F12: 2 | H12: =F12*G12 -> 0
B13: 5 | C13: 蛇の目 | D13: 蛇の目 | E13: JR2203NH | F13: 2 | G13: 360000 | H13: =F13*G13 -> 720000 | K13: ﾀﾞｲﾔ直送(2/20着） | M13: 40931
B14: 5 | C14: 蛇の目 | D14: 蛇の目 | E14: 荷造り運賃 | F14: 2 | G14: 10000 | H14: =F14*G14 -> 20000 | M14: 40931
B15: 6 | C15: 蛇の目 | D15: 蛇の目 | E15: COM2増設 | F15: 2 | G15: 20000 | H15: =F15*G15 -> 40000 | M15: 40931
B16: 7 | C16: 蛇の目 | D16: 蛇の目 | E16: JR-TB | F16: 2 | G16: 38000 | H16: =F16*G16 -> 76000 | K16: ﾀﾞｲﾔ直送 | M16: 在庫使用
B17: 8 | C17: パナソニック | D17: 蛇の目 | E17: A110 | F17: 2 | G17: 155400 | H17: =F17*G17 -> 310800 | J17: ANMA110 | K17: ﾀﾞｲﾔ直送(2/20着） | L17: Z | M17: 40931
B18: 8 | C18: パナソニック | D18: 蛇の目 | E18: RS232C | F18: 2 | G18: 12000 | H18: =F18*G18 -> 24000 | J18: 960536106 | K18: ﾀﾞｲﾔ直送(2/20着） | L18: Z | M18: 40931
B19: 8 | C19: パナソニック | D19: 蛇の目 | E19: 送料 | F19: 2 | G19: 1000 | H19: =F19*G19 -> 2000 | J19: - | L19: Z | M19: 40931
B20: 9 | C20: パナソニック | D20: 蛇の目 | E20: CSマウントカメラ | F20: 2 | G20: 54600 | H20: =F20*G20 -> 109200 | J20: ANM832 | K20: ﾀﾞｲﾔ直送(2/20着） | L20: Z | M20: 40931
B21: 10 | C21: パナソニック | D21: 蛇の目 | E21: 操作キーパット | F21: 2 | G21: 7900 | H21: =F21*G21 -> 15800 | J21: ANM85202 | K21: ﾀﾞｲﾔ直送(2/20着） | L21: Z | M21: 40931
B22: 11 | C22: パナソニック | D22: 松下制御テクノ | E22: レンズ | F22: 2 | G22: 23000 | H22: =F22*G22 -> 46000 | J22: ANB846NL | L22: Z | M22: 40931 | P22: 40935 | Q22: 40935
B23: 12 | C23: オプトアート | D23: 都機工 | E23: リアコンバーターレンズ | F23: 2 | G23: 10800 | H23: =F23*G23 -> 21600 | J23: TVR02 | L23: Z | M23: 40931 | P23: 40942 | Q23: 40940
B24: 12 | C24: オプトアート | D24: 都機工 | E24: 送料 | F24: 2 | G24: 1000 | H24: =F24*G24 -> 2000 | J24: - | L24: Z | M24: 40931
B25: 12 | C25: VSテクノロジー | D25: VSテクノロジー | E25: 中間リング | F25: 4 | G25: 1380 | H25: =F25*G25 -> 5520 | J25: SV-EXR10 | L25: Z | M25: 40931 | P25: 40955 | Q25: 40955
B26: 13 | C26: CCS | D26: CCS | E26: LED安定照明器 | F26: 2 | G26: 44000 | H26: =F26*G26 -> 88000 | J26: LDR2-32RD | L26: Z | M26: 40931 | P26: 40955 | Q26: 40955
B27: 13 | C27: CCS | D27: CCS | E27: コントローラー | F27: 2 | G27: 13600 | H27: =F27*G27 -> 27200 | J27: PSB-512VL | L27: Z | M27: 40931 | P27: 40955 | Q27: 40955
B28: 13 | C28: CCS | D28: CCS | E28: ケーブル | F28: 2 | G28: 2400 | H28: =F28*G28 -> 4800 | J28: CB-2 | L28: Z | M28: 40931 | P28: 40955 | Q28: 40955
B29: 14 | C29: オジックとダイア | D29: オジックとダイア | E29: 搬送及び制御機構 | F29: 2 | G29: 1895000 | H29: =F29*G29 -> 3790000 | J29: 搬送装置 | M29: 40924 | P29: 40983
B30: 15 | E30: 調整費 | F30: 2 | H30: =F30*G30 -> 0
B31: 16 | E31: 諸経費 | F31: 2 | H31: =F31*G31 -> 0
B32: 17 | E32: 特別値引き | F32: 2

Sheet 12.02.15 【96117】 トーコテック原価一覧
B2: お客先名 | E2: ㈱トーコーテック | G2: 合計金額 | J2: =SUM(H:H) -> 123940
B3: 担当営業 | E3: 福島
B4: 受注番号 | E4: 96117
B5: 希望納期 | E5: 40970
B6: 最終納品 | E6: 40975
B8: 見積り分類 | C8: メーカー | D8: 仕入先 | E8: 品名 / 型式 | F8: 数量 | G8: 単価 | H8: 金額 | I8: 分類合計 | J8: 詳細 | K8: 備考 | L8: 技術分類 | M8: 発注日 | N8: 発注 | O8: 納期 | P8: 入荷予定日 | Q8: 入荷日
B9: 2 | C9: 蛇の目 | D9: 蛇の目 | E9: JR2303N | F9: 1 | J9: ロボット | K9: 在庫（確認中）
B10: 3 | C10: 蛇の目 | D10: 蛇の目 | E10: JR-TB | F10: 1 | H10: =F10*G10 -> 0 | J10: ティーチングボックス | K10: 在庫品
B11: 4 | C11: ミスミ | D11: ミスミ | E11: I/Oケーブル | F11: 1 | H11: =F11*G11 -> 0 | K11: 在庫品
B12: 5 | C12: 遠藤製作所 | D12: 遠藤製作所 | E12: 96117-Y01 | F12: 1 | G12: 3800 | H12: =F12*G12 -> 3800 | J12: ロボット取付板 | M12: 40954 | N12: 済 | O12: 40969 | P12: 40969 | Q12: 40975
B13: 5 | C13: 遠藤製作所 | D13: 遠藤製作所 | E13: 96117-Y02 | F13: 2 | G13: 6900 | H13: =F13*G13 -> 13800 | J13: 梁ブロック | M13: 40954 | N13: 済 | O13: 40969 | P13: 40969 | Q13: 40975
B14: 5 | C14: 遠藤製作所 | D14: 遠藤製作所 | E14: 96117-Y03 | F14: 1 | G14: 4500 | H14: =F14*G14 -> 4500 | J14: ATD固定ブロック上 | M14: 40954 | N14: 済 | O14: 40969 | P14: 40969 | Q14: 40975
B15: 5 | C15: 遠藤製作所 | D15: 遠藤製作所 | E15: 96117-Y04 | F15: 1 | G15: 9800 | H15: =F15*G15 -> 9800 | J15: ATD固定ブロック下 | M15: 40954 | N15: 済 | O15: 40969 | P15: 40969 | Q15: 40975
C16: 遠藤製作所 | D16: 遠藤製作所 | E16: 96117-Y05 | F16: 1 | G16: 7200 | H16: =F16*G16 -> 7200 | J16: ATD固定板金 | M16: 40954 | N16: 済 | O16: 40969 | P16: 40969 | Q16: 40975
B17: 7 | C17: 蛇の目 | D17: 蛇の目 | E17: PCソフト（JR C-points） | F17: 1 | G17: 30000 | H17: =F17*G17 -> 30000 | K17: 手配願います。 | M17: 40954 | P17: 40970 | Q17: 40970
B18: 8 | C18: 機材 | D18: 機材 | E18: ATD300CB-S | F18: 1 | H18: =F18*G18 -> 0 | M18: 在庫使用
B19: 9 | C19: EFD | D19: EFD | E19: 7018555 | F19: 1 | H19: =F19*G19 -> 0 | J19: 5180-Bポリプロピレンノズル
B20: 10 | C20: EFD | D20: EFD | E20: 7514-2S | F20: 1 | H20: =F20*G20 -> 0 | J20: スペシャルノズル用チップアダプタ
B21: 11 | E21: 設計・組立調整費 | F21: 1 | H21: =F21*G21 -> 0
B22: 12 | E22: 搬入・据付調整費 | F22: 1 | H22: =F22*G22 -> 0
B23: 13 | D23: ﾐｽﾐ | E23: AXSH212-VC-1PD2-2EB-3.0-1AC-2DA-F | F23: 1 | G23: 6840 | H23: =F23*G23 -> 6840 | J23: FAｽｲｯﾁﾎﾞｯｸｽ | M23: 40974 | P23: 40980 | Q23: 40982
B24: 14 | D24: ﾐｽﾐ | E24: XYSG40-CR | F24: 1 | G24: 32000 | H24: 32000 | J24: XYｽﾃ-ｼﾞ XYSG | M24: 済 | P24: 40970
B25: 15 | D25: ﾐｽﾐ | E25: XSG40-CR | F25: 1 | G25: 16000 | H25: 16000 | J25: XYｽﾃ-ｼﾞ XSG | M25: 済 | P25: 40970
H27: =F27*G27 -> 0
H28: =F28*G28 -> 0
H29: =F29*G29 -> 0

Sheet 12.02.20 【96346】テルモ 原価一覧
B2: お客先名 | E2: テルモ | G2: 合計金額 | J2: =SUM(H:H) -> 27700
B3: 担当営業 | E3: 山澤
B4: 受注番号 | E4: 96346
B5: 希望納期 | E5: 40973
B6: 最終納品 | E6: 40991
B8: 見積り分類 | C8: メーカー | D8: 仕入先 | E8: 品名 / 型式 | F8: 数量 | G8: 単価 | H8: 金額 | I8: 分類合計 | J8: 詳細 | K8: 備考 | L8: 技術分類 | M8: 発注日 | N8: 発注 | O8: 納期 | P8: 入荷予定日 | Q8: 入荷日
B9: 7 | C9: 遠藤製作所 | D9: 遠藤製作所 | E9: 96346-Y01 | F9: 1 | G9: 6800 | H9: =F9*G9 -> 6800 | J9: ツール板 | M9: 40959 | P9: 40973 | Q9: 40970
H10: =F10*G10 -> 0
B11: 5.6 | C11: ミスミ | D11: ミスミ | E11: %WRFH-4050-120110-17 | F11: 1 | G11: 20900 | H11: =F11*G11 -> 20900 | J11: 特注ハーネス | M11: 40959 | P11: 40973 | Q11: 40973
H12: =F12*G12 -> 0
H13: =F13*G13 -> 0
H14: =F14*G14 -> 0
H15: =F15*G15 -> 0
H16: =F16*G16 -> 0
H17: =F17*G17 -> 0
H18: =F18*G18 -> 0
H19: =F19*G19 -> 0
H20: =F20*G20 -> 0
H21: =F21*G21 -> 0
H22: =F22*G22 -> 0
H23: =F23*G23 -> 0
... H30: =F30*G30 -> 0

Sheet 【97281】 東亜電機（シャープ多気）
B2: お客先名 | E2: 東亜電気 | G2: 合計金額 | J2: =SUM(H:H) -> 68118330
B4: お客先名 | E4: 東亜電気（シャープ多気） | G4: 合計金額 | J4: =SUM(H:H) -> 68118330
B5: 担当営業 | E5: 真保
B6: 受注番号 | E6: 97281 | G6: 備考
B7: 希望納期 | E7: 41015
B8: 最終納品
B10: 見積り分類 | C10: メーカー | D10: 仕入先 | E10: 品名 / 型式 | F10: 数量 | G10: 単価 | H10: 金額 | I10: 分類合計 | J10: 詳細 | K10: 備考 | L10: 技術分類 | M10: 発注日 | N10: 発注 | O10: 納期 | P10: 入荷予定日 | Q10: 入荷日
C11: 蛇の目 | D11: 蛇の目 | E11: JR2203N | F11: 130 | G11: 290000 | H11: =F11*G11 -> 37700000 | K11: 上野部長対応 | M11: 40981 | P11: 4/9-70台（引き取り） | Q11: 4/9-70・4/23-60
C12: 蛇の目 | D12: 蛇の目 | E12: 荷造り運賃 | H12: =F12*G12 -> 0 | M12: 40981 | P12: 4/23-60台（引き取り）
C13: 蛇の目 | D13: 蛇の目 | E13: JR-TB | H13: =F13*G13 -> 0 | M13: 在庫使用
C14: 蛇の目 | D14: 蛇の目 | E14: ﾌﾟﾘﾝﾄ基板 | F14: 3 | G14: 31000 | H14: 93000 | M14: 41011 | P14: 41017 | Q14: 41016
C16: SMC | D16: 都機工 | E16: ＭＧＪ6-10 | F16: 264 | G16: 4840 | H16: =F16*G16 -> 1277760 | K16: 4個予備部品 | M16: 40991 | P16: 4/5 ,11 | Q16: 4/5-144･4/10-119・4/13-1
C17: SMC | D17: 都機工 | E17: CXSJM6-10 | F17: 264 | G17: 4000 | H17: =F17*G17 -> 1056000 | K17: 4個予備部品 | M17: 40991 | P17: 4/5 ,11 | Q17: 4/5-144・4/10-119・4/13-1
C18: SMC | D18: 都機工 | E18: KJL04-M3 | F18: 1060 | G18: 253 | H18: =F18*G18 -> 268180 | K18: 4個予備部品 | M18: 40991 | P18: 4/5 ,11 | Q18: 4/5-576･4/10-480
C19: SMC | D19: 都機工 | E19: KJU04-00 | F19: 260 | G19: 235 | H19: =F19*G19 -> 61100 | M19: 40991 | P19: 4/5 ,11 | Q19: 4/5-72・4/6-72・4/10-116
C20: SMC | D20: 都機工 | E20: AS1002F-04 | F20: 260 | G20: 650 | H20: =F20*G20 -> 169000 | M20: 40991 | P20: 4/5 ,11 | Q20: 4/5-72・4/6-72・4/10-116
C21: SMC | D21: 都機工 | E21: AW10-ALQ01 | F21: 134 | G21: 3327 | H21: =F21*G21 -> 445818 | K21: 4個予備部品 | M21: 40991 | P21: 4/5 ,11 | Q21: 4/5-72・4/10-62
C22: SMC | D22: 都機工 | E22: SS5YJ3-S41-02-C4 | F22: 134 | G22: 2550 | H22: =F22*G22 -> 341700 | K22: 4個予備部品 | M22: 40991 | P22: 4/5 ,11 | Q22: 4/5-72・4/10-62
C23: SMC | D23: 都機工 | E23: SYJ3140-5MOZ | F23: 268 | G23: 3950 | H23: =F23*G23 -> 1058600 | K23: 4個予備部品 | M23: 40991 | P23: 4/5 ,11 | Q23: 4/5-144･4/10-124
C24: SMC | D24: 都機工 | E24: SY100-30-4A-6 | F24: 268 | G24: 80 | H24: =F24*G24 -> 21440 | K24: 4個予備部品 | M24: 40991 | P24: 4/5 ,11 | Q24: 4/5-144･4/10-124
C25: SMC | D25: 都機工 | E25: KQ2L04-01S | F25: 130 | G25: 169 | H25: =F25*G25 -> 21970 | M25: 40991 | P25: 4/5 ,11 | Q25: 4/5-72・4/10-58
C26: SMC | D26: 都機工 | E26: AN10-01 | F26: 260 | G26: 250 | H26: =F26*G26 -> 65000 | M26: 40991 | P26: 4/5 ,11 | Q26: 4/5-144･4/10-116
C27: SMC | D27: 都機工 | E27: KJU06-00 | F27: 260 | G27: 245 | H27: =F27*G27 -> 63700 | M27: 40991 | P27: 4/5 ,11 | Q27: 4/5-72・4/6-72・4/10-116
C28: SUNX | D28: 都機工 | E28: EX-14A | F28: 264 | G28: 3000 | H28: =F28*G28 -> 792000 | K28: 4個予備部品 | M28: 40991 | P28: 4/5 ,11 | Q28: 4/5-144･4/10-120
C29: SUNX | D29: 都機工 | E29: MS-EX10-1 | F29: 260 | G29: 170 | H29: =F29*G29 -> 44200 | M29: 40991 | P29: 4/5 ,11 | Q29: 4/5-144･4/10-116
D30: 都機工 | E30: SG30 | F30: 1 | G30: 11200 | H30: =F30*G30 -> 11200 | M30: 40996 | P30: 40998 | Q30: 40998
D31: 都機工 | E31: 2046S DG | F31: 1 | G31: 3576 | H31: =F31*G31 -> 3576 | M31: 40996 | P31: 40998 | Q31: 40998
D32: 都機工 | E32: KJU04-00 | F32: 260 | G32: 235 | H32: =F32*G32 -> 61100 | M32: 41010 | P32: 41012 | Q32: 41012
D33: 都機工 | E33: 2046S DG | F33: 3 | G33: 3576 | H33: =F33*G33 -> 10728 | M33: 41010 | P33: 41012 | Q33: 41012
C35: MISUMI | D35: MISUMI | E35: CRKB3-12 | F35: 100 | G35: 17 | H35: 1700 | K35: ｼﾞｭｼﾛｰﾚｯﾄﾈｼﾞ (CRKB) | Q35: 41020
C36: MISUMI | D36: MISUMI | E36: 350689-1 | F36: 1 | G36: 817 | H36: 817 | K36: ﾕﾆﾊﾞｰｻﾙﾒｰﾃﾝﾛｯｸ(ｺﾝﾀｸﾄ) | Q36: 41020
C37: MISUMI | D37: MISUMI | E37: 350689-1 | F37: 2 | G37: 817 | H37: 1634 | K37: ﾕﾆﾊﾞｰｻﾙﾒｰﾃﾝﾛｯｸ(ｺﾝﾀｸﾄ) | P37: 41003 | Q37: 41020
C38: MISUMI | D38: MISUMI | E38: 350780-1-20P | F38: 7 | G38: 1083 | H38: 7581 | K38: ﾕﾆﾊﾞｰｻﾙﾒｰﾃﾝﾛｯｸ(ｿｹｯﾄ) | Q38: 41020
C39: MISUMI | D39: MISUMI | E39: BOX-SCB4-25* | F39: 2 | G39: 3200 | H39: 6400 | K39: ｷｬｯﾌﾟﾎﾞﾙﾄ ﾊｺﾊﾝﾊﾞｲ (SCB-BOX) | Q39: 41020
C40: MISUMI | D40: MISUMI | E40: BOX-SCB3-25* | F40: 1 | G40: 2800 | H40: 2800 | K40: ｷｬｯﾌﾟﾎﾞﾙﾄ ﾊｺﾊﾝﾊﾞｲ (SCB-BOX) | Q40: 41020
C41: MISUMI | D41: MISUMI | E41: SCB3-25 | F41: 100 | G41: 9 | H41: 900 | K41: ﾈｼﾞ CB･SCB･BCB･SBCB･GUTB | Q41: 41020
C42: MISUMI | D42: MISUMI | E42: BOX-SCB4-25* | F42: 1 | G42: 3200 | H42: 3200 | K42: ｷｬｯﾌﾟﾎﾞﾙﾄ ﾊｺﾊﾝﾊﾞｲ (SCB-BOX) | Q42: 41020
C43: MISUMI | D43: MISUMI | E43: CRKB3-12 | F43: 220 | G43: 17 | H43: 3740 | K43: ｼﾞｭｼﾛｰﾚｯﾄﾈｼﾞ (CRKB) | Q43: 41020
C44: MISUMI | D44: MISUMI | E44: BOX-SKNTR4* | F44: 1 | G44: 2800 | H44: 2800 | K44: ﾅｯﾄ ﾊｺﾊﾝﾊﾞｲ(SLBNR-BOX) | Q44: 41020
C45: MISUMI | D45: MISUMI | E45: BOX-SCB4-8* | F45: 4 | G45: 3600 | H45: 14400 | K45: ｷｬｯﾌﾟﾎﾞﾙﾄ ﾊｺﾊﾝﾊﾞｲ (SCB-BOX) | Q45: 41020
C46: MISUMI | D46: MISUMI | E46: SCB3-5 | F46: 100 | G46: 10 | H46: 1000 | K46: ﾈｼﾞ CB･SCB･BCB･SBCB･GUTB | Q46: 41020
C47: MISUMI | D47: MISUMI | E47: SCB3-6 | F47: 100 | G47: 6 | H47: 600 | K47: ﾈｼﾞ CB･SCB･BCB･SBCB･GUTB | Q47: 41020
C48: MISUMI | D48: MISUMI | E48: BOX-MSSFS4-8 | F48: 1 | G48: 2900 | H48: 2900 | K48: (ﾊｺ)ﾛｯｶｸｱﾅﾂｷﾄﾒﾈｼﾞ(BOX-MSSFS) | Q48: 41020
C49: MISUMI | D49: MISUMI | E49: BOX-SCB2-5 | F49: 1 | G49: 4400 | H49: 4400 | K49: ｷｬｯﾌﾟﾎﾞﾙﾄ ﾊｺﾊﾝﾊﾞｲ (SCB-BOX) | Q49: 41020
C50: MISUMI | D50: MISUMI | E50: BOX-SCB2-10 | F50: 1 | G50: 4900 | H50: 4900 | K50: ｷｬｯﾌﾟﾎﾞﾙﾄ ﾊｺﾊﾝﾊﾞｲ (SCB-BOX) | P50: 41001 | Q50: 41020
C51: MISUMI | D51: MISUMI | E51: BOX-SCB3-5 | F51: 1 | G51: 3800 | H51: 3800 | K51: ｷｬｯﾌﾟﾎﾞﾙﾄ ﾊｺﾊﾝﾊﾞｲ (SCB-BOX) | P51: 41001 | Q51: 41020
C52: MISUMI | D52: MISUMI | E52: BOX-SCB3-6* | F52: 1 | G52: 3200 | H52: 3200 | K52: ｷｬｯﾌﾟﾎﾞﾙﾄ ﾊｺﾊﾝﾊﾞｲ (SCB-BOX) | P52: 41001 | Q52: 41020
C53: MISUMI | D53: MISUMI | E53: BOX-SCB3-8* | F53: 1 | G53: 3300 | H53: 3300 | K53: ｷｬｯﾌﾟﾎﾞﾙﾄ ﾊｺﾊﾝﾊﾞｲ (SCB-BOX) | P53: 41001 | Q53: 41020
C54: MISUMI | D54: MISUMI | E54: BOX-SCB3-15* | F54: 2 | G54: 3700 | H54: 7400 | K54: ｷｬｯﾌﾟﾎﾞﾙﾄ ﾊｺﾊﾝﾊﾞｲ (SCB-BOX) | P54: 41001 | Q54: 41020
C55: MISUMI | D55: MISUMI | E55: BOX-SCB4-6* | F55: 1 | G55: 3900 | H55: 3900 | K55: ｷｬｯﾌﾟﾎﾞﾙﾄ ﾊｺﾊﾝﾊﾞｲ (SCB-BOX) | P55: 41003 | Q55: 41020
C56: MISUMI | D56: MISUMI | E56: BOX-SCB4-8* | F56: 2 | G56: 3600 | H56: 7200 | K56: ｷｬｯﾌﾟﾎﾞﾙﾄ ﾊｺﾊﾝﾊﾞｲ (SCB-BOX) | P56: 41003 | Q56: 41020
C57: MISUMI | D57: MISUMI | E57: BOX-SCB4-10* | F57: 2 | G57: 3800 | H57: 7600 | K57: ｷｬｯﾌﾟﾎﾞﾙﾄ ﾊｺﾊﾝﾊﾞｲ (SCB-BOX) | M57: 40990 | P57: 41005 | Q57: 41020
C58: MISUMI | D58: MISUMI | E58: BOX-SCB4-12* | F58: 2 | G58: 4000 | H58: 8000 | K58: ｷｬｯﾌﾟﾎﾞﾙﾄ ﾊｺﾊﾝﾊﾞｲ (SCB-BOX) | M58: 40990 | P58: 41015 | Q58: 41020
C59: MISUMI | D59: MISUMI | E59: BOX-SCB4-15* | F59: 1 | G59: 4400 | H59: 4400 | K59: ｷｬｯﾌﾟﾎﾞﾙﾄ ﾊｺﾊﾝﾊﾞｲ (SCB-BOX) | P59: 41004 | Q59: 41020
C60: MISUMI | D60: MISUMI | E60: BOX-SCB5-25* | F60: 1 | G60: 5440 | H60: 5440 | K60: ｷｬｯﾌﾟﾎﾞﾙﾄ ﾊｺﾊﾝﾊﾞｲ (SCB-BOX) | P60: 41004 | Q60: 41020
C61: MISUMI | D61: MISUMI | E61: BOX-MSSFS4-8 | F61: 1 | G61: 2900 | H61: 2900 | K61: (ﾊｺ)ﾛｯｶｸｱﾅﾂｷﾄﾒﾈｼﾞ(BOX-MSSFS) | P61: 41004 | Q61: 41020
C62: MISUMI | D62: MISUMI | E62: BOX-SCB5-20* | F62: 1 | G62: 4880 | H62: 4880 | K62: ｷｬｯﾌﾟﾎﾞﾙﾄ ﾊｺﾊﾝﾊﾞｲ (SCB-BOX) | P62: 41004 | Q62: 41020
C63: MISUMI | D63: MISUMI | E63: SCB4-20 | F63: 50 | G63: 16 | H63: 800 | K63: ﾈｼﾞ CB･SCB･BCB･SBCB･GUTB | P63: 41004 | Q63: 41020
C64: MISUMI | D64: MISUMI | E64: SCB4-30 | F64: 50 | G64: 21 | H64: 1050 | K64: ﾈｼﾞ CB･SCB･BCB･SBCB･GUTB | P64: 41004 | Q64: 41020
C65: MISUMI | D65: MISUMI | E65: SCB2.5-15 | F65: 520 | G65: 33 | H65: 17160 | K65: ﾈｼﾞ CB･SCB･BCB･SBCB･GUTB | P65: 41004 | Q65: 41020
C66: MISUMI | D66: MISUMI | E66: RSCB4-8 | F66: 1300 | G66: 6 | H66: 7800 | K66: ﾛｯｶｸﾎﾞﾙﾄ-SUS- RSCB | P66: 41004 | Q66: 41020
C67: MISUMI | D67: MISUMI | E67: XSG25-CR | F67: 30 | G67: 15500 | H67: 465000 | K67: Xｽﾃｰｼﾞ XSG | P67: 41004 | Q67: 41020
C68: MISUMI | D68: MISUMI | E68: XSG25-CR | F68: 30 | G68: 15500 | H68: 465000 | K68: Xｽﾃｰｼﾞ XSG | P68: 41004 | Q68: 41020
C69: MISUMI | D69: MISUMI | E69: XYSG25-CR | F69: 30 | G69: 31000 | H69: 930000 | K69: XYｽﾃｰｼﾞ XYSG | P69: 41004 | Q69: 41020
C70: MISUMI | D70: MISUMI | E70: XYSG25-CR | F70: 30 | G70: 31000 | H70: 930000 | K70: XYｽﾃｰｼﾞ XYSG | P70: 41004 | Q70: 41020
... C75: MISUMI | D75: MISUMI | E75: CTSV-25036-100P | F75: 5 | G75: 690 | H75: 3450 | K75: ｹｯｿｸﾊﾞﾝﾄﾞ(ﾀｲｺｳ) | P75: 41004 | Q75: 41020
C76: MISUMI | D76: MISUMI | E76: 37104-4080-G00FL-8P | F76: 20 | G76: 1119 | H76: 22380 | K76: E-CONｺﾈｸﾀ | Q76: 41020
C77: MISUMI | D77: MISUMI | E77: 37104-4080-G00FL-8P | F77: 15 | G77: 1119 | H77: 16785 | K77: E-CONｺﾈｸﾀ | P77: 41005 | Q77: 41020
C78: MISUMI | D78: MISUMI | E78: 350689-1 | F78: 6 | G78: 817 | H78: 4902 | K78: ﾕﾆﾊﾞｰｻﾙﾒｰﾃﾝﾛｯｸ(ｺﾝﾀｸﾄ) | P78: 41005 | Q78: 41020
C79: MISUMI | D79: MISUMI | E79: 350780-1-20P | F79: 7 | G79: 1083 | H79: 7581 | K79: ﾕﾆﾊﾞｰｻﾙﾒｰﾃﾝﾛｯｸ(ｿｹｯﾄ) | P79: 41005 | Q79: 41020
C80: MISUMI | D80: MISUMI | E80: CBSTSR3-5 | F80: 1060 | G80: 150 | H80: 159000 | K80: ｺﾞｸﾃｲﾄｳﾎﾞﾙﾄ(CBSTSR) | P80: 41005 | Q80: 41020
C81: MISUMI | D81: MISUMI | E81: MWI-MIL14-ECON5 | F81: 130 | G81: 2347 | H81: 305110 | K81: E-CONｺﾈｸﾀﾍﾝｶﾝﾀﾝｼﾀﾞｲ | Q81: 41020
C82: MISUMI | D82: MISUMI | E82: 37104-3101-000FL-8P | F82: 35 | G82: 1038 | H82: 36330 | K82: E-CONｺﾈｸﾀ | P82: 41010 | Q82: 41020
C83: MISUMI | D83: MISUMI | E83: MSBY8-40 | F83: 130 | G83: 342 | H83: 44460 | K83: ｽﾄﾘｯﾊﾟﾎﾞﾙﾄ (MSBY) | P83: 41010 | Q83: 41020
C84: MISUMI | D84: MISUMI | E84: SLCG5.5-8 | F84: 520 | G84: 70 | H84: 36400 | K84: ｼｮｳｹｲﾛｯｶｸｼﾁｭｳ (SLCG) | P84: 41010 | Q84: 41020
C85: MISUMI | D85: MISUMI | E85: CRKB3-10 | F85: 260 | G85: 17 | H85: 4420 | K85: ｼﾞｭｼﾛｰﾚｯﾄﾈｼﾞ (CRKB) | P85: 41010 | Q85: 41020
C86: MISUMI | D86: MISUMI | E86: SHCDG4-14 | F86: 520 | G86: 132 | H86: 68640 | K86: ﾋﾝｼﾞﾋﾟﾝﾂﾊﾞﾂｷﾄﾒﾜﾄﾒｺﾃｲﾖｳ SHCDG | P86: 41010 | Q86: 41020
C87: MISUMI | D87: MISUMI | E87: AXSH212-VC-1PD2-2EB-1.5-1AC-2DA-F | F87: 5 | G87: 6615 | H87: 33075 | K87: FAｽｲｯﾁﾎﾞｯｸｽ(ｱｾﾝﾌﾞﾙ) | P87: 41022 | Q87: 41020
C88: MISUMI | D88: MISUMI | E88: XSG25-CR | F88: 30 | G88: 15500 | H88: 465000 | K88: Xｽﾃｰｼﾞ XSG | P88: 41022 | Q88: 41020
C89: MISUMI | D89: MISUMI | E89: XSG25-CR | F89: 40 | G89: 15500 | H89: 620000 | K89: Xｽﾃｰｼﾞ XSG | P89: 41022 | Q89: 41020
C90: MISUMI | D90: MISUMI | E90: XYSG25-CR | F90: 30 | G90: 31000 | H90: 930000 | K90: XYｽﾃｰｼﾞ XYSG | Q90: 41020
C91: MISUMI | D91: MISUMI | E91: XYSG25-CR | F91: 40 | G91: 31000 | H91: 1240000 | K91: XYｽﾃｰｼﾞ XYSG | Q91: 41020
C92: MISUMI | D92: MISUMI | E92: AXSH212-VC-1PD2-2EB-1.5-1AC-2DA-F | F92: 125 | G92: 6615 | H92: 826875 | Q92: 41020
C93: MISUMI | D93: MISUMI | E93: PNUIC-REX-USB60F-R | F93: 1 | G93: 5200 | H93: 5200 | Q93: 41039
C94: MISUMI | D94: MISUMI | E94: DGC-9SS | F94: 1 | G94: 203 | H94: 203 | Q94: 41039
C95: MISUMI | D95: MISUMI | E95: PACK-SMIB2.0-2 | F95: 1 | G95: 900 | H95: 900 | Q95: 41039
C96: MISUMI | D96: MISUMI | E96: AXSH212-VC-1PD2-2EB-1.5-1AC-2DA-F | F96: 125 | G96: 6615 | H96: 6615 | P96: 41040 | Q96: 41040
C97: MISUMI | D97: MISUMI | E97: PACK-WSJJ4-2-2 | F97: 1 | G97: 420 | H97: 420 | P97: 41043
C101: タイショー | D101: タイショー | E101: SSAM-X01 | F101: 130 | G101: 11160 | H101: =F101*G101 -> 1450800 | K101: ベース板 | Q101: 41023
C102: タイショー | D102: タイショー | E102: SSAM-X02-1 | F102: 520 | G102: 3990 | H102: =F102*G102 -> 2074800 | K102: 側面アルミブロック | Q102: 41023
C103: タイショー | D103: タイショー | E103: SSAM-X02-2 | F103: 130 | G103: 3160 | H103: =F103*G103 -> 410800 | K103: 中央ブロック（上側） | Q103: 41023
C104: タイショー | D104: タイショー | E104: SSAM-X03 | F104: 130 | G104: 8720 | H104: =F104*G104 -> 1133600 | K104: ワーク治具（上側） | Q104: 41023
C105: タイショー | D105: タイショー | E105: SSAM-X04 | F105: 130 | G105: 8530 | H105: =F105*G105 -> 1108900 | K105: ワーク治具（下側） | Q105: 41023
C106: タイショー | D106: タイショー | E106: SSAM-X05-1 | F106: 260 | G106: 500 | H106: =F106*G106 -> 130000 | K106: 角プレート（上2.5mm）不要品 | Q106: 41023
C107: タイショー | D107: タイショー | E107: SSAM-X05-2 | F107: 260 | G107: 1450 | H107: =F107*G107 -> 377000 | K107: 角プレート（上10mm) | Q107: 41023
C108: タイショー | D108: タイショー | E108: SSAM-X06 | F108: 260 | G108: 1500 | H108: =F108*G108 -> 390000 | K108: 角プレート（下2.5mm) | Q108: 41023
C109: タイショー | D109: タイショー | E109: SSAM-X07 | F109: 130 | G109: 950 | H109: =F109*G109 -> 123500 | K109: 保護プレート | Q109: 41023
C110: タイショー | D110: タイショー | E110: SSAM-X08 | F110: 130 | G110: 3410 | H110: =F110*G110 -> 443300 | K110: Yシリンダ移動プレート | Q110: 41023
C111: タイショー | D111: タイショー | E111: SSAM-X09-1 | F111: 260 | G111: 1920 | H111: =F111*G111 -> 499200 | K111: Xシリンダブラケット | Q111: 41023
C112: タイショー | D112: タイショー | E112: SSAM-X09-2 | F112: 260 | G112: 1320 | H112: =F112*G112 -> 343200 | K112: Yシリンダブラケット | Q112: 41023
...

Sheet 【97373】タイコエレクトロニクス（11号機） 原価一覧
B2: お客先名 | E2: タイコエレクトロニクス | G2: 合計金額 | J2: =SUM(H:H) -> 736856
B3: 担当営業 | E3: 平山
B4: 受注番号 | E4: 97373
B5: 希望納期 | E5: 41002
B6: 最終納品
B8: 見積り分類 | C8: メーカー | D8: 仕入先 | E8: 品名 / 型式 | F8: 数量 | G8: 単価 | H8: 金額 | I8: 分類合計 | J8: 詳細 | K8: 備考 | L8: 技術分類 | M8: 発注日 | N8: 発注 | O8: 納期 | P8: 入荷予定日 | Q8: 入荷日
B9: 1 | C9: 蛇の目 | D9: 蛇の目 | E9: JR2303N（外部） | F9: 1 | G9: 546000 | H9: =F9*G9 -> 546000 | K9: 平山案件 | M9: 40987 | P9: 41010 | Q9: 41010
B10: 1 | C10: 蛇の目 | D10: 蛇の目 | E10: 外部操作スイッチ | F10: 1 | G10: 19000 | H10: =F10*G10 -> 19000 | K10: 平山案件 | M10: 40987 | P10: 41010
B11: 1 | C11: 蛇の目 | D11: 蛇の目 | E11: COM2増設費用 | F11: 1 | G11: 20000 | H11: =F11*G11 -> 20000 | K11: 平山案件 | M11: 40987
B12: 1 | C12: 蛇の目 | D12: 蛇の目 | E12: 荷造り運賃 | F12: 1 | G12: 10000 | H12: =F12*G12 -> 10000 | K12: 平山案件 | M12: 40987
H13: =F13*G13 -> 0
C14: ミスミ | D14: ミスミ | E14: SLSBWRK7-70 | F14: 4 | G14: 300 | H14: =F14*G14 -> 1200 | J14: 六角支柱 | L14: Y | M14: 40987 | P14: 40991 | Q14: 40991
C15: ミスミ | D15: ミスミ | E15: SBD-S4-8 | F15: 2 | G15: 320 | H15: =F15*G15 -> 640 | J15: 段付六角スペーサ | L15: Z | M15: 40987 | P15: 40991 | Q15: 40991
C16: ミスミ | D16: ミスミ | E16: SP-S4-8 | F16: 2 | G16: 220 | H16: =F16*G16 -> 440 | J16: パイプスペーサ | L16: Z | M16: 40987 | P16: 40991 | Q16: 40991
C17: ミスミ | D17: ミスミ | E17: KBBS3-10 | F17: 2 | G17: 380 | H17: =F17*G17 -> 760 | J17: 極低頭六角穴付ねじ | L17: Z | M17: 40987 | P17: 40991 | Q17: 40991
C18: ミスミ | D18: ミスミ | E18: SETGS10-45-SC6-M4-N4-LKC | F18: 5 | G18: 1430 | H18: =F18*G18 -> 7150 | J18: 円形支柱 | L18: X | M18: 40987 | P18: 40991 | Q18: 40991
C19: ミスミ | D19: ミスミ | E19: FSAW-K-12680-898-120314-0074 | F19: 1 | G19: 21660 | H19: =F19*G19 -> 21660 | J19: Web設計ボックス | L19: Z | M19: 40987 | P19: 40994 | Q19: 40994
C20: ミスミ | D20: ミスミ | E20: PMUF4H5-120-120-1-10-4.5 | F20: 1 | G20: 2050 | H20: =F20*G20 -> 2050 | J20: パンチングメタル | L20: Z | M20: 40987 | P20: 40991 | Q20: 40991
C21: ミスミ | D21: ミスミ | E21: MRB-260 | F21: 1 | G21: 930 | H21: =F21*G21 -> 930 | J21: DINレール | L21: Z | M21: 40987 | P21: 40991 | Q21: 40991
C22: ミスミ | D22: ミスミ | E22: C06N-09MS-09FS-CROSS-ES05 | F22: 1 | G22: 2367 | H22: =F22*G22 -> 2367 | J22: RS232Cハーネス | L22: Z | M22: 40987 | P22: 40991 | Q22: 40991
C23: ミスミ | D23: ミスミ | E23: HD-LN-4-40-05 | F23: 1 | G23: 226 | H23: =F23*G23 -> 226 | J23: Dsubロック金具 | L23: Z | M23: 40987 | P23: 40991 | Q23: 40991
C24: ミスミ | D24: ミスミ | E24: PSSFGT15-100-M5 | F24: 1 | G24: 960 | H24: =F24*G24 -> 960 | J24: SUS汎用シャフト | L24: Z | M24: 40987 | P24: 40991 | Q24: 40991
C25: ミスミ | D25: ミスミ | E25: KNCLSS4-8-20 | F25: 2 | G25: 290 | H25: =F25*G25 -> 580 | J25: 金属カラー | L25: Z | M25: 40987 | P25: 40991 | Q25: 40991
... C48: ミスミ | D48: ミスミ | E48: SCBS4-8 | F48: 2 | G48: 38 | H48: =F48*G48 -> 76 | J48: 座金組込み六角穴付ボルト | L48: X | M48: 40987 | P48: 40991 | Q48: 40991
C50: 遠藤製作所 | D50: 遠藤製作所 | E50: SS3163 | F50: 1 | G50: 8600 | H50: 8600 | J50: ロボット取付板 | L50: Y | M50: 40987 | P50: 41003 | Q50: 41003
C51: 遠藤製作所 | D51: 遠藤製作所 | E51: SS3164-01 | F51: 1 | G51: 10800 | H51: =F51*G51 -> 10800 | J51: スターラー台 | L51: Z | M51: 40987 | P51: 41003 | Q51: 41003
C52: 遠藤製作所 | D52: 遠藤製作所 | E52: SS3165-01 | F52: 1 | G52: 10800 | H52: =F52*G52 -> 10800 | J52: ワーク冶具ベース | L52: X | M52: 40987 | P52: 41003 | Q52: 41003
C53: 遠藤製作所 | D53: 遠藤製作所 | E53: SS3170 | F53: 1 | G53: 5400 | H53: =F53*G53 -> 5400 | J53: ACJ-3 精密RG取付板 | L53: Z | M53: 40987 | P53: 41003 | Q53: 41003
C54: 遠藤製作所 | D54: 遠藤製作所 | E54: SS40576 | F54: 1 | G54: 2900 | H54: =F54*G54 -> 2900 | J54: CCD取付板（K） | L54: Y | M54: 40987 | P54: 41003 | Q54: 41003
C55: 遠藤製作所 | D55: 遠藤製作所 | E55: SS40577 | F55: 1 | G55: 3400 | H55: =F55*G55 -> 3400 | J55: 照明取付板（CA-DRW8M） | L55: Y | M55: 40987 | P55: 41003 | Q55: 41003
C56: 遠藤製作所 | D56: 遠藤製作所 | E56: SS40578 | F56: 1 | G56: 1980 | H56: =F56*G56 -> 1980 | J56: 位置決めピンΦ8 | L56: X | M56: 40987 | P56: 41003 | Q56: 41003
C57: 遠藤製作所 | D57: 遠藤製作所 | E57: SS40579 | F57: 1 | G57: 1980 | H57: =F57*G57 -> 1980 | J57: 位置決めピンΦ6 | L57: X | M57: 40987 | P57: 41003 | Q57: 41003
C58: 遠藤製作所 | D58: 遠藤製作所 | E58: SS40585-01 | F58: 1 | G58: 3800 | H58: =F58*G58 -> 3800 | J58: シャフト板金 | L58: Z | M58: 40987 | P58: 41003 | Q58: 41003
C59: 遠藤製作所 | D59: 遠藤製作所 | E59: SS40613 | F59: 1 | G59: 3400 | H59: =F59*G59 -> 3400 | J59: CCD取付板（K） ノズル用 | L59: Y | M59: 40987 | P59: 41003 | Q59: 41003
C60: 遠藤製作所 | D60: 遠藤製作所 | E60: SS40614-03 | F60: 1 | G60: 7800 | H60: =F60*G60 -> 7800 | J60: ノズル位置合わせカメラ用ベース | L60: Z | M60: 40987 | P60: 41003 | Q60: 41003
C61: 遠藤製作所 | D61: 遠藤製作所 | E61: SS40615 | F61: 2 | G61: 1400 | H61: =F61*G61 -> 2800 | J61: プリズム横押え板金 | L61: Z | M61: 40987 | P61: 41003 | Q61: 41003
C62: 遠藤製作所 | D62: 遠藤製作所 | E62: 96429-Z01 | F62: 1 | G62: 9800 | H62: =F62*G62 -> 9800 | J62: スターラースペーサ(SW-101N) | L62: Z | M62: 40987 | P62: 41003 | Q62: 41003
C63: 遠藤製作所 | D63: 遠藤製作所 | E63: SS40618 | F63: 1 | G63: 5900 | H63: 5900 | J63: 捨て打ちﾍﾞｰｽ | L63: Z | M63: 40987 | P63: 41003 | Q63: 41003
C64: 遠藤製作所 | D64: 遠藤製作所 | E64: SS40619 | F64: 1 | G64: 1900 | H64: 1900 | J64: 捨て打ちﾍﾞｰｽ連結板 | L64: Z | M64: 40987 | P64: 41003 | Q64: 41003
C65: 遠藤製作所 | D65: 遠藤製作所 | E65: SS40641 | F65: 1 | G65: 5200 | H65: 5200 | J65: ﾌﾟﾘｽﾞﾑ取付板2 | L65: Z | M65: 40987 | P65: 41003 | Q65: 41003

Sheet 【97374】タイコエレクトロニクス（12号機） 原価一覧
B2: お客先名 | E2: タイコエレクトロニクス | G2: 合計金額 | J2: =SUM(H:H) -> 736856
B3: 担当営業 | E3: 平山
B4: 受注番号 | E4: 97374
B5: 希望納期 | E5: 41002
B6: 最終納品
B8: 見積り分類 | C8: メーカー | D8: 仕入先 | E8: 品名 / 型式 | F8: 数量 | G8: 単価 | H8: 金額 | I8: 分類合計 | J8: 詳細 | K8: 備考 | L8: 技術分類 | M8: 発注日 | N8: 発注 | O8: 納期 | P8: 入荷予定日 | Q8: 入荷日
B9: 1 | C9: 蛇の目 | D9: 蛇の目 | E9: JR2303N（外部） | F9: 1 | G9: 546000 | H9: =F9*G9 -> 546000 | K9: 平山案件 | M9: 40987 | P9: 41010 | Q9: 41010
B10: 1 | C10: 蛇の目 | D10: 蛇の目 | E10: 外部操作スイッチ | F10: 1 | G10: 19000 | H10: =F10*G10 -> 19000 | K10: 平山案件 | M10: 40987 | P10: 41010
B11: 1 | C11: 蛇の目 | D11: 蛇の目 | E11: COM2増設費用 | F11: 1 | G11: 20000 | H11: =F11*G11 -> 20000 | K11: 平山案件 | M11: 40987
B12: 1 | C12: 蛇の目 | D12: 蛇の目 | E12: 荷造り運賃 | F12: 1 | G12: 10000 | H12: =F12*G12 -> 10000 | K12: 平山案件 | M12: 40987
H13: =F13*G13 -> 0
C14: ミスミ | D14: ミスミ | E14: SLSBWRK7-70 | F14: 4 | G14: 300 | H14: =F14*G14 -> 1200 | J14: 六角支柱 | L14: Y | M14: 40987 | P14: 40991 | Q14: 40991
C15: ミスミ | D15: ミスミ | E15: SBD-S4-8 | F15: 2 | G15: 320 | H15: =F15*G15 -> 640 | J15: 段付六角スペーサ | L15: Z | M15: 40987 | P15: 40991 | Q15: 40991
C16: ミスミ | D16: ミスミ | E16: SP-S4-8 | F16: 2 | G16: 220 | H16: =F16*G16 -> 440 | J16: パイプスペーサ | L16: Z | M16: 40987 | P16: 40991 | Q16: 40991
C17: ミスミ | D17: ミスミ | E17: KBBS3-10 | F17: 2 | G17: 380 | H17: =F17*G17 -> 760 | J17: 極低頭六角穴付ねじ | L17: Z | M17: 40987 | P17: 40991 | Q17: 40991
C18: ミスミ | D18: ミスミ | E18: SETGS10-45-SC6-M4-N4-LKC | F18: 5 | G18: 1430 | H18: =F18*G18 -> 7150 | J18: 円形支柱 | L18: X | M18: 40987 | P18: 40991 | Q18: 40991
C19: ミスミ | D19: ミスミ | E19: FSAW-K-12680-898-120314-0074 | F19: 1 | G19: 21660 | H19: =F19*G19 -> 21660 | J19: Web設計ボックス | L19: Z | M19: 40987 | P19: 40994 | Q19: 40994
C20: ミスミ | D20: ミスミ | E20: PMUF4H5-120-120-1-10-4.5 | F20: 1 | G20: 2050 | H20: =F20*G20 -> 2050 | J20: パンチングメタル | L20: Z | M20: 40987 | P20: 40991 | Q20: 40991
C21: ミスミ | D21: ミスミ | E21: MRB-260 | F21: 1 | G21: 930 | H21: =F21*G21 -> 930 | J21: DINレール | L21: Z | M21: 40987 | P21: 40991 | Q21: 40991
C22: ミスミ | D22: ミスミ | E22: C06N-09MS-09FS-CROSS-ES05 | F22: 1 | G22: 2367 | H22: =F22*G22 -> 2367 | J22: RS232Cハーネス | L22: Z | M22: 40987 | P22: 40991 | Q22: 40991
C23: ミスミ | D23: ミスミ | E23: HD-LN-4-40-05 | F23: 1 | G23: 226 | H23: =F23*G23 -> 226 | J23: Dsubロック金具 | L23: Z | M23: 40987 | P23: 40991 | Q23: 40991
C24: ミスミ | D24: ミスミ | E24: PSSFGT15-100-M5 | F24: 1 | G24: 960 | H24: =F24*G24 -> 960 | J24: SUS汎用シャフト | L24: Z | M24: 40987 | P24: 40991 | Q24: 40991
C25: ミスミ | D25: ミスミ | E25: KNCLSS4-8-20 | F25: 2 | G25: 290 | H25: =F25*G25 -> 580 | J25: 金属カラー | L25: Z | M25: 40987 | P25: 40991 | Q25: 40991
... C48: ミスミ | D48: ミスミ | E48: SCBS4-8 | F48: 2 | G48: 38 | H48: =F48*G48 -> 76 | J48: 座金組込み六角穴付ボルト | L48: X | M48: 40987 | P48: 40991 | Q48: 40991
C50: 遠藤製作所 | D50: 遠藤製作所 | E50: SS3163 | F50: 1 | G50: 8600 | H50: 8600 | J50: ロボット取付板 | L50: Y | M50: 40987 | P50: 41003 | Q50: 41003
C51: 遠藤製作所 | D51: 遠藤製作所 | E51: SS3164-01 | F51: 1 | G51: 10800 | H51: =F51*G51 -> 10800 | J51: スターラー台 | L51: Z | M51: 40987 | P51: 41003 | Q51: 41003
C52: 遠藤製作所 | D52: 遠藤製作所 | E52: SS3165-01 | F52: 1 | G52: 10800 | H52: =F52*G52 -> 10800 | J52: ワーク冶具ベース | L52: X | M52: 40987 | P52: 41003 | Q52: 41003
C53: 遠藤製作所 | D53: 遠藤製作所 | E53: SS3170 | F53: 1 | G53: 5400 | H53: =F53*G53 -> 5400 | J53: ACJ-3 精密RG取付板 | L53: Z | M53: 40987 | P53: 41003 | Q53: 41003
C54: 遠藤製作所 | D54: 遠藤製作所 | E54: SS40576 | F54: 1 | G54: 2900 | H54: =F54*G54 -> 2900 | J54: CCD取付板（K） | L54: Y | M54: 40987 | P54: 41003 | Q54: 41003
C55: 遠藤製作所 | D55: 遠藤製作所 | E55: SS40577 | F55: 1 | G55: 3400 | H55: =F55*G55 -> 3400 | J55: 照明取付板（CA-DRW8M） | L55: Y | M55: 40987 | P55: 41003 | Q55: 41003
C56: 遠藤製作所 | D56: 遠藤製作所 | E56: SS40578 | F56: 1 | G56: 1980 | H56: =F56*G56 -> 1980 | J56: 位置決めピンΦ8 | L56: X | M56: 40987 | P56: 41003 | Q56: 41003
C57: 遠藤製作所 | D57: 遠藤製作所 | E57: SS40579 | F57: 1 | G57: 1980 | H57: =F57*G57 -> 1980 | J57: 位置決めピンΦ6 | L57: X | M57: 40987 | P57: 41003 | Q57: 41003
C58: 遠藤製作所 | D58: 遠藤製作所 | E58: SS40585-01 | F58: 1 | G58: 3800 | H58: =F58*G58 -> 3800 | J58: シャフト板金 | L58: Z | M58: 40987 | P58: 41003 | Q58: 41003
C59: 遠藤製作所 | D59: 遠藤製作所 | E59: SS40613 | F59: 1 | G59: 3400 | H59: =F59*G59 -> 3400 | J59: CCD取付板（K） ノズル用 | L59: Y | M59: 40987 | P59: 41003 | Q59: 41003
C60: 遠藤製作所 | D60: 遠藤製作所 | E60: SS40614-03 | F60: 1 | G60: 7800 | H60: =F60*G60 -> 7800 | J60: ノズル位置合わせカメラ用ベース | L60: Z | M60: 40987 | P60: 41003 | Q60: 41003
C61: 遠藤製作所 | D61: 遠藤製作所 | E61: SS40615 | F61: 2 | G61: 1400 | H61: =F61*G61 -> 2800 | J61: プリズム横押え板金 | L61: Z | M61: 40987 | P61: 41003 | Q61: 41003
C62: 遠藤製作所 | D62: 遠藤製作所 | E62: 96429-Z01 | F62: 1 | G62: 9800 | H62: =F62*G62 -> 9800 | J62: スターラースペーサ(SW-101N) | L62: Z | M62: 40987 | P62: 41003 | Q62: 41003
C63: 遠藤製作所 | D63: 遠藤製作所 | E63: SS40618 | F63: 1 | G63: 5900 | H63: 5900 | J63: 捨て打ちﾍﾞｰｽ | L63: Z | M63: 40987 | P63: 41003 | Q63: 41003
C64: 遠藤製作所 | D64: 遠藤製作所 | E64: SS40619 | F64: 1 | G64: 1900 | H64: 1900 | J64: 捨て打ちﾍﾞｰｽ連結板 | L64: Z | M64: 40987 | P64: 41003 | Q64: 41003
C65: 遠藤製作所 | D65: 遠藤製作所 | E65: SS40641 | F65: 1 | G65: 5200 | H65: 5200 | J65: ﾌﾟﾘｽﾞﾑ取付板2 | L65: Z | M65: 40987 | P65: 41003 | Q65: 41003

Sheet 【97454】旭化成 原価一覧
B2: お客先名 | E2: 旭化成 | G2: 合計金額 | J2: =SUM(H:H) -> 1180673
B3: 担当営業 | E3: 勝田
B4: 受注番号 | E4: 97454
B5: 希望納期 | E5: 41022
B6: 最終納品 | E6: 41026
B8: 見積り分類 | C8: メーカー | D8: 仕入先 | E8: 品名 / 型式 | F8: 数量 | G8: 単価 | H8: 金額 | I8: 分類合計 | J8: 詳細 | K8: 備考 | L8: 技術分類 | M8: 発注日 | N8: 発注 | O8: 納期 | P8: 入荷予定日 | Q8: 入荷日
B9: 1 | C9: 蛇の目 | D9: 蛇の目 | E9: JR2503N | F9: 1 | G9: 765000 | H9: =F9*G9 -> 765000 | K9: 勝田依頼分 | M9: 41009 | Q9: 41012
B10: 1 | C10: 蛇の目 | D10: 蛇の目 | E10: 荷造り運賃 | F10: 1 | G10: 10000 | H10: =F10*G10 -> 10000 | M10: 41009
H11: =F11*G11 -> 0
B12: 13 | C12: ミスミ | D12: ミスミ | E12: HFS6-3030-1010 | F12: 4 | G12: 830 | H12: =F12*G12 -> 3320 | J12: アルミフレーム | L12: Z | M12: 41009 | P12: 41011 | Q12: 41011
B13: 13 | C13: ミスミ | D13: ミスミ | E13: HFS6-3030-372 | F13: 4 | G13: 300 | H13: =F13*G13 -> 1200 | J13: アルミフレーム | L13: Z | M13: 41009 | P13: 41011 | Q13: 41011
B14: 13 | C14: ミスミ | D14: ミスミ | E14: HFS8-4040-1020 | F14: 1 | G14: 1540 | H14: =F14*G14 -> 1540 | J14: アルミフレーム | L14: Z | M14: 41009 | P14: 41011 | Q14: 41011
B15: 13 | C15: ミスミ | D15: ミスミ | E15: HFS8-4040-1097 | F15: 4 | G15: 1650 | H15: =F15*G15 -> 6600 | J15: アルミフレーム | L15: Z | M15: 41009 | P15: 41011 | Q15: 41011
B16: 13 | C16: ミスミ | D16: ミスミ | E16: HFS8-4040-340 | F16: 2 | G16: 510 | H16: =F16*G16 -> 1020 | J16: アルミフレーム | L16: Z | M16: 41009 | P16: 41011 | Q16: 41011
B17: 13 | C17: ミスミ | D17: ミスミ | E17: HFS8-4040-720 | F17: 7 | G17: 1080 | H17: =F17*G17 -> 7560 | J17: アルミフレーム | L17: Z | M17: 41009 | P17: 41011 | Q17: 41011
B18: 13 | C18: ミスミ | D18: ミスミ | E18: HFS8-4040-870 | F18: 5 | G18: 1310 | H18: =F18*G18 -> 6550 | J18: アルミフレーム | L18: Z | M18: 41009 | P18: 41011 | Q18: 41011
B19: 13 | C19: ミスミ | D19: ミスミ | E19: HFS8-4080-870 | F19: 2 | G19: 2370 | H19: =F19*G19 -> 4740 | J19: アルミフレーム | K19: 次回：720に変更 | L19: Z | M19: 41009 | P19: 41011 | Q19: 4/12.
B20: 13 | C20: ミスミ | D20: ミスミ | E20: SHBLBS8 | F20: 8 | G20: 429 | H20: =F20*G20 -> 3432 | J20: ブラインドブラケット | L20: Z | M20: 41009 | P20: 41010 | Q20: 41010
B21: 13 | C21: ミスミ | D21: ミスミ | E21: HBLFSN6-C-SST | F21: 8 | G21: 184 | H21: =F21*G21 -> 1472 | J21: 片リブブラケット | L21: Z | M21: 41009 | P21: 41010 | Q21: 41010
B22: 13 | C22: ミスミ | D22: ミスミ | E22: HBLFSN8-C-SST | F22: 52 | G22: 233 | H22: =F22*G22 -> 12116 | J22: 片リブブラケット | L22: Z | M22: 41009 | P22: 41010 | Q22: 41010
B23: 13 | C23: ミスミ | D23: ミスミ | E23: HCBR6 | F23: 4 | G23: 157 | H23: =F23*G23 -> 628 | J23: パネルサポートブラケット | L23: Z | M23: 41009 | P23: 41010 | Q23: 41010
B24: 13 | C24: ミスミ | D24: ミスミ | E24: HHPNDLK8-6-SST | F24: 2 | G24: 755 | H24: =F24*G24 -> 1510 | J24: アルミ抜差し蝶番（左） | L24: Z | M24: 41009 | P24: 41010 | Q24: 41010
B25: 13 | C25: ミスミ | D25: ミスミ | E25: HHPNDRK8-6-SST | F25: 2 | G25: 755 | H25: =F25*G25 -> 1510 | J25: アルミ抜差し蝶番（左） | L25: Z | M25: 41009 | P25: 41010 | Q25: 41010
B26: 13 | C26: ミスミ | D26: ミスミ | E26: HMEN8-6 | F26: 2 | G26: 855 | H26: =F26*G26 -> 1710 | J26: マグネットキャッチ | L26: Z | M26: 41009 | P26: 41010 | Q26: 4/11.
B27: 13 | C27: ミスミ | D27: ミスミ | E27: HMER8-6 | F27: 2 | G27: 2065 | H27: =F27*G27 -> 4130 | J27: センサ付マグネットキャッチ | L27: Z | M27: 41009 | P27: 41010 | Q27: 41010
B28: 13 | C28: ミスミ | D28: ミスミ | E28: HFC6-3030-B | F28: 8 | G28: 160 | H28: =F28*G28 -> 1280 | J28: フレームキャップ | L28: Z | M28: 41009 | P28: 41010 | Q28: 41010
B29: 13 | C29: ミスミ | D29: ミスミ | E29: HFC8-4040-B | F29: 4 | G29: 180 | H29: =F29*G29 -> 720 | J29: フレームキャップ | L29: Z | M29: 41009 | P29: 41010 | Q29: 41010
B30: 13 | C30: ミスミ | D30: ミスミ | E30: HHDNFA112 | F30: 2 | G30: 720 | H30: =F30*G30 -> 1440 | J30: アングル取手 | L30: Z | M30: 41009 | P30: 41010 | Q30: 41010
B31: 13 | C31: ミスミ | D31: ミスミ | E31: HNTATSN8-4 | F31: 20 | G31: 52 | H31: =F31*G31 -> 1040 | J31: 後入れナットストッパセット | L31: Z | M31: 41009 | P31: 41010 | Q31: 41010
B32: 13 | C32: ミスミ | D32: ミスミ | E32: HNTATSN8-5 | F32: 20 | G32: 52 | H32: =F32*G32 -> 1040 | J32: 後入れナットストッパセット | L32: Z | M32: 41009 | P32: 41010 | Q32: 41010
B33: 13 | C33: ミスミ | D33: ミスミ | E33: HNTATSN8-6 | F33: 20 | G33: 52 | H33: =F33*G33 -> 1040 | J33: 後入れナットストッパセット | L33: Z | M33: 41009 | P33: 41010 | Q33: 41010
B34: 13 | C34: ミスミ | D34: ミスミ | E34: HNTATSN8-8 | F34: 20 | G34: 52 | H34: =F34*G34 -> 1040 | J34: 後入れナットストッパセット | L34: Z | M34: 41009 | P34: 41010 | Q34: 41010
B35: 13 | C35: ミスミ | D35: ミスミ | E35: HNTATSN6-6 | F35: 20 | G35: 47 | H35: =F35*G35 -> 940 | J35: 後入れナットストッパセット | L35: Z | M35: 41009 | P35: 41010 | Q35: 41010
B36: 13 | C36: ミスミ | D36: ミスミ | E36: HNTRSN8-5 | F36: 80 | G36: 59 | H36: =F36*G36 -> 4720 | J36: 後入れロックナット | L36: Z | M36: 41009 | P36: 41010 | Q36: 41010
B37: 13 | C37: ミスミ | D37: ミスミ | E37: SHCBM5-15 | F37: 80 | G37: 13 | H37: =F37*G37 -> 1040 | J37: 十字穴付トラスねじ | L37: Z | M37: 41009 | P37: 41010 | Q37: 41010
B38: 13 | C38: ミスミ | D38: ミスミ | E38: BFHBF-SUD-A60-T3.0-D30-Q40-N4 | F38: 4 | G38: 2280 | H38: =F38*G38 -> 9120 | J38: 板金丸プレート | L38: Z | M38: 41009 | P38: 41015 | Q38: 41015
... B47: 3 | C47: ミスミ | D47: ミスミ | E47: DC-C8-J13-F41R | F47: 1 | G47: 547 | H47: =F47*G47 -> 547 | J47: D-Subコネクタフード | L47: Z | M47: 41009 | P47: 41010 | Q47: 41010
M48: 41009
B49: 10・11 | C49: ミスミ | D49: ミスミ | E49: XSG40-CZ | F49: 1 | G49: 16000 | H49: =F49*G49 -> 16000 | J49: リニアボールX軸ステージ | L49: Y | M49: 41009 | P49: 41016 | Q49: 41016
B50: 10・11 | C50: ミスミ | D50: ミスミ | E50: LRLB5-10 | F50: 1 | G50: 570 | H50: =F50*G50 -> 570 | J50: 長尺ローレット付ボルト | L50: Y | M50: 41009 | P50: 41010 | Q50: 41010
B51: 10・11 | C51: ミスミ | D51: ミスミ | E51: BVHVU6-3 | F51: 1 | G51: 780 | H51: =F51*G51 -> 780 | J51: ハンドバルブ | L51: Y | M51: 41009 | P51: 41010 | Q51: 41010
B52: 10・11 | C52: ミスミ | D52: ミスミ | E52: SCB4-25 | F52: 3 | G52: 80 | H52: =F52*G52 -> 240 | J52: 六角穴付ボルト | L52: Y | M52: 41009 | P52: 41010 | Q52: 41010
B53: 10・11 | C53: ミスミ | D53: ミスミ | E53: SCB4-35 | F53: 2 | G53: 88 | H53: =F53*G53 -> 176 | J53: 六角穴付ボルト | L53: Y | M53: 41009 | P53: 41010 | Q53: 41010
B54: 10・11 | C54: ミスミ | D54: ミスミ | E54: SCB4-40 | F54: 1 | G54: 95 | H54: =F54*G54 -> 95 | J54: 六角穴付ボルト | L54: Y | M54: 41009 | P54: 41010 | Q54: 41010
H55: =F55*G55 -> 0
B56: 12 | C56: ミスミ | D56: ミスミ | E56: SPCB-SU-D20-L50-J7-M6-MA5-SC15-W10-S17-LKC | F56: 2 | G56: 3384 | H56: =F56*G56 -> 6768 | J56: 支柱ピン | L56: X | M56: 41009 | P56: 41015 | Q56: 41015
B57: 12 | C57: ミスミ | D57: ミスミ | E57: SCPE-SU-D20-L50-P10-B5-E2-J7-M6-SC15-W10-S17-LKC | F57: 1 | G57: 5330 | H57: =F57*G57 -> 5330 | J57: 支柱ピン | L57: X | M57: 41009 | P57: 41015 | Q57: 4/16.
B58: 12 | C58: ミスミ | D58: ミスミ | E58: SCPE-SU-D20-L50-P8-B5-E2-J7-M6-SC15-W10-S17-LKC | F58: 1 | G58: 5330 | H58: =F58*G58 -> 5330 | J58: 支柱ピン | L58: X | M58: 41009 | P58: 41015 | Q58: 41015
B59: 12 | C59: ミスミ | D59: ミスミ | E59: LPCSB4-P8.9-B23.0-G7 | F59: 2 | G59: 710 | H59: =F59*G59 -> 1420 | J59: 位置決めピン | L59: X | M59: 41009 | P59: 41015 | Q59: 41015
B60: 12 | C60: ミスミ | D60: ミスミ | E60: LPCSB3-P6.9-B23.0-G5 | F60: 4 | G60: 680 | H60: =F60*G60 -> 2720 | J60: 位置決めピン | L60: X | M60: 41009 | P60: 41015 | Q60: 41015
B61: 12 | C61: ミスミ | D61: ミスミ | E61: SETN10-30-SC10-M4 | F61: 8 | G61: 750 | H61: =F61*G61 -> 6000 | J61: 円形支柱 | L61: X | M61: 41009 | P61: 41015 | Q61: 41015
B62: 12 | C62: ミスミ | D62: ミスミ | E62: SCB4-8 | F62: 6 | G62: 75 | H62: =F62*G62 -> 450 | J62: 六角穴付ボルト | L62: X | M62: 41009 | P62: 41010 | Q62: 41010
B63: 12 | C63: ミスミ | D63: ミスミ | E63: SCB4-30 | F63: 10 | G63: 35 | H63: =F63*G63 -> 350 | J63: 六角穴付ボルト | L63: X | M63: 41009 | P63: 41010 | Q63: 41010
B65: 13 | C65: キーエンス | D65: キーエンス | E65: SL-VP7N | F65: 1 | G65: 9000 | H65: 9000 | J65: 本体接続ケーブル（NPN 汎用） | L65: Z | M65: 41009 | P65: 41011 | Q65: 41010
B66: 13 | C66: キーエンス | D66: キーエンス | E66: OP-42347 | F66: 2 | G66: 1400 | H66: 2800 | J66: 取付金具 | L66: Z | M66: 41009 | P66: 41011 | Q66: 41010
H67: =F67*G67 -> 0
B68: 12 | C68: 遠藤製作所 | D68: 遠藤製作所 | E68: 97454-X01 | F68: 1 | G68: 12000 | H68: =F68*G68 -> 12000 | J68: ロボットベース板 | L68: X | M68: 41009 | P68: 41022 | Q68: 41022
B69: 12 | C69: 遠藤製作所 | D69: 遠藤製作所 | E69: 97454-X02 | F69: 1 | G69: 2100 | H69: =F69*G69 -> 2100 | J69: ノズル位置決めピン | L69: X | M69: 41009 | P69: 41022 | Q69: 41022
B70: 12 | C70: 遠藤製作所 | D70: 遠藤製作所 | E70: 97454-X03 | F70: 1 | G70: 23000 | H70: =F70*G70 -> 23000 | J70: DR-S-02大型ワークベース | L70: X | M70: 41009 | P70: 41022 | Q70: 41022
B71: 12 | C71: 遠藤製作所 | D71: 遠藤製作所 | E71: 97454-X04 | F71: 2 | G71: 7500 | H71: =F71*G71 -> 15000 | J71: DR-S-02大型ワークガイド | L71: X | M71: 41009 | P71: 41022 | Q71: 41022
B72: 12 | C72: 遠藤製作所 | D72: 遠藤製作所 | E72: 97454-X05 | F72: 1 | G72: 25000 | H72: =F72*G72 -> 25000 | J72: DR-S-01中型ワークベース | L72: X | M72: 41009 | P72: 41022 | Q72: 41022
B73: 12 | C73: 遠藤製作所 | D73: 遠藤製作所 | E73: 97454-X06 | F73: 2 | G73: 6800 | H73: =F73*G73 -> 13600 | J73: DR-S-01中型ワークガイド1 | L73: X | M73: 41009 | P73: 41022 | Q73: 41022
B74: 12 | C74: 遠藤製作所 | D74: 遠藤製作所 | E74: 97454-X07 | F74: 1 | G74: 8200 | H74: =F74*G74 -> 8200 | J74: DR-S-01中型ワークガイド2 | L74: X | M74: 41009 | P74: 41022 | Q74: 41022
B75: 10・11 | C75: 遠藤製作所 | D75: 遠藤製作所 | E75: 97454-Y01 | F75: 1 | G75: 10800 | H75: =F75*G75 -> 10800 | J75: ロボット取付板（ATD300） | L75: Y | M75: 41009 | P75: 41022 | Q75: 41022
B76: 10・11 | C76: 遠藤製作所 | D76: 遠藤製作所 | E76: 97454-Y02 | F76: 1 | G76: 13800 | H76: =F76*G76 -> 13800 | J76: バルブホルダ | L76: Y | M76: 41009 | P76: 41022 | Q76: 41022
B77: 10・11 | C77: 遠藤製作所 | D77: 遠藤製作所 | E77: SS3152 | F77: 1 | G77: 7800 | H77: =F77*G77 -> 7800 | J77: タブテーブル（L120） | L77: Y | M77: 41009 | P77: 41022 | Q77: 41022
B78: 10・11 | C78: 遠藤製作所 | D78: 遠藤製作所 | E78: SS40564 | F78: 1 | G78: 19500 | H78: =F78*G78 -> 19500 | J78: 新カートリッジホルダ（ダブ用） | L78: Y | M78: 41009 | P78: 41022 | Q78: 41022
B79: 10・11 | C79: 遠藤製作所 | D79: 遠藤製作所 | E79: SS40633 | F79: 1 | G79: 2800 | H79: =F79*G79 -> 2800 | J79: X軸ステージ変換板 | L79: Y | M79: 41009 | P79: 41022 | Q79: 41022
B80: 12 | C80: 遠藤製作所 | D80: 遠藤製作所 | E80: ノズル位置決めピン追加工 | F80: 1 | G80: 800 | H80: 800 | K80: 受取済 | L80: X | M80: 41025 | Q80: 41026
B82: 13 | C82: ニットクエンジニヤリング | D82: ニットクエンジニヤリング | E82: 組立作業費 | F82: 1 | G82: 45000 | H82: 45000 | J82: 見積No：12-02660-2 | L82: Z | M82: 41012 | Q82: 41019
B83: 13 | C83: ニットクエンジニヤリング | D83: ニットクエンジニヤリング | E83: 配線材料等(97454-Z01製作含） | F83: 1 | G83: 7500 | H83: 7500 | J83: 見積No：12-02660-2 | L83: Z | M83: 41012 | Q83: 41019
B84: 13 | C84: ニットクエンジニヤリング | D84: ニットクエンジニヤリング | E84: 配線作業等 | F84: 1 | G84: 31500 | H84: 31500 | J84: 見積No：12-02660-2 | L84: Z | M84: 41012 | Q84: 41019
B85: 13 | C85: ニットクエンジニヤリング | D85: ニットクエンジニヤリング | E85: スイッチ取付金具 | F85: 1 | G85: 18000 | H85: 18000 | J85: 見積No：12-02660-2 | L85: Z | M85: 41012 | Q85: 41019
B86: 13 | C86: ニットクエンジニヤリング | D86: ニットクエンジニヤリング | E86: 出精値引き | F86: 1 | G86: -8000 | H86: -8000 | J86: 見積No：12-02660-2 | L86: Z | M86: 41012
H87: =F87*G87 -> 0
B88: 13 | C88: ミスミ | D88: ミスミ | E88: SHCBM5-10 | F88: 15 | G88: 33 | H88: =F88*G88 -> 495 | J88: 十字穴付トラスねじ | K88: 97454（SAITO）で発注、受取済 | L88: Z | M88: 41024 | Q88: 41025
H91: =F91*G91 -> 0
H92: =F92*G92 -> 0
H94: =F94*G94 -> 0
H95: =F95*G95 -> 0
H96: =F96*G96 -> 0
H97: =F97*G97 -> 0
H98: =F98*G98 -> 0
H99: =F99*G99 -> 0
H100: =F100*G100 -> 0
H101: =F101*G101 -> 0
H102: =F102*G102 -> 0
H103: =F103*G103 -> 0
H104: =F104*G104 -> 0

Sheet 【97655】 ㈱オジックとダイア 原価一覧4-12出荷
B2: お客先名 | E2: ㈱オジックとタ゛イア | G2: 合計金額 | J2: =SUM(H:H) -> 1472700
B3: 担当営業 | E3: 青木
B4: 受注番号 | E4: 97655
B5: 希望納期 | E5: 41011
B6: 最終納品
B8: 見積り分類 | C8: メーカー | D8: 仕入先 | E8: 品名 / 型式 | F8: 数量 | G8: 単価 | H8: 金額 | I8: 分類合計 | J8: 詳細 | K8: 備考 | L8: 技術分類 | M8: 発注日 | N8: 発注 | O8: 納期 | P8: 入荷予定日 | Q8: 入荷日
B9: 1 | C9: 蛇の目 | D9: 蛇の目 | E9: JR2403N | F9: 2 | G9: 699000 | H9: =F9*G9 -> 1398000 | J9: 内部ｽｲｯﾁ仕様 | K9: 仙台（営）青木依頼分 | M9: 40991 | P9: 41012 | Q9: 4/13ｵｼﾞｯｸ直送
B10: 1 | C10: 蛇の目 | D10: 蛇の目 | E10: COM2増設費用 | F10: 2 | G10: 20000 | H10: =F10*G10 -> 40000 | J10: 「ＣＯＭ２」増設仕様 | M10: 40991 | P10: 41012
B11: 1 | C11: 蛇の目 | D11: 蛇の目 | E11: IO-1増設ｹｰﾌﾞﾙ | F11: 2 | G11: 7350 | H11: =F11*G11 -> 14700 | M11: 40991 | P11: 41012
B12: 1 | C12: 蛇の目 | D12: 蛇の目 | E12: 荷造り運賃 | F12: 2 | G12: 10000 | H12: =F12*G12 -> 20000 | M12: 40991
B13: 2 | C13: 蛇の目 | D13: 蛇の目 | E13: JR-TB | F13: 1 | H13: =F13*G13 -> 0 | J13: ティーチングペンダント | M13: 在庫使用

Sheet 【97746】パナソニック 原価一覧
B2: お客先名 | E2: パナソニック | G2: 合計金額 | J2: =SUM(H:H) -> 9078
B3: 担当営業 | E3: 宮嶋
B4: 受注番号 | E4: 97746
B5: 希望納期 | E5: 41005
B6: 最終納品
B8: 見積り分類 | C8: メーカー | D8: 仕入先 | E8: 品名 / 型式 | F8: 数量 | G8: 単価 | H8: 金額 | I8: 分類合計 | J8: 詳細 | K8: 備考 | L8: 技術分類 | M8: 発注日 | N8: 発注 | O8: 納期 | P8: 入荷予定日 | Q8: 入荷日
C9: ミスミ | D9: ミスミ | E9: CRKB4-10 | F9: 1 | G9: 78 | H9: =F9*G9 -> 78 | J9: 樹脂ローレットねじ | L9: Z | M9: 40995 | P9: 40996 | Q9: 40996
H10: =F10*G10 -> 0
C11: 遠藤製作所 | D11: 遠藤製作所 | E11: SS40288 | F11: 1 | G11: 9000 | H11: =F11*G11 -> 9000 | J11: 10ccシリンジウケ | L11: Z | M11: 40995 | P11: 41005 | Q11: 41004
H12: =F12*G12 -> 0
H13: =F13*G13 -> 0
H14: =F14*G14 -> 0
H15: =F15*G15 -> 0
H16: =F16*G16 -> 0
H17: =F17*G17 -> 0
H18: =F18*G18 -> 0
H19: =F19*G19 -> 0
H20: =F20*G20 -> 0
H21: =F21*G21 -> 0
H22: =F22*G22 -> 0
H23: =F23*G23 -> 0
... H67: =F67*G67 -> 0

Sheet 【97824】栄通信工業 原価一覧
B2: お客先名 | E2: 栄通信工業 | G2: 合計金額 | J2: =SUM(H:H) -> 798472
B3: 担当営業 | E3: 村上
B4: 受注番号 | E4: 97824
B5: 希望納期 | E5: 41022
B6: 最終納品 | E6: 41025
B8: 見積り分類 | C8: メーカー | D8: 仕入先 | E8: 品名 / 型式 | F8: 数量 | G8: 単価 | H8: 金額 | I8: 分類合計 | J8: 詳細 | K8: 備考 | L8: 技術分類 | M8: 発注日 | N8: 発注 | O8: 納期 | P8: 入荷予定日 | Q8: 入荷日
B9: 1・2 | C9: 蛇の目 | D9: 蛇の目 | E9: JR2404N | F9: 1 | G9: 754000 | H9: =F9*G9 -> 754000 | K9: 村上案件 | M9: 40998 | P9: 41025 | Q9: 41025
B10: 4 | C10: 蛇の目 | D10: 蛇の目 | E10: PCソフト | F10: 1 | G10: 30000 | H10: =F10*G10 -> 30000 | K10: 村上案件 | M10: 40998 | P10: 41025
B11: 1・2 | C11: 蛇の目 | D11: 蛇の目 | E11: 荷造り運賃 | F11: 1 | G11: 10000 | H11: =F11*G11 -> 10000 | K11: 村上案件 | M11: 40998
H12: =F12*G12 -> 0
B13: 3 | C13: ミスミ | D13: ミスミ | E13: NEDJ-PT-SB-37-2 | F13: 1 | G13: 4472 | H13: =F13*G13 -> 4472 | J13: Dsubコネクタハーネス | L13: Ｚ | M13: 40998 | P13: 41002 | Q13: 41002
H14: =F14*G14 -> 0
H15: =F15*G15 -> 0
H16: =F16*G16 -> 0
H17: =F17*G17 -> 0
H18: =F18*G18 -> 0
H19: =F19*G19 -> 0
H20: =F20*G20 -> 0
H21: =F21*G21 -> 0
H22: =F22*G22 -> 0
H23: =F23*G23 -> 0
H24: =F24*G24 -> 0
H25: =F25*G25 -> 0
... H67: =F67*G67 -> 0

Sheet 【97897】富士スクリーン 原価一覧
B2: お客先名 | E2: 富士スクリーン | G2: 合計金額 | J2: =SUM(H:H) -> 117116
B3: 担当営業 | E3: 田中
B4: 受注番号 | E4: 97897
B5: 希望納期 | E5: 41009
B6: 最終納品
B8: 見積り分類 | C8: メーカー | D8: 仕入先 | E8: 品名 / 型式 | F8: 数量 | G8: 単価 | H8: 金額 | I8: 分類合計 | J8: 詳細 | K8: 備考 | L8: 技術分類 | M8: 発注日 | N8: 発注 | O8: 納期 | P8: 入荷予定日 | Q8: 入荷日
C9: 蛇の目 | D9: 蛇の目 | E9: JRV 塗布用PCソフト | F9: 1 | G9: 30000 | H9: =F9*G9 -> 30000 | L9: Z | M9: 41003 | P9: 41011 | Q9: 41011
C10: 蛇の目 | D10: 蛇の目 | E10: 送料 | F10: 1 | G10: 1000 | H10: =F10*G10 -> 1000 | L10: Z | M10: 41003
H11: =F11*G11 -> 0
C12: ミスミ | D12: ミスミ | E12: PNUIC-REX-USB60F-R | F12: 1 | G12: 5200 | H12: =F12*G12 -> 5200 | J12: USBコンバータ | L12: Z | M12: 41003 | P12: 41010 | Q12: 41010
C13: ミスミ | D13: ミスミ | E13: DGC-9SS | F13: 1 | G13: 203 | H13: =F13*G13 -> 203 | J13: ジェンダーチェンジャー | L13: Z | M13: 41003 | P13: 41010 | Q13: 41010
C14: ミスミ | D14: ミスミ | E14: @ECHN-20111222-00025 | F14: 1 | G14: 1767 | H14: =F14*G14 -> 1767 | J14: Web設計ハーネス | L14: Z | M14: 41003 | P14: 41012 | Q14: 41012
C15: ミスミ | D15: ミスミ | E15: SCB4-35 | F15: 2 | G15: 88 | H15: =F15*G15 -> 176 | J15: 六角穴付ボルト | L15: Y | M15: 41003 | P15: 41010 | Q15: 41010
C16: ミスミ | D16: ミスミ | E16: XSG40-CZ | F16: 1 | G16: 12500 | H16: =F16*G16 -> 12500 | J16: リニアボールＸ軸ステージ | L16: Y | M16: 41003 | P16: 41010 | Q16: 41010
C17: ミスミ | D17: ミスミ | E17: ＡＰＭＴＳ－Ｎ１－Ｔ２ | F17: 1 | G17: 1100 | H17: =F17*G17 -> 1100 | J17: ねじ変換継手 | L17: Y | M17: 41003 | P17: 41010 | Q17: 41010
C18: ミスミ | D18: ミスミ | E18: ＬＲＬＢ５－１０ | F18: 1 | G18: 570 | H18: =F18*G18 -> 570 | J18: 長尺ローレット付きボルト | L18: Y | M18: 41003 | P18: 41010 | Q18: 41010
C19: ミスミ | D19: ミスミ | E19: ＮＯＳＣ５－１０－１６ | F19: 1 | G19: 600 | H19: =F19*G19 -> 600 | J19: 小径ローレットノブ | L19: Y | M19: 41003 | P19: 41010 | Q19: 41010
C21: 遠藤製作所 | D21: 遠藤製作所 | E21: SS40079 | F21: 1 | G21: 13800 | H21: =F21*G21 -> 13800 | J21: 740,752,780用ホルダ（Ｐ＝25） | L21: Y | M21: 41003 | P21: 41015 | Q21: 41016
C22: 遠藤製作所 | D22: 遠藤製作所 | E22: SS3244 | F22: 1 | G22: 7800 | H22: =F22*G22 -> 7800 | J22: タブテーブル（Ｌ１１０） | L22: Y | M22: 41003 | P22: 41015 | Q22: 41016
C23: 遠藤製作所 | D23: 遠藤製作所 | E23: 97897－Ｘ０１ | F23: 1 | G23: 9800 | H23: =F23*G23 -> 9800 | J23: ベース板（２００ｍｍ） | L23: X | M23: 41003 | P23: 41015 | Q23: 41016
C24: 遠藤製作所 | D24: 遠藤製作所 | E24: 97897－Ｙ０１ | F24: 1 | G24: 2300 | H24: 2300 | J24: Ｘステージ変換板（３６０ｃｃ用） | L24: Y | M24: 41003 | P24: 41015 | Q24: 41016
C25: 遠藤製作所 | D25: 遠藤製作所 | E25: 97897－Ｙ０２ | F25: 1 | G25: 9800 | H25: 9800 | J25: ツール板 | L25: Y | M25: 41003 | P25: 41015 | Q25: 41016
C26: 遠藤製作所 | D26: 遠藤製作所 | E26: 97897－Ｙ０３ | F26: 1 | G26: 12000 | H26: 12000 | J26: 5194ホルダ（タブ用） | L26: Y | M26: 41003 | P26: 41015 | Q26: 41016
C27: 遠藤製作所 | D27: 遠藤製作所 | E27: 97897－Ｙ０４ | F27: 1 | G27: 8500 | H27: 8500 | J27: Ｘステージ変換板（５５ｃｃ用） | L27: Y | M27: 41003 | P27: 41015 | Q27: 41016
H28: 0
H29: 0
H30: 0
H31: 0
H32: 0
H33: 0
H34: 0
H35: 0
H36: 0
H37: =F37*G37 -> 0
H38: =F38*G38 -> 0
H39: =F39*G39 -> 0
H40: =F40*G40 -> 0
H41: =F41*G41 -> 0
H42: =F42*G42 -> 0
H43: =F43*G43 -> 0
H44: =F44*G44 -> 0
H45: =F45*G45 -> 0
H46: =F46*G46 -> 0
H47: =F47*G47 -> 0
H48: =F48*G48 -> 0
... H71: =F71*G71 -> 0

Sheet 【97901】 カイインダストリーズ㈱
B2: お客先名 | E2: ｶｲｲﾝﾀﾞｽﾄﾘｰｽﾞ㈱ | G2: 合計金額 | J2: =SUM(H:H) -> 310462
B3: 担当営業 | E3: 田中
B4: 受注番号 | E4: 97901 | G4: 備考
B5: 希望納期 | E5: 2012/03/4/16
B6: 最終納品
B8: 見積り分類 | C8: メーカー | D8: 仕入先 | E8: 品名 / 型式 | F8: 数量 | G8: 単価 | H8: 金額 | I8: 分類合計 | J8: 詳細 | K8: 備考 | L8: 技術分類 | M8: 発注日 | N8: 発注 | O8: 納期 | P8: 入荷予定日 | Q8: 入荷日
B9: 1 | C9: 蛇の目 | D9: 蛇の目 | E9: JRV2203 | F9: 1 | G9: 235000 | H9: =F9*G9 -> 235000 | J9: ３軸ロボット | M9: 在庫使用
B10: 1 | C10: 蛇の目 | D10: 蛇の目 | E10: 荷造り運賃 | F10: 1 | G10: 5000 | H10: =F10*G10 -> 5000
B11: 2 | C11: 蛇の目 | D11: 蛇の目 | E11: JRV-TB | F11: 1 | G11: 40000 | H11: =F11*G11 -> 40000 | J11: ﾃｨｰﾁﾝｸﾞﾎﾞｯｸｽ Ｖｼﾘｰｽﾞ用 | M11: 在庫使用
B12: 3 | C12: SET | D12: SET | E12: 5 | H12: =F12*G12 -> 0 | J12: 7012436/12ｏｚRETAINER SYSTEM ★印↓ | L12: -
B13: 4 | C13: SET | D13: SET | E13: 7013859 | F13: 1 | H13: =F13*G13 -> 0 | J13: RETAINER BODY 0 120Ｚ CL ★ | L13: -
B14: 5 | C14: SET | D14: SET | E14: 7012531 | F14: 1 | H14: =F14*G14 -> 0 | J14: RETAINER CAP ★ | L14: -
B15: 6 | C15: SET | D15: SET | E15: 7012407 | F15: 1 | H15: =F15*G15 -> 0 | J15: CARTRIDGE 120Z CLEAR 25 PC★ | L15: -
B16: 7 | C16: SET | D16: SET | E16: 7012419 | F16: 1 | H16: =F16*G16 -> 0 | J16: PISTON,2.5/6/12 0Z.CARTRIDGE ★ | L16: -
B17: 8 | C17: SET | D17: SET | E17: 7012423 | F17: 1 | H17: =F17*G17 -> 0 | J17: END CAP ,2.5/6/12 0Z CARTRIDGE/25★ | L17: -
B18: 9 | C18: SET | D18: SET | E18: 7012427 | F18: 1 | H18: =F18*G18 -> 0 | J18: OUTLET CAP，CARTRIDGE25 PC★ | L18: -
B19: 10 | C19: SET | D19: SET | E19: 5 | F19: 1 | H19: =F19*G19 -> 0 | J19: φ6ｴｱﾎｰｽ ｸﾘｱﾌﾞﾙｰ 1.5mm ★ | L19: -
B20: 11 | C20: SET | D20: SET | E20: KQ2H06-01S | F20: 1 | H20: =F20*G20 -> 0 | J20: 継手ﾊｰﾌﾕﾆｵﾝ φ6×1/8PT ★ | L20: -
B21: 12 | C21: SET | D21: SET | E21: 7012407 | F21: 1 | H21: =F21*G21 -> 0 | J21: CARTRIDGE 120Z CLEAR 25 PC★ | L21: -
B22: 13 | C22: SET | D22: SET | E22: 7012419 | F22: 1 | H22: =F22*G22 -> 0 | J22: PISTON,2.5/6/12 0Z.CARTRIDGE 25PC | L22: -
B23: 14 | C23: SET | D23: SET | E23: 7016941 | F23: 1 | H23: =F23*G23 -> 0 | J23: 2186 ｶｰﾄﾘｯｼﾞﾙｱﾛｯｸ | L23: -
B24: 15 | C24: 遠藤製作所 | D24: 遠藤製作所 | E24: 97901-Y001 | F24: 1 | G24: 9800 | H24: =F24*G24 -> 9800 | J24: ｶｰﾄﾘｯｼﾞ取付ﾍﾞｰｽﾌﾞﾗｹｯﾄ | K24: 図面作図中に付き発注はまだです | L24: Y | M24: 41008 | P24: 41015 | Q24: 41016
B25: 15 | C25: 遠藤製作所 | D25: 遠藤製作所 | E25: 97901-Y002 | F25: 1 | G25: 5900 | H25: =F25*G25 -> 5900 | J25: ｶｰﾄﾘｯｼﾞ受け A | K25: 図面作図中に付き発注はまだです | L25: Y | M25: 41008 | P25: 41015 | Q25: 41016
B26: 15 | C26: 遠藤製作所 | D26: 遠藤製作所 | E26: 97901-Y003 | F26: 1 | G26: 5900 | H26: =F26*G26 -> 5900 | J26: ｶｰﾄﾘｯｼﾞ受け B | K26: 図面作図中に付き発注はまだです | L26: Y | M26: 41008 | P26: 41015 | Q26: 41016
B27: 15 | C27: 遠藤製作所 | D27: 遠藤製作所 | E27: 97901-Y002-1 | F27: 1 | G27: 1500 | H27: =F27*G27 -> 1500 | J27: ｶｰﾄﾘｯｼﾞ受け A追加工費 | M27: 41016 | Q27: 4/17斉藤(秀)氏引取
B28: 15 | C28: 遠藤製作所 | D28: 遠藤製作所 | E28: 97901-Y003-1 | F28: 1 | G28: 3000 | H28: =F28*G28 -> 3000 | J28: ｶｰﾄﾘｯｼﾞ受け B追加工費 | M28: 41016 | Q28: 4/17斉藤(秀)氏引取
B29: 15 | C29: ミスミ | D29: ミスミ | E29: ＮＯＳＣ５－１０－１６ | F29: 2 | G29: 600 | H29: =F29*G29 -> 1200 | J29: 小径ローレットノブ | L29: Y | M29: 41005 | P29: 41008 | Q29: 41008
B30: 15 | C30: ミスミ | D30: ミスミ | E30: ＭＳ３－１０ | F30: 24 | G30: 34 | H30: =F30*G30 -> 816 | J30: ﾉｯｸﾋﾟﾝ | L30: Y | M30: 41005 | P30: 41008 | Q30: 41008
B31: 15 | C31: ミスミ | D31: ミスミ | E31: SCB5-10 | F31: 2 | G31: 75 | H31: =F31*G31 -> 150 | J31: 六角穴付ボルト | L31: Y | M31: 41005 | P31: 41008 | Q31: 41008
B32: 15 | C32: ミスミ | D32: ミスミ | E32: SCB5-15 | F32: 4 | G32: 75 | H32: =F32*G32 -> 300 | J32: 六角穴付ボルト | L32: Y | M32: 41005 | P32: 41008 | Q32: 41008
B33: 16 | C33: ミスミ | D33: ミスミ | E33: @ECHN-20111222-00025 | F33: 1 | G33: 1767 | H33: =F33*G33 -> 1767 | J33: Web設計ハーネス（IOｹｰﾌﾞﾙ) | M33: 41005 | P33: 41016 | Q33: 41016
C34: ミスミ | D34: ミスミ | E34: NKSM5-25 | F34: 1 | G34: 129 | H34: =F34*G34 -> 129 | J34: ﾉﾌﾞ | N34: 済 | P34: 41017 | Q34: 41017
B35: 17 | C35: SET | D35: SET | E35: SDP300 | F35: 1 | H35: =F35*G35 -> 0 | J35: ﾃﾞｨｽﾍﾟﾝｻ
B36: 18 | C36: SET | D36: SET | E36: SH18-B | F36: 1 | H36: =F36*G36 -> 0 | J36: 18G GPﾃﾆ-ﾄﾞﾙﾉｽﾞﾙ12.7㎜
B37: 19 | E37: 20 | F37: 1 | H37: =F37*G37 -> 0 | J37: 設計・組立調整費
B38: 20 | E38: 20 | F38: 1 | H38: =F38*G38 -> 0 | J38: 現地納入調整費
B39: 21 | E39: 20 | F39: 1 | H39: =F39*G39 -> 0 | J39: 荷造り運賃・保険料
B40: 22 | E40: 1 | F40: 1 | H40: =F40*G40 -> 0 | J40: 特別値引き
B41: 23 | C41: SET | D41: SET | E41: ＳＨ１5-B | F41: 5 | G41: 本 | J41: 15G GPﾃﾆｰﾄﾞﾙﾉｽﾞﾙ12.7mm(ｱﾝﾊﾞｰ)ｻﾝﾌﾟﾙ
B42: 24 | C42: SET | D42: SET | E42: ＳＨ20-B | F42: 5 | G42: 本 | J42: 20G GPﾃﾆｰﾄﾞﾙﾉｽﾞﾙ12.7mm(ﾋﾟﾝｸ)ｻﾝﾌﾟﾟﾙ
H43: =F43*G43 -> 0
H44: =F44*G44 -> 0
H45: =F45*G45 -> 0
H46: =F46*G46 -> 0
H47: =F47*G47 -> 0
H48: =F48*G48 -> 0
H49: =F49*G49 -> 0
H50: =F50*G50 -> 0
H51: =F51*G51 -> 0
H52: =F52*G52 -> 0

Sheet 【97909】村田製作所　原価一覧
B2: お客先名 | E2: 村田製作所 | G2: 合計金額 | J2: =SUM(H:H) -> 642241
B3: 担当営業 | E3: 桑原
B4: 受注番号 | E4: 97909
B5: 希望納期 | E5: 41015
B6: 最終納品
B8: 見積り分類 | C8: メーカー | D8: 仕入先 | E8: 品名 / 型式 | F8: 数量 | G8: 単価 | H8: 金額 | I8: 分類合計 | J8: 詳細 | K8: 備考 | L8: 技術分類 | M8: 発注日 | N8: 発注 | O8: 納期 | P8: 入荷予定日 | Q8: 入荷日
B9: 2 | C9: 蛇の目 | D9: 蛇の目 | E9: JR2203N | F9: 1 | G9: 395000 | H9: =F9*G9 -> 395000 | K9: 桑原手配分 | M9: 41003 | P9: 41010 | Q9: 41010
B10: 2 | C10: 蛇の目 | D10: 蛇の目 | E10: 外部制御スイッチ | F10: 1 | G10: 19000 | H10: =F10*G10 -> 19000 | K10: 桑原手配分 | M10: 41003 | P10: 41010
B11: 2 | C11: 蛇の目 | D11: 蛇の目 | E11: COM2増設費用 | F11: 1 | G11: 10000 | H11: =F11*G11 -> 10000 | K11: 桑原手配分 | M11: 41003
B12: 2 | C12: 蛇の目 | D12: 蛇の目 | E12: 荷造り運賃 | F12: 1 | G12: 10000 | H12: =F12*G12 -> 10000 | K12: 桑原手配分 | M12: 41003
H13: =F13*G13 -> 0
B14: 14 | C14: 遠藤製作所 | D14: 遠藤製作所 | E14: YKMU7-0001 | F14: 1 | G14: 6800 | H14: =F14*G14 -> 6800 | J14: ロボット取付板 | M14: 41003 | P14: 41015 | Q14: 41016
B15: 14 | C15: 遠藤製作所 | D15: 遠藤製作所 | E15: YKMU7-0002 | F15: 1 | G15: 7200 | H15: =F15*G15 -> 7200 | J15: マイクロ取付板金 | M15: 41003 | P15: 41015 | Q15: 41016
B16: 14 | C16: 遠藤製作所 | D16: 遠藤製作所 | E16: YKMU7-0003 | F16: 1 | G16: 2900 | H16: =F16*G16 -> 2900 | J16: XYマイクロ取付板 | M16: 41003 | P16: 41015 | Q16: 41016
B17: 14 | C17: 遠藤製作所 | D17: 遠藤製作所 | E17: YKMU7-0004 | F17: 1 | G17: 2900 | H17: =F17*G17 -> 2900 | J17: Z軸マイクロ取付板 | M17: 41003 | P17: 41015 | Q17: 41016
B18: 14 | C18: 遠藤製作所 | D18: 遠藤製作所 | E18: YKMU7-0005-1 | F18: 1 | G18: 5600 | H18: =F18*G18 -> 5600 | J18: バルブ取付板 | M18: 41003 | P18: 41015 | Q18: 41016
B19: 14 | C19: 遠藤製作所 | D19: 遠藤製作所 | E19: YKMU7-0006 | F19: 1 | G19: 13000 | H19: =F19*G19 -> 13000 | J19: バルブホルダ | M19: 41003 | P19: 41015 | Q19: 41016
B20: 14 | C20: 遠藤製作所 | D20: 遠藤製作所 | E20: YKMU7-0007 | F20: 1 | G20: 6800 | H20: =F20*G20 -> 6800 | J20: ATD200ガイド板金 | M20: 41003 | P20: 41015 | Q20: 41016
B21: 14 | C21: 遠藤製作所 | D21: 遠藤製作所 | E21: YKMU7-0008-1 | F21: 1 | G21: 13500 | H21: =F21*G21 -> 13500 | J21: ATD突当固定ブロック | M21: 41003 | P21: 41015 | Q21: 41016
B22: 13 | C22: 遠藤製作所 | D22: 遠藤製作所 | E22: SS3231 | F22: 1 | G22: 9400 | H22: =F22*G22 -> 9400 | J22: 精密レギュレータ取付板金 | M22: 41003 | P22: 41015 | Q22: 41016
H23: =F23*G23 -> 0
B24: 15 | C24: ミスミ | D24: ミスミ | E24: PS7D-37V3A | F24: 1 | G24: 5270 | H24: =F24*G24 -> 5270 | J24: コネクタ端子台（DIN） | M24: 41003 | P24: 41010 | Q24: 41010
B25: 15 | C25: ミスミ | D25: ミスミ | E25: NEDJ-PS-SB-37-1 | F25: 1 | G25: 5569 | H25: =F25*G25 -> 5569 | J25: D-Subハーネス | M25: 41003 | P25: 41010 | Q25: 41010
B26: 14 | C26: ミスミ | D26: ミスミ | E26: XYSG40-CR | F26: 1 | G26: 32000 | H26: =F26*G26 -> 32000 | J26: XYステージ | M26: 41003 | P26: 41010 | Q26: 41010
B27: 14 | C27: ミスミ | D27: ミスミ | E27: XSG40-CR | F27: 1 | G27: 16000 | H27: =F27*G27 -> 16000 | J27: XYステージ | M27: 41003 | P27: 41010 | Q27: 41010
B28: 15 | C28: ミスミ | D28: ミスミ | E28: ESAW-TCM310-5P | F28: 1 | G28: 3022 | H28: =F28*G28 -> 3022 | J28: ブロックコモン端子台 | M28: 41003 | P28: 41010 | Q28: 41010
B29: 15 | C29: ミスミ | D29: ミスミ | E29: GPR-M-2CL-D24-D | F29: 1 | G29: 960 | H29: =F29*G29 -> 960 | J29: ハイパワーリレー 2c 7A | M29: 41003 | P29: 41010 | Q29: 41010
B30: 15 | C30: ミスミ | D30: ミスミ | E30: GPR-MS-2CD | F30: 1 | G30: 210 | H30: =F30*G30 -> 210 | J30: リレーソケット | M30: 41003 | P30: 41010 | Q30: 41010
B31: 16 | C31: ミスミ | D31: ミスミ | E31: APMTYL-N1-N1-L20 | F31: 1 | G31: 840 | H31: =F31*G31 -> 840 | J31: ねじ変換継手 | M31: 41003 | P31: 41010 | Q31: 41010
B32: 4 | C32: ミスミ | D32: ミスミ | E32: NEDJ-PT-SB-9-1 | F32: 1 | G32: 1990 | H32: =F32*G32 -> 1990 | J32: D-Subハーネス | M32: 41003 | P32: 41010 | Q32: 41010
H33: =F33*G33 -> 0
B34: 15 | C34: SMC | D34: 都機工 | E34: VT307V-5H-01-F | F34: 1 | G34: 4710 | H34: =F34*G34 -> 4710 | J34: 負圧用電磁弁（SMC） | M34: 41003 | P34: 41017 | Q34: 41017
B35: 14 | C35: クロダニューマティックス | D35: 都機工 | E35: LF-C6 | F35: 1 | G35: 4370 | H35: =F35*G35 -> 4370 | J35: 真空用フィルタ（クロダニューマティックス） | M35: 41003 | P35: 41017 | Q35: 41017
B36: 13 | C36: SMC | D36: 都機工 | E36: KJL06-M5 | F36: 10 | G36: 241 | H36: =F36*G36 -> 2410 | J36: エルボユニオン（SMC） | M36: 41003 | P36: 41009 | Q36: 41009
B37: 13 | C37: SMC | D37: 都機工 | E37: KJL06-01S | F37: 10 | G37: 192 | H37: =F37*G37 -> 1920 | J37: エルボユニオン（SMC） | M37: 41003 | P37: 41009 | Q37: 41009
B38: 13 | C38: SMC | D38: 都機工 | E38: KJY06-01S | F38: 10 | G38: 290 | H38: =F38*G38 -> 2900 | J38: サービスユニオン（SMC） | M38: 41003 | P38: 41009 | Q38: 41009
C39: SMC | D39: 都機工 | E39: IR1000-01-B-R | F39: 1 | G39: 5940 | H39: =F39*G39 -> 5940 | J39: 精密レギュレータ（SMC） | M39: 41003 | P39: 41009 | Q39: 41009
B40: 13 | C40: SMC | D40: 都機工 | E40: ISE30A-01-N-ML | F40: 1 | G40: 5940 | H40: =F40*G40 -> 5940 | J40: デジタルゲージ（SMC） | M40: 41003 | P40: 41009 | Q40: 41009
B41: 15 | C41: タカチ電機工業 | D41: 都機工 | E41: FCWS280-150-100KGSS | F41: 1 | G41: 10660 | H41: =F41*G41 -> 10660 | J41: 開閉式コントロールBOX | M41: 41003 | P41: 41015 | Q41: 41012
B42: 15 | C42: タカチ電機工業 | D42: 都機工 | E42: FCSC280-150-1 | F42: 1 | G42: 2280 | H42: =F42*G42 -> 2280 | J42: シャーシ | M42: 41003 | P42: 41015 | Q42: 41012
B43: 13 | C43: SMC | D43: 都機工 | E43: IR1010-01B | F43: 1 | G43: 5940 | H43: =F43*G43 -> 5940 | J43: 精密レギュレータ | M43: 41019 | P43: 41022 | Q43: 4/20斉藤氏受領
B45: 15 | C45: キーエンス | D45: キーエンス | E45: AP-C30 | F45: 1 | G45: 14800 | H45: 14800 | J45: 圧力センサ | M45: 41003 | Q45: 41004
B46: 15 | C46: キーエンス | D46: キーエンス | E46: AP-B03 | F46: 1 | G46: 450 | H46: =F46*G46 -> 450 | J46: 銘板、天井取付金具 | M46: 41003 | Q46: 41004
H47: =F47*G47 -> 0
H48: =F48*G48 -> 0
B49: 15 | C49: ミスミ | D49: ミスミ | E49: MRB-230 | F49: 1 | G49: 930 | H49: 930 | J49: DINレール | M49: 41009 | P49: 41015 | Q49: 41015
B50: 15 | C50: ミスミ | D50: ミスミ | E50: MD-1L-R | F50: 1 | G50: 570 | H50: 570 | J50: 配線ダクト | M50: 41009 | P50: 41015 | Q50: 41015
B51: 15 | C51: ミスミ | D51: ミスミ | E51: F1.25-M3 | F51: 1 | G51: 460 | H51: 460 | J51: 圧着端子（Y型） | M51: 41009 | P51: 41015 | Q51: 41015
H52: 0
B53: 15 | C53: 遠藤製作所 | D53: 遠藤製作所 | E53: 97909-Z01 | F53: 1 | G53: 6250 | H53: 6250 | J53: 開閉式コントロールボックス追加工図 | M53: 41009 | Q53: 41016
B54: 15 | C54: 遠藤製作所 | D54: 遠藤製作所 | E54: 97909-Z02 | F54: 1 | G54: 3750 | H54: 3750 | J54: FCC専用シャーシ追加工図 | M54: 41009 | Q54: 41016

Sheet 【97984】 ミサワ医科工業ック原価一覧
B2: お客先名 | E2: ミサワ医科工業 | G2: 合計金額 | J2: =SUM(H:H) -> 36150
B3: 担当営業 | E3: 平山
B4: 受注番号 | E4: 97984
B5: 希望納期 | E5: 41015
B6: 最終納品
B8: 見積り分類 | C8: メーカー | D8: 仕入先 | E8: 品名 / 型式 | F8: 数量 | G8: 単価 | H8: 金額 | I8: 分類合計 | J8: 詳細 | K8: 備考 | L8: 技術分類 | M8: 発注日 | N8: 発注 | O8: 納期 | P8: 入荷予定日 | Q8: 入荷日
C9: 遠藤製作所 | D9: 遠藤製作所 | E9: SS40369-1 | F9: 1 | G9: 19800 | H9: 19800 | J9: 発注願います（見積もり後日提出） | M9: 41004 | P9: 41015 | Q9: 41016
C10: 遠藤製作所 | D10: 遠藤製作所 | E10: SS40331 | F10: 1 | G10: 5800 | H10: =F10*G10 -> 5800 | J10: 発注願います（見積もり後日提出） | M10: 41004 | P10: 41015 | Q10: 41016
C11: ミスミ | D11: ミスミ | E11: NA3UCR-20-2-5 | F11: 1 | G11: 1950 | H11: 1950 | J11: NA3UCR | M11: 41003 | P11: 41008 | Q11: 41008
C12: ミスミ | D12: ミスミ | E12: MHK6.25-25.4-V120-W80 | F12: 1 | G12: 3630 | H12: 3630 | J12: ｶｰﾄﾘｯｼﾞﾋｰﾀ ｺｳｵﾝ (MCHIK) | M12: 41003 | P12: 41008 | Q12: 41008
C13: ミスミ | D13: ミスミ | E13: MSNDM6 | F13: 1 | G13: 3380 | H13: 3380 | J13: ｾﾝｻ ﾈｼﾞﾄﾘﾂｹ (MSNDM) | M13: 41003 | P13: 41008 | Q13: 41008
C14: ミスミ | D14: ミスミ | E14: SBD-S4-20 | F14: 4 | G14: 320 | H14: 1280 | J14: ﾀﾞﾝﾂｷﾛｯｶｸ･ﾛｯｶｸ･ﾊﾟｲﾌﾟｽﾍﾟｰｻ | M14: 41003 | P14: 41008 | Q14: 41008
C15: ミスミ | D15: ミスミ | E15: MSSF4-3 | F15: 1 | G15: 122 | H15: 122 | J15: ﾛｯｶｸｱﾅﾂｷﾄﾒﾈｼﾞ MSSF | M15: 41003 | P15: 41008 | Q15: 41008
C16: ミスミ | D16: ミスミ | E16: CRKB4-15 | F16: 2 | G16: 94 | H16: 188 | J16: ｼﾞｭｼﾛｰﾚｯﾄﾈｼﾞ (CRKB) | M16: 41003 | P16: 41008 | Q16: 41008

Sheet 【98116】シチズン電子 原価一覧
B2: お客先名 | E2: シチズン電子 | G2: 合計金額 | J2: =SUM(H:H) -> 912720
B3: 担当営業 | E3: 冨沢
B4: 受注番号 | E4: 98116
B5: 希望納期 | E5: 41022
B6: 最終納品
B8: 見積り分類 | C8: メーカー | D8: 仕入先 | E8: 品名 / 型式 | F8: 数量 | G8: 単価 | H8: 金額 | I8: 分類合計 | J8: 詳細 | K8: 備考 | L8: 技術分類 | M8: 発注日 | N8: 発注 | O8: 納期 | P8: 入荷予定日 | Q8: 入荷日
B9: 1 | C9: 蛇の目 | D9: 蛇の目 | E9: ANMA110 | F9: 2 | G9: 155400 | H9: =F9*G9 -> 310800 | J9: マイクロイメージチェッカ | K9: 小山さん連絡済 | L9: Y | M9: 41010 | P9: 41022 | Q9: 41019
B10: 1 | C10: 蛇の目 | D10: 蛇の目 | E10: ANM832 | F10: 2 | G10: 54600 | H10: =F10*G10 -> 109200 | J10: CSマウントカメラ（3ｍケーブル付） | L10: Y | M10: 41010 | P10: 41022 | Q10: 41019
B11: 1 | C11: 蛇の目 | D11: 蛇の目 | E11: ANM85202 | F11: 2 | G11: 7900 | H11: =F11*G11 -> 15800 | J11: 操作キーパッド（2ｍケーブル付） | L11: Y | M11: 41010 | P11: 41022 | Q11: 41019
B12: 1 | C12: 蛇の目 | D12: 蛇の目 | E12: ANB846NL | F12: 2 | G12: 32700 | H12: =F12*G12 -> 65400 | J12: Cマウントレンズ | L12: Y | M12: 41010 | P12: 41022 | Q12: 41019
B13: 1 | C13: 蛇の目 | D13: 蛇の目 | E13: ANB848 | F13: 2 | G13: 15000 | H13: =F13*G13 -> 30000 | J13: 中間リング | L13: Y | M13: 41010 | P13: 41022 | Q13: 41019
B14: 1 | C14: 蛇の目 | D14: 蛇の目 | E14: 960536003 | F14: 2 | G14: 12000 | H14: =F14*G14 -> 24000 | J14: RS232Cケーブル | L14: Y | M14: 41010 | P14: 41022 | Q14: 41019
B15: 1 | C15: 蛇の目 | D15: 蛇の目 | E15: MD-80RGB（3色） | F15: 2 | G15: 119700 | H15: =F15*G15 -> 239400 | J15: 画像処理用リング安定照明器セット | L15: Y | M15: 41010 | P15: 41022 | Q15: 41019
B16: 1 | C16: 蛇の目 | D16: 蛇の目 | E16: 荷造り運賃 | F16: 2 | G16: 1000 | H16: =F16*G16 -> 2000 | L16: Y | M16: 41010
H17: =F17*G17 -> 0
B18: 2 | C18: ミスミ | D18: ミスミ | E18: @ECHN-20061106-00010 | F18: 2 | G18: 2814 | H18: =F18*G18 -> 5628 | J18: 特注ハーネス | L18: Z | M18: 41010 | P18: 41019 | Q18: 41019
B19: 2 | C19: ミスミ | D19: ミスミ | E19: NA3GH-24-2-1 | F19: 2 | G19: 638 | H19: =F19*G19 -> 1276 | J19: 多芯電線 | L19: Z | M19: 41010 | P19: 41015 | Q19: 41015
B21: 2 | C21: ミスミ | D21: ミスミ | E21: SLSBWF7-28.5 | F21: 4 | G21: 610 | H21: =F21*G21 -> 2440 | J21: 六角支柱 | L21: Y | M21: 41010 | P21: 41015 | Q21: 41015
B22: 2 | C22: ミスミ | D22: ミスミ | E22: SP-S3-5 | F22: 4 | G22: 210 | H22: =F22*G22 -> 840 | J22: パイプスペーサ | L22: Y | M22: 41010 | P22: 41015 | Q22: 41015
B23: 2 | C23: ミスミ | D23: ミスミ | E23: SSE2B10-155 | F23: 2 | G23: 6830 | H23: =F23*G23 -> 13660 | J23: ミニチュアスライドガイド | L23: Y | M23: 41010 | P23: 41015 | Q23: 41015
B24: 2 | C24: ミスミ | D24: ミスミ | E24: SLSBWRK7-60 | F24: 8 | G24: 300 | H24: =F24*G24 -> 2400 | J24: 六角支柱 | L24: Y | M24: 41010 | P24: 41015 | Q24: 41015
B25: 2 | C25: ミスミ | D25: ミスミ | E25: CRKB4-10 | F25: 2 | G25: 78 | H25: =F25*G25 -> 156 | J25: 樹脂ローレットねじ | L25: Y | M25: 41010 | P25: 41015 | Q25: 41015
H26: =F26*G26 -> 0
B27: 2 | C27: 遠藤製作所 | D27: 遠藤製作所 | E27: 98116-Y01 | F27: 2 | G27: 8600 | H27: =F27*G27 -> 17200 | J27: 取付板 | L27: Y | M27: 41010 | P27: 41022 | Q27: 41022
B28: 2 | C28: 遠藤製作所 | D28: 遠藤製作所 | E28: 98116-Y02 | F28: 2 | G28: 2400 | H28: =F28*G28 -> 4800 | J28: スライドプレート上2 | L28: Y | M28: 41010 | P28: 41022 | Q28: 41022
B29: 2 | C29: 遠藤製作所 | D29: 遠藤製作所 | E29: 98116-Y03 | F29: 2 | G29: 2100 | H29: =F29*G29 -> 4200 | J29: CCD取付板 | L29: Y | M29: 41010 | P29: 41022 | Q29: 41022
B30: 2 | C30: 遠藤製作所 | D30: 遠藤製作所 | E30: 98116-Y04 | F30: 2 | G30: 2400 | H30: =F30*G30 -> 4800 | J30: スライドププレート下 | L30: Y | M30: 41010 | P30: 41022 | Q30: 41022
B31: 2 | C31: 遠藤製作所 | D31: 遠藤製作所 | E31: 98116-Y05 | F31: 2 | G31: 2800 | H31: =F31*G31 -> 5600 | J31: ライト取付板2 | L31: Y | M31: 41010 | P31: 41022 | Q31: 41022
B32: 2 | C32: 遠藤製作所 | D32: 遠藤製作所 | E32: 98116-Y06 | F32: 4 | G32: 1980 | H32: =F32*G32 -> 7920 | J32: ガイド板 | L32: Y | M32: 41010 | P32: 41022 | Q32: 41022
B33: 2 | C33: 遠藤製作所 | D33: 遠藤製作所 | E33: 98116-Y07 | F33: 2 | G33: 2400 | H33: =F33*G33 -> 4800 | J33: ダイヤルゲージ取付 | L33: Y | M33: 41010 | P33: 41022 | Q33: 41022
B34: 2 | C34: 遠藤製作所 | D34: 遠藤製作所 | E34: SS40287 | F34: 2 | G34: 20200 | H34: =F34*G34 -> 40400 | J34: シリンジウケ 10cc＆30ccG付 | L34: Y | M34: 41010 | P34: 41022 | Q34: 41022
H35: =F35*G35 -> 0
H36: =F36*G36 -> 0
H37: =F37*G37 -> 0
H38: =F38*G38 -> 0
H39: =F39*G39 -> 0
H40: =F40*G40 -> 0
H41: =F41*G41 -> 0
H42: =F42*G42 -> 0
H43: =F43*G43 -> 0
H44: =F44*G44 -> 0
H45: =F45*G45 -> 0
H46: =F46*G46 -> 0
... H69: =F69*G69 -> 0

Sheet 12.02.17 【96429】タイコエレクトロニクス（7号機
B2: お客先名 | E2: タイコエレクトロニクス | G2: 合計金額 | J2: =SUM(H:H) -> 735596
B3: 担当営業 | E3: 平山
B4: 受注番号 | E4: 96429
B5: 希望納期 | E5: 40973
B6: 最終納品 | E6: 40997
B8: 見積り分類 | C8: メーカー | D8: 仕入先 | E8: 品名 / 型式 | F8: 数量 | G8: 単価 | H8: 金額 | I8: 分類合計 | J8: 詳細 | K8: 備考 | L8: 技術分類 | M8: 発注日 | N8: 発注 | O8: 納期 | P8: 入荷予定日 | Q8: 入荷日
B9: 1 | C9: 蛇の目 | D9: 蛇の目 | E9: JR2303N（外部） | F9: 1 | G9: 546000 | H9: =F9*G9 -> 546000 | K9: 平山案件 | M9: 40956 | P9: 40973 | Q9: 40973
B10: 1 | C10: 蛇の目 | D10: 蛇の目 | E10: 外部操作スイッチ | F10: 1 | G10: 19000 | H10: =F10*G10 -> 19000 | K10: 平山案件 | M10: 40956 | P10: 40973
B11: 1 | C11: 蛇の目 | D11: 蛇の目 | E11: COM2増設費用 | F11: 1 | G11: 20000 | H11: =F11*G11 -> 20000 | K11: 平山案件 | M11: 40956 | P11: 40973
B12: 1 | C12: 蛇の目 | D12: 蛇の目 | E12: 荷造り運賃 | F12: 1 | G12: 10000 | H12: =F12*G12 -> 10000 | K12: 平山案件 | M12: 40956
H13: =F13*G13 -> 0
C14: ミスミ | D14: ミスミ | E14: SLSBWRK7-70 | F14: 4 | G14: 300 | H14: =F14*G14 -> 1200 | J14: 六角支柱 | L14: Y | M14: 40959 | P14: 40963 | Q14: 40963
C15: ミスミ | D15: ミスミ | E15: SBD-S4-8 | F15: 2 | G15: 320 | H15: =F15*G15 -> 640 | J15: 段付六角スペーサ | L15: Z | M15: 40959 | P15: 40963 | Q15: 40963
C16: ミスミ | D16: ミスミ | E16: SP-S4-8 | F16: 2 | G16: 220 | H16: =F16*G16 -> 440 | J16: パイプスペーサ | L16: Z | M16: 40959 | P16: 40963 | Q16: 40963
C17: ミスミ | D17: ミスミ | E17: KBBS3-10 | F17: 2 | G17: 380 | H17: =F17*G17 -> 760 | J17: 極低頭六角穴付ねじ | L17: Z | M17: 40959 | P17: 40963 | Q17: 40963
C18: ミスミ | D18: ミスミ | E18: SETGS10-45-SC6-M4-N4-LKC | F18: 5 | G18: 1430 | H18: =F18*G18 -> 7150 | J18: 円形支柱 | L18: X | M18: 40959 | P18: 40963 | Q18: 40963
C19: ミスミ | D19: ミスミ | E19: FSAW-K-12680-788-101005-0057 | F19: 1 | G19: 20560 | H19: =F19*G19 -> 20560 | J19: Web設計ボックス | L19: Z | M19: 40959 | P19: 40963 | Q19: 40963
C20: ミスミ | D20: ミスミ | E20: PMUF4H5-120-120-1-10-4.5 | F20: 1 | G20: 2050 | H20: =F20*G20 -> 2050 | J20: パンチングメタル | L20: Z | M20: 40959 | P20: 40963 | Q20: 40963
C21: ミスミ | D21: ミスミ | E21: MRB-260 | F21: 1 | G21: 930 | H21: =F21*G21 -> 930 | J21: DINレール | L21: Z | M21: 40959 | P21: 40963 | Q21: 40963
C22: ミスミ | D22: ミスミ | E22: C06N-09MS-09FS-CROSS-ES05 | F22: 1 | G22: 2367 | H22: =F22*G22 -> 2367 | J22: RS232Cハーネス | L22: Z | M22: 40959 | P22: 40963 | Q22: 40963
C23: ミスミ | D23: ミスミ | E23: HD-LN-4-40-05 | F23: 1 | G23: 226 | H23: =F23*G23 -> 226 | J23: Dsubロック金具 | L23: Z | M23: 40959 | P23: 40963 | Q23: 40963
C24: ミスミ | D24: ミスミ | E24: PSSFGT15-100-M5 | F24: 1 | G24: 960 | H24: =F24*G24 -> 960 | J24: SUS汎用シャフト | L24: Z | M24: 40959 | P24: 40963 | Q24: 40963
C25: ミスミ | D25: ミスミ | E25: KNCLSS4-8-20 | F25: 2 | G25: 290 | H25: =F25*G25 -> 580 | J25: 金属カラー | L25: Z | M25: 40959 | P25: 40963 | Q25: 40963
... C46: ミスミ | D46: ミスミ | E46: SAVT-JS-B-2-0.5 | F46: 1 | G46: 448 | H46: =F46*G46 -> 448 | J46: SMコネクタハーネス（中継用メス） | L46: Z | M46: 40959 | P46: 40963 | Q46: 40963
C48: 遠藤製作所 | D48: 遠藤製作所 | E48: SS3163 | F48: 1 | G48: 8600 | H48: 8600 | J48: ロボット取付板 | L48: Y | M48: 40956 | P48: 40973 | Q48: 40970
C49: 遠藤製作所 | D49: 遠藤製作所 | E49: SS3164-01 | F49: 1 | G49: 10800 | H49: =F49*G49 -> 10800 | J49: スターラー台 | L49: Z | M49: 40956 | P49: 40973 | Q49: 40970
C50: 遠藤製作所 | D50: 遠藤製作所 | E50: SS3165-01 | F50: 1 | G50: 10800 | H50: =F50*G50 -> 10800 | J50: ワーク冶具ベース | L50: X | M50: 40956 | P50: 40973 | Q50: 40970
C51: 遠藤製作所 | D51: 遠藤製作所 | E51: SS3170 | F51: 1 | G51: 5400 | H51: =F51*G51 -> 5400 | J51: ACJ-3 精密RG取付板 | L51: Z | M51: 40956 | P51: 40973 | Q51: 40970
C52: 遠藤製作所 | D52: 遠藤製作所 | E52: SS40576 | F52: 1 | G52: 2900 | H52: =F52*G52 -> 2900 | J52: CCD取付板（K） | L52: Y | M52: 40956 | P52: 40973 | Q52: 40970
C53: 遠藤製作所 | D53: 遠藤製作所 | E53: SS40577 | F53: 1 | G53: 3400 | H53: =F53*G53 -> 3400 | J53: 照明取付板（CA-DRW8M） | L53: Y | M53: 40956 | P53: 40973 | Q53: 40970
C54: 遠藤製作所 | D54: 遠藤製作所 | E54: SS40578 | F54: 1 | G54: 1980 | H54: =F54*G54 -> 1980 | J54: 位置決めピンΦ8 | L54: X | M54: 40956 | P54: 40973 | Q54: 40970
C55: 遠藤製作所 | D55: 遠藤製作所 | E55: SS40579 | F55: 1 | G55: 1980 | H55: =F55*G55 -> 1980 | J55: 位置決めピンΦ6 | L55: X | M55: 40956 | P55: 40973 | Q55: 40970
C56: 遠藤製作所 | D56: 遠藤製作所 | E56: SS40585-01 | F56: 1 | G56: 3800 | H56: =F56*G56 -> 3800 | J56: シャフト板金 | L56: Z | M56: 40956 | P56: 40973 | Q56: 40970
C57: 遠藤製作所 | D57: 遠藤製作所 | E57: SS40613 | F57: 1 | G57: 3400 | H57: =F57*G57 -> 3400 | J57: CCD取付板（K） ノズル用 | L57: Y | M57: 40956 | P57: 40973 | Q57: 40970
C58: 遠藤製作所 | D58: 遠藤製作所 | E58: SS40614-03 | F58: 1 | G58: 7800 | H58: =F58*G58 -> 7800 | J58: ノズル位置合わせカメラ用ベース | L58: Z | M58: 40956 | P58: 40973 | Q58: 40970
C59: 遠藤製作所 | D59: 遠藤製作所 | E59: SS40615 | F59: 2 | G59: 1400 | H59: =F59*G59 -> 2800 | J59: プリズム横押え板金 | L59: Z | M59: 40956 | P59: 40973 | Q59: 40970
B60: 追加 | C60: 遠藤製作所 | D60: 遠藤製作所 | E60: 96429-Z01 | F60: 1 | G60: 9800 | H60: =F60*G60 -> 9800 | J60: スターラースペーサ(SW-101N) | L60: Z | M60: 40961 | P60: 40973 | Q60: 40970
B61: 追加 | C61: 遠藤製作所 | D61: 遠藤製作所 | E61: SS40618 | F61: 1 | G61: 5900 | H61: 5900 | J61: 捨て打ちﾍﾞｰｽ | M61: 40969 | P61: 40973 | Q61: 40970
B62: 追加 | C62: 遠藤製作所 | D62: 遠藤製作所 | E62: SS40619 | F62: 1 | G62: 1900 | H62: 1900 | J62: 捨て打ちﾍﾞｰｽ連結板 | M62: 40969 | P62: 40973 | Q62: 40970
B63: 追加 | C63: 遠藤製作所 | D63: 遠藤製作所 | E63: SS40641 | F63: 1 | G63: 5200 | H63: 5200 | J63: ﾌﾟﾘｽﾞﾑ取付板2 | M63: 40969 | P63: 40973 | Q63: 40970

Sheet 12.02.17 【96433】タイコエレクトロニクス（8号機
B2: お客先名 | E2: タイコエレクトロニクス | G2: 合計金額 | J2: =SUM(H:H) -> 735596
B3: 担当営業 | E3: 平山
B4: 受注番号 | E4: 96433
B5: 希望納期 | E5: 40973
B6: 最終納品 | E6: 40997
B8: 見積り分類 | C8: メーカー | D8: 仕入先 | E8: 品名 / 型式 | F8: 数量 | G8: 単価 | H8: 金額 | I8: 分類合計 | J8: 詳細 | K8: 備考 | L8: 技術分類 | M8: 発注日 | N8: 発注 | O8: 納期 | P8: 入荷予定日 | Q8: 入荷日
B9: 1 | C9: 蛇の目 | D9: 蛇の目 | E9: JR2303N（外部） | F9: 1 | G9: 546000 | H9: =F9*G9 -> 546000 | K9: 平山案件 | M9: 40956 | P9: 40973 | Q9: 40973
B10: 1 | C10: 蛇の目 | D10: 蛇の目 | E10: 外部操作スイッチ | F10: 1 | G10: 19000 | H10: =F10*G10 -> 19000 | K10: 平山案件 | M10: 40956 | P10: 40973
B11: 1 | C11: 蛇の目 | D11: 蛇の目 | E11: COM2増設費用 | F11: 1 | G11: 20000 | H11: =F11*G11 -> 20000 | K11: 平山案件 | M11: 40956 | P11: 40973
B12: 1 | C12: 蛇の目 | D12: 蛇の目 | E12: 荷造り運賃 | F12: 1 | G12: 10000 | H12: =F12*G12 -> 10000 | K12: 平山案件 | M12: 40956
H13: =F13*G13 -> 0
C14: ミスミ | D14: ミスミ | E14: SLSBWRK7-70 | F14: 4 | G14: 300 | H14: =F14*G14 -> 1200 | J14: 六角支柱 | L14: Y | M14: 40959 | P14: 40963 | Q14: 40963
C15: ミスミ | D15: ミスミ | E15: SBD-S4-8 | F15: 2 | G15: 320 | H15: =F15*G15 -> 640 | J15: 段付六角スペーサ | L15: Z | M15: 40959 | P15: 40963 | Q15: 40963
C16: ミスミ | D16: ミスミ | E16: SP-S4-8 | F16: 2 | G16: 220 | H16: =F16*G16 -> 440 | J16: パイプスペーサ | L16: Z | M16: 40959 | P16: 40963 | Q16: 40963
C17: ミスミ | D17: ミスミ | E17: KBBS3-10 | F17: 2 | G17: 380 | H17: =F17*G17 -> 760 | J17: 極低頭六角穴付ねじ | L17: Z | M17: 40959 | P17: 40963 | Q17: 40963
C18: ミスミ | D18: ミスミ | E18: SETGS10-45-SC6-M4-N4-LKC | F18: 5 | G18: 1430 | H18: =F18*G18 -> 7150 | J18: 円形支柱 | L18: X | M18: 40959 | P18: 40963 | Q18: 40963
C19: ミスミ | D19: ミスミ | E19: FSAW-K-12680-788-101005-0057 | F19: 1 | G19: 20560 | H19: =F19*G19 -> 20560 | J19: Web設計ボックス | L19: Z | M19: 40959 | P19: 40963 | Q19: 40963
C20: ミスミ | D20: ミスミ | E20: PMUF4H5-120-120-1-10-4.5 | F20: 1 | G20: 2050 | H20: =F20*G20 -> 2050 | J20: パンチングメタル | L20: Z | M20: 40959 | P20: 40963 | Q20: 40963
C21: ミスミ | D21: ミスミ | E21: MRB-260 | F21: 1 | G21: 930 | H21: =F21*G21 -> 930 | J21: DINレール | L21: Z | M21: 40959 | P21: 40963 | Q21: 40963
C22: ミスミ | D22: ミスミ | E22: C06N-09MS-09FS-CROSS-ES05 | F22: 1 | G22: 2367 | H22: =F22*G22 -> 2367 | J22: RS232Cハーネス | L22: Z | M22: 40959 | P22: 40963 | Q22: 40963
C23: ミスミ | D23: ミスミ | E23: HD-LN-4-40-05 | F23: 1 | G23: 226 | H23: =F23*G23 -> 226 | J23: Dsubロック金具 | L23: Z | M23: 40959 | P23: 40963 | Q23: 40963
C24: ミスミ | D24: ミスミ | E24: PSSFGT15-100-M5 | F24: 1 | G24: 960 | H24: =F24*G24 -> 960 | J24: SUS汎用シャフト | L24: Z | M24: 40959 | P24: 40963 | Q24: 40963
C25: ミスミ | D25: ミスミ | E25: KNCLSS4-8-20 | F25: 2 | G25: 290 | H25: =F25*G25 -> 580 | J25: 金属カラー | L25: Z | M25: 40959 | P25: 40963 | Q25: 40963
... C59: 遠藤製作所 | D59: 遠藤製作所 | E59: SS40615 | F59: 2 | G59: 1400 | H59: =F59*G59 -> 2800 | J59: プリズム横押え板金 | L59: Z | M59: 40956 | P59: 40973 | Q59: 40970
B60: 追加 | C60: 遠藤製作所 | D60: 遠藤製作所 | E60: 96429-Z01 | F60: 1 | G60: 9800 | H60: =F60*G60 -> 9800 | J60: スターラースペーサ(SW-101N) | L60: Z | M60: 40961 | P60: 40973 | Q60: 40970
B61: 追加 | C61: 遠藤製作所 | D61: 遠藤製作所 | E61: SS40618 | F61: 1 | G61: 5900 | H61: 5900 | J61: 捨て打ちﾍﾞ-ｽ | M61: 40969 | P61: 40973 | Q61: 40970
B62: 追加 | C62: 遠藤製作所 | D62: 遠藤製作所 | E62: SS40619 | F62: 1 | G62: 1900 | H62: 1900 | J62: 捨て打ちﾍﾞ-ｽ連結板 | M62: 40969 | P62: 40973 | Q62: 40970
B63: 追加 | C63: 遠藤製作所 | D63: 遠藤製作所 | E63: SS40641 | F63: 1 | G63: 5200 | H63: 5200 | J63: ﾌﾟﾘｽﾞﾑ取付板2 | M63: 40969 | P63: 40973 | Q63: 40970

Sheet コピー【97281】 東亜電機（シャープ多気）
B2: お客先名 | E2: 東亜電気 | G2: 合計金額 | J2: =SUM(H:H) -> 53688436
B4: お客先名 | E4: 東亜電気（シャープ多気） | G4: 合計金額 | J4: =SUM(H:H) -> 53688436
B5: 担当営業 | E5: 真保
B6: 受注番号 | E6: 97281 | G6: 備考
B7: 希望納期 | E7: 41015
B8: 最終納品
B10: 見積り分類 | C10: メーカー | D10: 仕入先 | E10: 品名 / 型式 | F10: 数量 | G10: 単価 | H10: 金額 | I10: 分類合計 | J10: 詳細 | K10: 備考 | L10: 技術分類 | M10: 発注日 | N10: 発注 | O10: 納期 | P10: 入荷予定日 | Q10: 入荷日
C11: 蛇の目 | D11: 蛇の目 | E11: JR2203N | F11: 130 | G11: 290000 | H11: =F11*G11 -> 37700000 | K11: 上野部長対応 | M11: 40981 | P11: 4/9-70台（引き取り） | Q11: 4/9-70・
C12: 蛇の目 | D12: 蛇の目 | E12: 荷造り運賃 | H12: =F12*G12 -> 0 | M12: 40981 | P12: 4/23-60台（引き取り）
C13: 蛇の目 | D13: 蛇の目 | E13: JR-TB | H13: =F13*G13 -> 0 | M13: 在庫使用
C14: 蛇の目 | D14: 蛇の目 | E14: ﾌﾟﾘﾝﾄ基板 | F14: 3 | G14: 31000 | H14: 93000 | M14: 41011 | P14: 41017 | Q14: 41016
C16: SMC | D16: 都機工 | E16: ＭＧＪ6-10 | F16: 264 | G16: 4840 | H16: =F16*G16 -> 1277760 | K16: 4個予備部品 | M16: 40991 | P16: 4/5 ,11 | Q16: 4/5-144･4/10-119・4/13-1
C17: SMC | D17: 都機工 | E17: CXSJM6-10 | F17: 264 | G17: 4000 | H17: =F17*G17 -> 1056000 | K17: 4個予備部品 | M17: 40991 | P17: 4/5 ,11 | Q17: 4/5-144・4/10-119・4/13-1
C18: SMC | D18: 都機工 | E18: KJL04-M3 | F18: 1060 | G18: 253 | H18: =F18*G18 -> 268180 | K18: 4個予備部品 | M18: 40991 | P18: 4/5 ,11 | Q18: 4/5-576･4/10-480
C19: SMC | D19: 都機工 | E19: KJU04-00 | F19: 260 | G19: 235 | H19: =F19*G19 -> 61100 | M19: 40991 | P19: 4/5 ,11 | Q19: 4/5-72・4/6-72・4/10-116
C20: SMC | D20: 都機工 | E20: AS1002F-04 | F20: 260 | G20: 650 | H20: =F20*G20 -> 169000 | M20: 40991 | P20: 4/5 ,11 | Q20: 4/5-72・4/6-72・4/10-116
C21: SMC | D21: 都機工 | E21: AW10-ALQ01 | F21: 134 | G21: 3327 | H21: =F21*G21 -> 445818 | K21: 4個予備部品 | M21: 40991 | P21: 4/5 ,11 | Q21: 4/5-72・4/10-62
C22: SMC | D22: 都機工 | E22: SS5YJ3-S41-02-C4 | F22: 134 | G22: 2550 | H22: =F22*G22 -> 341700 | K22: 4個予備部品 | M22: 40991 | P22: 4/5 ,11 | Q22: 4/5-72・4/10-62
C23: SMC | D23: 都機工 | E23: SYJ3140-5MOZ | F23: 268 | G23: 3950 | H23: =F23*G23 -> 1058600 | K23: 4個予備部品 | M23: 40991 | P23: 4/5 ,11 | Q23: 4/5-144･4/10-124
C24: SMC | D24: 都機工 | E24: SY100-30-4A-6 | F24: 268 | G24: 80 | H24: =F24*G24 -> 21440 | K24: 4個予備部品 | M24: 40991 | P24: 4/5 ,11 | Q24: 4/5-144･4/10-124
C25: SMC | D25: 都機工 | E25: KQ2L04-01S | F25: 130 | G25: 169 | H25: =F25*G25 -> 21970 | M25: 40991 | P25: 4/5 ,11 | Q25: 4/5-72・4/10-58
C26: SMC | D26: 都機工 | E26: AN10-01 | F26: 260 | G26: 250 | H26: =F26*G26 -> 65000 | M26: 40991 | P26: 4/5 ,11 | Q26: 4/5-144･4/10-116
C27: SMC | D27: 都機工 | E27: KJU06-00 | F27: 260 | G27: 245 | H27: =F27*G27 -> 63700 | M27: 40991 | P27: 4/5 ,11 | Q27: 4/5-72・4/6-72・4/10-116
C28: SUNX | D28: 都機工 | E28: EX-14A | F28: 264 | G28: 3000 | H28: =F28*G28 -> 792000 | K28: 4個予備部品 | M28: 40991 | P28: 4/5 ,11 | Q28: 4/5-144･4/10-120
C29: SUNX | D29: 都機工 | E29: MS-EX10-1 | F29: 260 | G29: 170 | H29: =F29*G29 -> 44200 | M29: 40991 | P29: 4/5 ,11 | Q29: 4/5-144･4/10-116
D30: 都機工 | E30: SG30 | F30: 1 | G30: 11200 | H30: =F30*G30 -> 11200 | M30: 40996 | P30: 40998 | Q30: 40998
D31: 都機工 | E31: 2046S DG | F31: 1 | G31: 3576 | H31: =F31*G31 -> 3576 | M31: 40996 | P31: 40998 | Q31: 40998
D32: 都機工 | E32: KJU04-00 | F32: 260 | G32: 235 | H32: =F32*G32 -> 61100 | M32: 41010 | P32: 41012 | Q32: 41012
D33: 都機工 | E33: 2046S DG | F33: 3 | G33: 3576 | H33: =F33*G33 -> 10728 | M33: 41010 | P33: 41012 | Q33: 41012
C35: MISUMI | D35: MISUMI | E35: MWI-MIL14-ECON5 | F35: 130 | G35: 2347 | H35: 305110 | Q35: 40994
C36: MISUMI | D36: MISUMI | E36: 37104-4080-G00FL-8P | F36: 35 | G36: 1119 | H36: 39165 | Q36: 3/26-15・4/9-20
C37: MISUMI | D37: MISUMI | E37: 37104-3101-000FL-8P | F37: 35 | G37: 1038 | H37: 36330 | P37: 41003 | Q37: 41003
C38: MISUMI | D38: MISUMI | E38: SLCG5.5-14 | F38: 120 | G38: 80 | H38: 9600
C39: MISUMI | D39: MISUMI | E39: SLCG5.5-14 | F39: 400 | G39: 80 | H39: 32000
C40: MISUMI | D40: MISUMI | E40: CRKB3-10 | F40: 260 | G40: 17 | H40: 4420
C41: MISUMI | D41: MISUMI | E41: MSBY8-40 | F41: 130 | G41: 342 | H41: 44460 | Q41: 41003
C42: MISUMI | D42: MISUMI | E42: SHCDG4-14 | F42: 520 | G42: 132 | H42: 68640 | Q42: 4/4･4/12-2(代替品)
C43: MISUMI | D43: MISUMI | E43: SLCG5.5-14 | F43: 520 | G43: 80 | H43: 41600
C44: MISUMI | D44: MISUMI | E44: SLCG5.5-8 | F44: 520 | G44: 70 | H44: 36400 | Q44: 41003
C45: MISUMI | D45: MISUMI | E45: AXSH212-VC-1PD2-2EB-1.5-1AC-2DA-F | F45: 5 | G45: 6615 | H45: 33075
C46: MISUMI | D46: MISUMI | E46: AXSH212-VC-1PD2-2EB-1.5-1AC-2DA-F | F46: 125 | G46: 6615 | H46: 826875
C47: MISUMI | D47: MISUMI | E47: XSG25-CR | F47: 130 | G47: 15500 | H47: 465000 | Q47: 3/23-30・4/2-40･4/19-30・
C48: MISUMI | D48: MISUMI | E48: XYSG25-CR | F48: 130 | G48: 31000 | H48: 930000 | Q48: 3/23-30・4/2-40･4/19-30・
C49: MISUMI | D49: MISUMI | E49: AXSH212-VC-1PD2-2EB-1.5-1AC-2DA-F | F49: 130 | G49: 6615 | H49: 859950 | Q49: 3/21-5
C50: MISUMI | D50: MISUMI | E50: XYSG25-CR | F50: 130 | G50: 31000 | H50: 4030000
C51: MISUMI | D51: MISUMI | E51: XSG25-CR | F51: 130 | G51: 15500 | H51: 2015000
D52: MISUMI | E52: CBSTSR3-5 | F52: 1060 | G52: 150 | H52: 159000 | Q52: 40994
D53: MISUMI | E53: KN-2-1 | F53: 1 | G53: 1060 | H53: 1060 | P53: 41001 | Q53: 41001
D54: MISUMI | E54: WMB-1 | F54: 2 | G54: 1450 | H54: 2900 | P54: 41001 | Q54: 41001
D55: MISUMI | E55: CTSV-10025-100P | F55: 10 | G55: 95 | H55: 950 | P55: 41001 | Q55: 41001
D56: MISUMI | E56: CTSV-20025-100P | F56: 10 | G56: 300 | H56: 3000 | P56: 41001 | Q56: 41001
D57: MISUMI | E57: CTSV-25036-100P | F57: 5 | G57: 690 | H57: 3450 | P57: 41001 | Q57: 41001
D58: MISUMI | E58: 350689-1 | F58: 6 | G58: 817 | H58: 4902 | P58: 41003 | Q58: 41003
D59: MISUMI | E59: 350780-1-20P | F59: 7 | G59: 1083 | H59: 7581 | P59: 41003 | Q59: 41003
D60: MISUMI | E60: %WRFH-4050-120319-116 | F60: 1 | G60: 7854 | H60: 7854 | M60: 40990 | P60: 41005 | Q60: 41005
D61: MISUMI | E61: %WRFH-4050-120319-116 | F61: 129 | G61: 7140 | H61: 7140 | M61: 40990 | P61: 41015 | Q61: 41015
D62: MISUMI | E62: BOX-SCB2-5 | F62: 1 | G62: 4400 | H62: 4400 | P62: 41004 | Q62: 41004
D63: MISUMI | E63: BOX-SCB2-10 | F63: 1 | G63: 4900 | H63: 4900 | P63: 41004 | Q63: 41004
D64: MISUMI | E64: BOX-SCB3-5 | F64: 1 | G64: 3800 | H64: 3800 | P64: 41004 | Q64: 41004
D65: MISUMI | E65: BOX-SCB3-6* | F65: 1 | G65: 3200 | H65: 3200 | P65: 41004 | Q65: 41004
D66: MISUMI | E66: BOX-SCB3-8* | F66: 1 | G66: 3300 | H66: 3300 | P66: 41004 | Q66: 41004
D67: MISUMI | E67: BOX-SCB3-15* | F67: 2 | G67: 3700 | H67: 7400 | P67: 41004 | Q67: 41004
D68: MISUMI | E68: BOX-SCB4-6* | F68: 1 | G68: 3900 | H68: 3900 | P68: 41004 | Q68: 41004
D69: MISUMI | E69: BOX-SCB4-8 | F69: 2 | G69: 3600 | H69: 7200 | P69: 41004 | Q69: 41004
D70: MISUMI | E70: BOX-SCB4-10* | F70: 2 | G70: 3800 | H70: 7600 | P70: 41004 | Q70: 41004
D71: MISUMI | E71: BOX-SCB4-12* | F71: 2 | G71: 4000 | H71: 8000 | P71: 41004 | Q71: 41004
D72: MISUMI | E72: BOX-SCB4-15* | F72: 1 | G72: 44000 | H72: 4400 | P72: 41004 | Q72: 41004
D73: MISUMI | E73: BOX-SCB5-25* | F73: 1 | G73: 5440 | H73: 5440 | P73: 41004 | Q73: 41004
... D78: MISUMI | E78: SCB2.5-15 | F78: 520 | G78: 33 | H78: 17160 | P78: 41004 | Q78: 41004
D79: MISUMI | E79: RSCB4-8 | F79: 1300 | G79: 6 | H79: 7800 | Q79: 41004
D80: MISUMI | E80: BOX-SCB4-8* | F80: 4 | G80: 3600 | H80: 14400 | P80: 41005 | Q80: 41005
D81: MISUMI | E81: BOX-SCB3-5 | F81: 100 | G81: 10 | H81: 1000 | P81: 41005 | Q81: 41005
D82: MISUMI | E82: BOX-SCB3-6 | F82: 100 | G82: 6 | H82: 600 | P82: 41005 | Q82: 41005
D83: MISUMI | E83: BOX-MSSFS4-8 | F83: 1 | G83: 2900 | H83: 2900 | P83: 41005 | Q83: 41005
D84: MISUMI | E84: BOX-SKNTR4* | F84: 1 | G84: 2800 | H84: 2800 | Q84: 41011
D85: MISUMI | E85: BOX-SCB4-25* | F85: 1 | G85: 3200 | H85: 3200 | P85: 41010 | Q85: 41010
D86: MISUMI | E86: CRKB3-12 | F86: 220 | G86: 17 | H86: 3740 | P86: 41010 | Q86: 41010
D87: MISUMI | E87: BOX-SCB4-25* | F87: 2 | G87: 3200 | H87: 6400 | P87: 41010 | Q87: 41010
D88: MISUMI | E88: BOX-SCB3-25* | F88: 1 | G88: 2800 | H88: 2800 | P88: 41010 | Q88: 41010
D89: MISUMI | E89: SCB3-25 | F89: 100 | G89: 9 | H89: 900 | P89: 41010 | Q89: 41010
D90: MISUMI | E90: 350689-1 | F90: 3 | G90: 817 | H90: 2451 | P90: 41022
D91: MISUMI | E91: 350780-1-20P | F91: 7 | G91: 1083 | H91: 7581 | P91: 41022

Sheet 【97645】ミツミ電機 原価一覧
B2: お客先名 | E2: ミツミ電機 | G2: 合計金額 | J2: =SUM(H:H) -> 222900
B3: 担当営業 | E3: 山澤
B4: 受注番号 | E4: 97645
B5: 希望納期 | E5: 41022
B6: 最終納品
B8: 見積り分類 | C8: メーカー | D8: 仕入先 | E8: 品名 / 型式 | F8: 数量 | G8: 単価 | H8: 金額 | I8: 分類合計 | J8: 詳細 | K8: 備考 | L8: 技術分類 | M8: 発注日 | N8: 発注 | O8: 納期 | P8: 入荷予定日 | Q8: 入荷日
C9: ミスミ | D9: ミスミ | E9: XYSG25 | F9: 3 | G9: 31000 | H9: =F9*G9 -> 93000 | J9: XYステージ（リニアボール） | L9: Y | M9: 41008 | P9: 41012 | Q9: 41012
C10: ミスミ | D10: ミスミ | E10: SETGR10-45-LKC | F10: 6 | G10: 380 | H10: =F10*G10 -> 2280 | J10: 円形支柱 | L10: Y | M10: 41008 | P10: 41012 | Q10: 41012
C11: ミスミ | D11: ミスミ | E11: %WRFH-4050-120328-4 | F11: 3 | G11: 24600 | H11: =F11*G11 -> 73800 | J11: 特注ハーネス | L11: Z | M11: 41008 | P11: 41022 | Q11: 41022
C12: ミスミ | D12: ミスミ | E12: SCB2-10 | F12: 12 | G12: 85 | H12: =F12*G12 -> 1020 | J12: 六角穴付ねじ | L12: Y | M12: 41008 | P12: 41012 | Q12: 41012
C14: 遠藤製作所 | D14: 遠藤製作所 | E14: 97645-Y01 | F14: 3 | G14: 4200 | H14: =F14*G14 -> 12600 | J14: ツール板 | L14: Y | M14: 41008 | Q14: 41022
C15: 遠藤製作所 | D15: 遠藤製作所 | E15: 97645-Y02 | F15: 3 | G15: 2500 | H15: =F15*G15 -> 7500 | J15: XYステージ取付上板 | L15: Y | M15: 41008 | Q15: 41022
C16: 遠藤製作所 | D16: 遠藤製作所 | E16: 97645-Y03 | F16: 3 | G16: 2500 | H16: =F16*G16 -> 7500 | J16: XYステージ取付下板 | L16: Y | M16: 41008 | Q16: 41022
C17: 遠藤製作所 | D17: 遠藤製作所 | E17: 97645-Y04 | F17: 3 | G17: 4200 | H17: =F17*G17 -> 12600 | J17: 温調取付板（XYSG25） | L17: Y | M17: 41008 | Q17: 41022
C18: 遠藤製作所 | D18: 遠藤製作所 | E18: 97645-Y05 | F18: 3 | G18: 4200 | H18: =F18*G18 -> 12600 | J18: 温調固定板 | L18: Y | M18: 41008 | Q18: 41022
H19: =F19*G19 -> 0
H20: =F20*G20 -> 0
H21: =F21*G21 -> 0
H22: =F22*G22 -> 0
H23: =F23*G23 -> 0
H24: =F24*G24 -> 0
H25: =F25*G25 -> 0
H26: =F26*G26 -> 0
H27: =F27*G27 -> 0
H28: =F28*G28 -> 0
H29: =F29*G29 -> 0
H30: =F30*G30 -> 0
... H68: =F68*G68 -> 0

Sheet 【98057】富士化学産業（株） 原価一覧
B2: お客先名 | E2: 富士化学産業株式会社 | G2: 合計金額 | J2: =SUM(H:H) -> 99300
B3: 担当営業 | E3: 中村
B4: 受注番号 | E4: 98057
B5: 希望納期 | E5: 2012/5/中旬
B6: 最終納品
B8: 見積り分類 | C8: メーカー | D8: 仕入先 | E8: 品名 / 型式 | F8: 数量 | G8: 単価 | H8: 金額 | I8: 分類合計 | J8: 詳細 | K8: 備考 | L8: 技術分類 | M8: 発注日 | N8: 発注 | O8: 納期 | P8: 入荷予定日 | Q8: 入荷日
C9: 蛇の目 | D9: 蛇の目 | E9: JRN 塗布用PCソフト | F9: 1 | G9: 30000 | H9: =F9*G9 -> 30000 | J9: JRVよりJRNに訂正交換(5/15入荷） | L9: Z | M9: 41025 | P9: 41038 | Q9: 41038
C10: 蛇の目 | D10: 蛇の目 | E10: 送料 | F10: 1 | G10: 1000 | H10: =F10*G10 -> 1000 | L10: Z | M10: 41025
H11: =F11*G11 -> 0
C13: 遠藤製作所 | D13: 遠藤製作所 | E13: 98057-Y01 | F13: 1 | G13: 4200 | H13: 4200 | J13: ツール板 | K13: ツール治具 | L13: Y | M13: 41025 | P13: 41040 | Q13: 41038
C14: 遠藤製作所 | D14: 遠藤製作所 | E14: 98057-Y02 | F14: 1 | G14: 3500 | H14: 3500 | J14: 温調取付板 | K14: ツール治具 | L14: Y | M14: 41025 | P14: 41040 | Q14: 41038
C15: 遠藤製作所 | D15: 遠藤製作所 | E15: SS40079 | F15: 1 | G15: 13800 | H15: =F15*G15 -> 13800 | J15: 740,752,780用ホルダ（Ｐ＝２５） | K15: ツール治具 | L15: Y | M15: 41025 | P15: 41040 | Q15: 41038
C16: 遠藤製作所 | D16: 遠藤製作所 | E16: SS4248 | F16: 1 | G16: 9800 | H16: 9800 | J16: 井桁ベース（２００ｘ２００） | K16: 井桁治具 | L16: X | M16: 41025 | P16: 41040 | Q16: 41038
C17: 遠藤製作所 | D17: 遠藤製作所 | E17: SS4736 | F17: 2 | G17: 4200 | H17: 8400 | J17: 井桁レール①（□２００） | K17: 井桁治具 | L17: X | M17: 41025 | P17: 41040 | Q17: 41038
C18: 遠藤製作所 | D18: 遠藤製作所 | E18: SS4737 | F18: 2 | G18: 6200 | H18: 12400 | J18: 井桁レール②（□２００） | K18: 井桁治具 | L18: X | M18: 41025 | P18: 41040 | Q18: 41038
C19: 遠藤製作所 | D19: 遠藤製作所 | E19: SS4738 | F19: 4 | G19: 2100 | H19: 8400 | J19: 井桁ストッパー① | K19: 井桁治具 | L19: X | M19: 41025 | P19: 41040 | Q19: 41038
C20: 遠藤製作所 | D20: 遠藤製作所 | E20: SS4739 | F20: 2 | G20: 3900 | H20: 7800 | J20: 井桁ストッパー② | K20: 井桁治具 | L20: X | M20: 41025 | P20: 41040 | Q20: 41038
C21: 遠藤製作所 | D21: 遠藤製作所 | E21: 98057-Y01-1 | F21: 1 | J21: 穴径訂正追加工 | K21: ツール治具 | L21: Y | M21: 41043 | P21: 41044 | Q21: 41045
H22: 0
H23: 0
H24: 0
H25: 0
H26: 0
H27: 0
H28: 0
H29: =F29*G29 -> 0
H30: =F30*G30 -> 0
H31: =F31*G31 -> 0
H32: =F32*G32 -> 0
H33: =F33*G33 -> 0
H34: =F34*G34 -> 0
H35: =F35*G35 -> 0
H36: =F36*G36 -> 0
H37: =F37*G37 -> 0
H38: =F38*G38 -> 0
H39: =F39*G39 -> 0
H40: =F40*G40 -> 0
... H63: =F63*G63 -> 0

Sheet 【98057】富士化学産業（株） 原価一覧-2
B2: お客先名 | E2: 富士化学産業株式会社 | G2: 合計金額 | J2: =SUM(H:H) -> 53116
B3: 担当営業 | E3: 中村
B4: 受注番号 | E4: 98057
B5: 希望納期 | E5: 2012/5/中旬
B6: 最終納品
B8: 見積り分類 | C8: メーカー | D8: 仕入先 | E8: 品名 / 型式 | F8: 数量 | G8: 単価 | H8: 金額 | I8: 分類合計 | J8: 詳細 | K8: 備考 | L8: 技術分類 | M8: 発注日 | N8: 発注 | O8: 納期 | P8: 入荷予定日 | Q8: 入荷日
C9: 蛇の目 | D9: 蛇の目 | E9: JRV 塗布用PCソフト | F9: 1 | G9: 30000 | H9: =F9*G9 -> 30000 | L9: Z
C10: 蛇の目 | D10: 蛇の目 | E10: 送料 | F10: 1 | G10: 1000 | H10: =F10*G10 -> 1000 | L10: Z
H11: =F11*G11 -> 0
C12: ミスミ | D12: ミスミ | E12: PNUIC-REX-USB60F-R | F12: 1 | G12: 5200 | H12: =F12*G12 -> 5200 | J12: USBコンバータ | L12: Z
C13: ミスミ | D13: ミスミ | E13: DGC-9SS | F13: 1 | G13: 203 | H13: =F13*G13 -> 203 | J13: ジェンダーチェンジャー | L13: Z
C14: ミスミ | D14: ミスミ | E14: @ECHN-20111222-00025 | F14: 1 | G14: 1767 | H14: =F14*G14 -> 1767 | J14: Web設計ハーネス | L14: Z
C15: ミスミ | D15: ミスミ | E15: SCB4-35 | F15: 2 | G15: 88 | H15: =F15*G15 -> 176 | J15: 六角穴付ボルト | L15: Y
C16: ミスミ | D16: ミスミ | E16: XSG40-CZ | F16: 1 | G16: 12500 | H16: =F16*G16 -> 12500 | J16: リニアボールＸ軸ステージ | L16: Y
C17: ミスミ | D17: ミスミ | E17: ＡＰＭＴＳ－Ｎ１－Ｔ２ | F17: 1 | G17: 1100 | H17: =F17*G17 -> 1100 | J17: ねじ変換継手 | L17: Y
C18: ミスミ | D18: ミスミ | E18: ＬＲＬＢ５－１０ | F18: 1 | G18: 570 | H18: =F18*G18 -> 570 | J18: 長尺ローレット付きボルト | L18: Y
C19: ミスミ | D19: ミスミ | E19: ＮＯＳＣ５－１０－１６ | F19: 1 | G19: 600 | H19: =F19*G19 -> 600 | J19: 小径ローレットノブ | L19: Y
C21: 遠藤製作所 | D21: 遠藤製作所 | E21: 98057-Y01 | F21: 1 | H21: 0 | J21: ツール板 | K21: ツール治具 | L21: Y
C22: 遠藤製作所 | D22: 遠藤製作所 | E22: 98057-Y02 | F22: 1 | H22: 0 | J22: 温調取付板 | K22: ツール治具 | L22: Y
C23: 遠藤製作所 | D23: 遠藤製作所 | E23: SS40079 | F23: 1 | H23: =F23*G23 -> 0 | J23: 740,752,780用ホルダ（Ｐ＝２５） | K23: ツール治具 | L23: Y
C24: 遠藤製作所 | D24: 遠藤製作所 | E24: SS4248 | F24: 1 | H24: 0 | J24: 井桁ベース（２００ｘ２００） | K24: 井桁治具 | L24: X
C25: 遠藤製作所 | D25: 遠藤製作所 | E25: SS4736 | F25: 2 | H25: 0 | J25: 井桁レール①（□２００） | K25: 井桁治具 | L25: X
C26: 遠藤製作所 | D26: 遠藤製作所 | E26: SS4737 | F26: 2 | H26: 0 | J26: 井桁レール②（□２００） | K26: 井桁治具 | L26: X
C27: 遠藤製作所 | D27: 遠藤製作所 | E27: SS4738 | F27: 4 | H27: 0 | J27: 井桁ストッパー① | K27: 井桁治具 | L27: X
C28: 遠藤製作所 | D28: 遠藤製作所 | E28: SS4739 | F28: 2 | H28: 0 | J28: 井桁ストッパー② | K28: 井桁治具 | L28: X
H29: 0
H30: 0
H31: 0
H32: 0
H33: 0
H34: 0
H35: 0
H36: 0
H37: =F37*G37 -> 0
H38: =F38*G38 -> 0
H39: =F39*G39 -> 0
H40: =F40*G40 -> 0
H41: =F41*G41 -> 0
H42: =F42*G42 -> 0
H43: =F43*G43 -> 0
H44: =F44*G44 -> 0
H45: =F45*G45 -> 0
H46: =F46*G46 -> 0
H47: =F47*G47 -> 0
H48: =F48*G48 -> 0
... H71: =F71*G71 -> 0

Sheet 【98157】富士システムズ株式会社 原価一覧4-12出荷
B2: お客先名 | E2: 富士ｼｽﾃﾑｽﾞ株式会社 | G2: 合計金額 | J2: =SUM(H:H) -> 756071
B3: 担当営業 | E3: 青木
B4: 受注番号 | E4: 98157
B5: 希望納期 | E5: 41011
B6: 最終納品
B8: 見積り分類 | C8: メーカー | D8: 仕入先 | E8: 品名 / 型式 | F8: 数量 | G8: 単価 | H8: 金額 | I8: 分類合計 | J8: 詳細 | K8: 備考 | L8: 技術分類 | M8: 発注日 | N8: 発注 | O8: 納期 | P8: 入荷予定日 | Q8: 入荷日
B9: 1 | C9: 蛇の目 | D9: 蛇の目 | E9: JR2303N | F9: 1 | G9: 546000 | H9: =F9*G9 -> 546000 | J9: 2303N 3軸ロボット 内部ｽｲｯﾁ仕様 | K9: 仙台（営）青木依頼分 | M9: 41015 | P9: ﾀﾞｲｱへ直送４/２５着
B10: 1 | C10: 蛇の目 | D10: 蛇の目 | E10: 荷造り運賃 | F10: 1 | G10: 10000 | H10: =F10*G10 -> 10000 | M10: 41015
B11: 2 | C11: 蛇の目 | D11: 蛇の目 | E11: 柱嵩上げ費用 | F11: 1 | G11: 35000 | H11: =F11*G11 -> 35000 | J11: JR2303NH 柱嵩上げ(JR2300Ｎ） | M11: 41015 | P11: ﾀﾞｲｱへ直送４/２５着
B12: 3 | C12: 蛇の目 | D12: 蛇の目 | E12: IO-1増設ｹｰﾌﾞﾙ | F12: 1 | G12: 5500 | H12: =F12*G12 -> 5500 | J12: IO-1増設ｹｰﾌﾞﾙ | M12: 41015 | P12: ﾀﾞｲｱへ直送４/２５着
B13: 4 | C13: 蛇の目 | D13: 蛇の目 | E13: JR-TB | F13: 1 | G13: 38000 | H13: =F13*G13 -> 38000 | J13: ティーチングペンダント | M13: 在庫使用
B14: 5 | C14: 蛇の目 | D14: 蛇の目 | E14: 20 | F14: 1 | G14: 50000 | H14: =F14*G14 -> 50000 | J14: ﾊｲｾﾝｻｰｷｯﾄ | M14: 41012 | P14: 41022
B15: 6 | C15: 蛇の目 | D15: 蛇の目 | E15: 20 | F15: 1 | G15: 31000 | H15: =F15*G15 -> 31000 | J15: B基板 | M15: 41012 | P15: 41022
B16: 6 | C16: 蛇の目 | D16: 蛇の目 | E16: 20 | F16: 1 | G16: 1000 | H16: =F16*G16 -> 1000 | J16: 送料 | M16: 41012
B17: 7 | C17: ＳＥＴ | D17: ＳＥＴ | E17: SV97MS | F17: 1 | H17: =F17*G17 -> 0 | J17: ｽﾌﾟﾚｰﾊﾞﾙﾌﾞ MS
B18: 8 | C18: ＳＥＴ | D18: ＳＥＴ | E18: SVC600 | F18: 1 | H18: =F18*G18 -> 0 | J18: ｽﾌﾟﾚｰﾊﾞﾙﾌﾞ ｺﾝﾄﾛｰﾗｰ
B19: 9 | C19: ＳＥＴ | D19: ＳＥＴ | E19: SH21-B | F19: 1 | H19: =F19*G19 -> 0 | J19: 21G GPﾆｰﾄﾞﾙﾉｽﾞﾙ12.7mm（ﾊﾟｰﾌﾟﾙ) 50入り
B20: 10 | C20: ＳＥＴ | D20: ＳＥＴ | E20: SH22-B | F20: 1 | H20: =F20*G20 -> 0 | J20: 22G GPﾆｰﾄﾞﾙﾉｽﾞﾙ12.7mm（ﾌﾞﾙｰ) 50入り
B21: 11 | C21: ＳＥＴ | D21: ＳＥＴ | E21: SH12CP-B | F21: 1 | H21: =F21*G21 -> 0 | J21: 30ccｼﾘﾝｼﾞ/ﾋﾟｽﾄﾝｾｯﾄ 20入
B22: 12 | C22: ＳＥＴ | D22: ＳＥＴ | E22: 100BSH52-6 | F22: 1 | H22: =F22*G22 -> 0 | J22: 30／55cc ｼﾘﾝｼﾞﾀﾞﾌﾟﾀｰ1.8m
B23: 13 | C23: 遠藤製作所 | D23: 遠藤製作所 | E23: 95113-X001 | F23: 1 | G23: 8900 | H23: =F23*G23 -> 8900 | J23: SV97用受けブラケット | L23: Y | M23: 41015 | P23: 41023
B24: 13 | C24: 遠藤製作所 | D24: 遠藤製作所 | E24: 95113-X002 | F24: 1 | G24: 5800 | H24: =F24*G24 -> 5800 | J24: SV97ﾊﾞﾙﾌﾞ受け Ａ | L24: Y | M24: 41015 | P24: 41023
B25: 13 | C25: 遠藤製作所 | D25: 遠藤製作所 | E25: 95113-X003 | F25: 1 | G25: 6200 | H25: =F25*G25 -> 6200 | J25: SV97ﾊﾞﾙﾌﾞ受け B | L25: Y | M25: 41015 | P25: 41023
B26: 13 | C26: ミスミ | D26: ミスミ | E26: MS3-20 | F26: 3 | G26: 99 | H26: =F26*G26 -> 297 | J26: ﾉｯｸﾋﾟﾝφ3-20mm | L26: Y | M26: 41015 | P26: 41018
B27: 13 | C27: ミスミ | D27: ミスミ | E27: MS3-15 | F27: 21 | G27: 34 | H27: =F27*G27 -> 714 | J27: ﾉｯｸﾋﾟﾝφ3-15mm | L27: Y | M27: 41015 | P27: 41018
B28: 13 | C28: ミスミ | D28: ミスミ | E28: SCB-4-40 | F28: 2 | G28: 95 | H28: =F28*G28 -> 190 | J28: 六角穴付ﾎﾞﾙﾄ(M4×40mm） | L28: Y | M28: 41015 | P28: 41018
B29: 13 | C29: ミスミ | D29: ミスミ | E29: SCB-4-14 | F29: 4 | G29: 80 | H29: =F29*G29 -> 320 | J29: 六角穴付ﾎﾞﾙﾄ(M4×14mm） | L29: Y | M29: 41015 | P29: 41018
B30: 14 | C30: 遠藤製作所 | D30: 遠藤製作所 | E30: 98201-Z01 | F30: 1 | G30: 4600 | H30: =F30*G30 -> 4600 | J30: 精密RG固定板金（右） | L30: Z | M30: 41015 | P30: 41023
B31: 14 | C31: SMC | D31: 都機工 | E31: SMC IR1010-01B-X465A | F31: 1 | G31: 12320 | H31: 12320 | J31: ﾚｷﾞｭﾚｰﾀ圧力計 | L31: Ｚ | M31: 41015 | P31: 41022 | Q31: 41022
B32: 14 | C32: ミスミ | D32: ミスミ | E32: MSCNL4-1 | F32: 1 | G32: 110 | H32: 110 | J32: φ4継手 | M32: 41015 | P32: 41018
B33: 14 | C33: ミスミ | D33: ミスミ | E33: MSCNL6-1 | F33: 1 | G33: 120 | H33: 120 | J33: φ6継手 | M33: 41015 | P33: 41018
B34: 15

Sheet 【98332】東鉱商事㈱ 原価一覧4-13出荷
B2: お客先名 | E2: 東鉱商事株式会社 | G2: 合計金額 | J2: =SUM(H:H) -> 29000
B3: 担当営業 | E3: 青木
B4: 受注番号 | E4: 98332
B5: 希望納期 | E5: 41012
B6: 最終納品
B8: 見積り分類 | C8: メーカー | D8: 仕入先 | E8: 品名 / 型式 | F8: 数量 | G8: 単価 | H8: 金額 | I8: 分類合計 | J8: 詳細 | K8: 備考 | L8: 技術分類 | M8: 発注日 | N8: 発注 | O8: 納期 | P8: 入荷予定日 | Q8: 入荷日
B9: 1 | C9: 遠藤製作所 | D9: 遠藤製作所 | E9: F1204P0081/3 | F9: 2 | G9: 14500 | H9: =F9*G9 -> 29000 | J9: 測定子（Ｃ TYPE） | K9: 図面は送信済み | L9: Y | M9: 41015 | P9: 41026 | Q9: 4/26斉藤氏受領

Sheet 【98454】コネクティックジャパン 原価一覧
B2: お客先名 | E2: コネクティックジャパン | G2: 合計金額 | J2: =SUM(H:H) -> 665066
B3: 担当営業 | E3: 村上
B4: 受注番号 | E4: 98454
B5: 希望納期 | E5: 41043
B6: 最終納品 | E6: 41051
B8: 見積り分類 | C8: メーカー | D8: 仕入先 | E8: 品名 / 型式 | F8: 数量 | G8: 単価 | H8: 金額 | I8: 分類合計 | J8: 詳細 | K8: 備考 | L8: 技術分類 | M8: 発注日 | N8: 発注 | O8: 納期 | P8: 入荷予定日 | Q8: 入荷日
B9: 1 | C9: 蛇の目 | D9: 蛇の目 | E9: ANMA110V2 | F9: 1 | G9: 155400 | H9: =F9*G9 -> 155400 | J9: マイクロイメージチェッカー | K9: 見積No：QSP-12-057 | L9: Y | M9: 41018 | P9: 41043 | Q9: 41040
B10: 2 | C10: 蛇の目 | D10: 蛇の目 | E10: ANM832 | F10: 1 | G10: 54600 | H10: =F10*G10 -> 54600 | J10: CSマウントカメラ | K10: 見積No：QSP-12-058 | L10: Y | M10: 41018 | P10: 41043 | Q10: 41040
B11: 2 | C11: 蛇の目 | D11: 蛇の目 | E11: ANM85202 | F11: 1 | G11: 7900 | H11: =F11*G11 -> 7900 | J11: 操作キーパッド | K11: 見積No：QSP-12-059 | L11: Y | M11: 41018 | P11: 41043 | Q11: 41040
B12: 2 | C12: 蛇の目 | D12: 蛇の目 | E12: ANB846NL(ｆ＝25） | F12: 1 | G12: 32700 | H12: =F12*G12 -> 32700 | J12: Cマウントレンズ | K12: 見積No：QSP-12-060 | L12: Y | M12: 41018 | P12: 41043 | Q12: 41040
B13: 2 | C13: 蛇の目 | D13: 蛇の目 | E13: ANB848 | F13: 1 | G13: 13500 | H13: =F13*G13 -> 13500 | J13: 中間リング | K13: 見積No：QSP-12-061 | L13: Y | M13: 41018 | P13: 41043 | Q13: 41040
B14: 5 | C14: 蛇の目 | D14: 蛇の目 | E14: 960536106 | F14: 1 | G14: 12000 | H14: =F14*G14 -> 12000 | J14: RS232Cケーブル | K14: 見積No：QSP-12-062 | L14: Y | M14: 41018 | P14: 41043 | Q14: 41040
B15: 4 | C15: 蛇の目 | D15: 蛇の目 | E15: MD-65RGB | F15: 1 | G15: 103200 | H15: =F15*G15 -> 103200 | J15: リング照明（3色） | K15: 見積No：QSP-12-063 | L15: Y | M15: 41018 | P15: 41043 | Q15: 41040
C16: 蛇の目 | D16: 蛇の目 | E16: 送料 | F16: 1 | G16: 1000 | H16: =F16*G16 -> 1000 | K16: 見積No：QSP-12-064 | L16: Y | M16: 41018
H17: =F17*G17 -> 0
B18: 3 | C18: ミスミ | D18: ミスミ | E18: PCFP-MV2G8-R | F18: 1 | G18: 48500 | H18: =F18*G18 -> 48500 | J18: 8.4インチ XGA ディスプレイ | L18: Z | M18: 41018 | P18: 41025 | Q18: 41025
B19: 3 | C19: ミスミ | D19: ミスミ | E19: DPAM-ES8 | F19: 1 | G19: 2950 | H19: =F19*G19 -> 2950 | J19: 固定ディスプレイスタンド | L19: Z | M19: 41018 | P19: 41025 | Q19: 41025
B20: 3 | C20: ミスミ | D20: ミスミ | E20: PCFP-MV-DC24 | F20: 1 | G20: 2980 | H20: =F20*G20 -> 2980 | J20: 小型ディスプレイ用ACアダプタ | L20: Z | M20: 41018 | P20: 41025 | Q20: 41025
B21: 3 | C21: ミスミ | D21: ミスミ | E21: PCFP-MV-CABLE300 | F21: 1 | G21: 1500 | H21: =F21*G21 -> 1500 | J21: ビデオケーブル | L21: Z | M21: 41018 | P21: 41025 | Q21: 41025
H22: =F22*G22 -> 0
B23: 6 | C23: ミスミ | D23: ミスミ | E23: SSE2BL10-230 | F23: 1 | G23: 8580 | H23: =F23*G23 -> 8580 | J23: ミニチュアリニアガイド | L23: Y | M23: 41018 | P23: 41025 | Q23: 41025
B24: 6 | C24: ミスミ | D24: ミスミ | E24: SLSBWF7-33.5-LKC | F24: 4 | G24: 1010 | H24: =F24*G24 -> 4040 | J24: 六角支柱 | L24: Y | M24: 41018 | P24: 41025 | Q24: 41025
B25: 6 | C25: ミスミ | D25: ミスミ | E25: SP-S3-5 | F25: 2 | G25: 210 | H25: =F25*G25 -> 420 | J25: パイプスペーサ | L25: Y | M25: 41018 | P25: 41025 | Q25: 41025
B26: 6 | C26: ミスミ | D26: ミスミ | E26: NKOS4-10 | F26: 2 | G26: 450 | H26: =F26*G26 -> 900 | J26: ローレットノブ | L26: Y | M26: 41018 | P26: 41025 | Q26: 41025
H27: =F27*G27 -> 0
B28: 9 | C28: ミスミ | D28: ミスミ | E28: CBSTS3-14 | F28: 6 | G28: 260 | H28: =F28*G28 -> 1560 | J28: 極低頭ボルト | L28: Z | M28: 41018 | P28: 41025 | Q28: 41025
B29: 9 | C29: ミスミ | D29: ミスミ | E29: HTCH0.5-20-20 | F29: 1 | G29: 780 | H29: =F29*G29 -> 780 | J29: 放熱ゲルシート | L29: Z | M29: 41018 | P29: 41025 | Q29: 41025
B30: 9 | C30: ミスミ | D30: ミスミ | E30: RBSMFA0.5-50-40 | F30: 1 | G30: 310 | H30: =F30*G30 -> 310 | J30: シリコンゴムシート | L30: Z | M30: 41018 | P30: 41025 | Q30: 41025
B31: 9 | C31: ミスミ | D31: ミスミ | E31: RBSMFA3-36-10 | F31: 2 | G31: 617 | H31: =F31*G31 -> 1234 | J31: シリコンゴムシート | L31: Z | M31: 41018 | P31: 41025 | Q31: 41025
B32: 9 | C32: ミスミ | D32: ミスミ | E32: NKOSF3-13 | F32: 1 | G32: 480 | H32: =F32*G32 -> 480 | J32: ローレットノブ | L32: Z | M32: 41018 | P32: 41025 | Q32: 41025
B33: 9 | C33: ミスミ | D33: ミスミ | E33: SFB3-10 | F33: 8 | G33: 104 | H33: =F33*G33 -> 832 | J33: 六角穴付皿ボルト | L33: Z | M33: 41018 | P33: 41025 | Q33: 41025
B34: 9 | C34: ミスミ | D34: ミスミ | E34: KCC10-4900-100224-28 | F34: 1 | G34: 4700 | H34: =F34*G34 -> 4700 | J34: 特注ﾊ-ﾈｽ | M34: 41019 | P34: 41036 | Q34: 41036
H35: =F35*G35 -> 0
B36: 9 | C36: タイショー | D36: タイショー | E36: TEB-10Mペルチェ温調ユニット | F36: 1 | G36: 178000 | H36: 178000 | J36: 見積No：12TM-0097-01 | L36: Z | M36: 41018 | P36: 41043 | Q36: 5/14斉藤(鉄)氏受領済
E37: （XXXX-Z01～Z06、TJ-0101-01-005込） | H37: =F37*G37 -> 0
H38: =F38*G38 -> 0
B39: 6 | C39: 遠藤製作所 | D39: 遠藤製作所 | E39: 98454-X01 | F39: 1 | G39: 10800 | H39: =F39*G39 -> 10800 | J39: 画像認識板P（e-starショート+ロング） | L39: Y | M39: 41018 | P39: 41043 | Q39: 41038
B40: 6 | C40: 遠藤製作所 | D40: 遠藤製作所 | E40: 98454-X02 | F40: 2 | G40: 2800 | H40: =F40*G40 -> 5600 | J40: CCD(P)+MD-65スライド板 | L40: Y | M40: 41018 | P40: 41043 | Q40: 41038
B41: 6 | C41: 遠藤製作所 | D41: 遠藤製作所 | E41: 98454-X03 | F41: 1 | G41: 2800 | H41: =F41*G41 -> 2800 | J41: CCD（P）取付板 | L41: Y | M41: 41018 | P41: 41043 | Q41: 41038
B42: 6 | C42: 遠藤製作所 | D42: 遠藤製作所 | E42: 98454-X04 | F42: 1 | G42: 4200 | H42: =F42*G42 -> 4200 | J42: MD-65取付板金 | L42: Y | M42: 41018 | P42: 41043 | Q42: 41038
B43: 6 | C43: 遠藤製作所 | D43: 遠藤製作所 | E43: 98454-X05 | F43: 1 | G43: 3600 | H43: =F43*G43 -> 3600 | J43: スライドガイド板金 | L43: Y | M43: 41018 | P43: 41043 | Q43: 41038
H44: =F44*G44 -> 0
H45: =F45*G45 -> 0
H46: =F46*G46 -> 0
H47: =F47*G47 -> 0
H48: =F48*G48 -> 0
H49: =F49*G49 -> 0
H50: =F50*G50 -> 0
H51: =F51*G51 -> 0
H52: =F52*G52 -> 0
H53: =F53*G53 -> 0
H54: =F54*G54 -> 0
H55: =F55*G55 -> 0
... H67: =F67*G67 -> 0

Sheet 【98518】 ソニーエナシ゛ーデバイス様 原価一覧4-19出
B2: お客先名 | E2: ｿﾆｰｴﾅｼﾞｰﾃﾞﾊﾞｲｽ | G2: 合計金額 | J2: =SUM(H:H) -> 961919
B3: 担当営業 | E3: 青木
B4: 受注番号 | E4: 98518
B5: 希望納期 | E5: 41018
B6: 最終納品 | E6: 41031
B8: 見積り分類 | C8: メーカー | D8: 仕入先 | E8: 品名 / 型式 | F8: 数量 | G8: 単価 | H8: 金額 | I8: 分類合計 | J8: 詳細 | K8: 備考 | L8: 技術分類 | M8: 発注日 | N8: 発注 | O8: 納期 | P8: 入荷予定日 | Q8: 入荷日
B9: 1 | C9: 蛇の目 | D9: 蛇の目 | E9: JR2503N | F9: 1 | G9: 765000 | H9: =F9*G9 -> 765000 | J9: 内部ｽｲｯﾁ仕様 | K9: 仙台（営）青木依頼分 | M9: 41022 | P9: 41040 | Q9: 41040
B10: 1 | C10: 蛇の目 | D10: 蛇の目 | E10: 荷造り運賃 | F10: 1 | G10: 10000 | H10: =F10*G10 -> 10000 | M10: 41022
B11: 1 | C11: ミスミ | D11: ミスミ | E11: AXSH212-VC-1PD2-2EB-1.5-1AC-2DA-F | F11: 1 | G11: 6615 | H11: =F11*G11 -> 6615 | J11: ＦＡｽｲｯﾁﾎﾞｯｸｽ | M11: 41019 | P11: 41024 | Q11: 41024
B12: 2 | C12: 蛇の目 | D12: 蛇の目 | E12: JR-TB | F12: 1 | G12: 38000 | H12: =F12*G12 -> 38000 | J12: ティーチングペンダント | M12: 在庫使用
B13: 3 | C13: ミスミ | D13: ミスミ | E13: NDDJ-PS-E37-1.0 | F13: 1 | G13: 5162 | H13: =F13*G13 -> 5162 | J13: ｺﾈｸﾀｰﾊｰﾈｽ 1m | M13: 41019 | P13: 41023 | Q13: 41023
B14: 4 | C14: ミスミ | D14: ミスミ | E14: MWI-DS37A-TB37 | F14: 1 | G14: 5100 | H14: =F14*G14 -> 5100 | J14: 端子台 | M14: 41019 | P14: 41022 | Q14: 41022
B15: 5 | C15: ミスミ | D15: ミスミ | E15: MWI-COM-P10N-10 | F15: 1 | G15: 2218 | H15: =F15*G15 -> 2218 | J15: ｅ-CON端子台 | M15: 41019 | P15: 41022 | Q15: 41022
B16: 6 | C16: ミスミ | D16: ミスミ | E16: @ECHN-20061106-00010 | F16: 1 | G16: 2814 | H16: =F16*G16 -> 2814 | J16: JR⇔SDP300 I/Oｹｰﾌﾞﾙ | M16: 41019 | P16: 41031 | Q16: 41031
B17: 7 | C17: ﾀｲｼｮｰ | D17: ﾀｲｼｮｰ | E17: 見積もりNO. 12TM-0157-00 | F17: 1 | G17: 18500 | H17: =F17*G17 -> 18500 | J17: 制御BOX ｱｯｾﾝﾌﾞﾘ加工費 | M17: 41022
C18: ﾀｲｼｮｰ | D18: ﾀｲｼｮｰ | E18: 見積もりNO. 12TM-0157-01 | F18: 1 | G18: 21845 | H18: =F18*G18 -> 21845 | J18: 購入品一式 | M18: 41061
C19: ﾀｲｼｮｰ | D19: ﾀｲｼｮｰ | E19: 見積もりNO. 12TM-0157-01 | F19: 1 | G19: 11500 | H19: =F19*G19 -> 11500 | J19: ｹ-ｽ追加工 | M19: 41061
B20: 7 | C20: ㈱ﾀｶﾁ電気工業 | D20: 都機工 | E20: FCWS400-150-125ＮＧＳＳ | F20: 1 | G20: 13000 | H20: =F20*G20 -> 13000 | J20: ﾌﾘｰｻｲｽﾞｹｰｽ | M20: 41019 | P20: 41036 | Q20: 41036
B21: 7 | C21: ㈱ﾀｶﾁ電気工業 | D21: 都機工 | E21: FCSC400-150-1 | F21: 1 | G21: 7990 | H21: =F21*G21 -> 7990 | J21: ﾌﾘｰｻｲｽﾞｹｰｽ ｵﾌﾟｼｮﾝ部品 | M21: 41019 | P21: 41036 | Q21: 41036
B22: 7 | C22: ミスミ | D22: ミスミ | E22: MRB-350 | F22: 1 | G22: 1080 | H22: =F22*G22 -> 1080 | J22: DINレール | M22: 41019 | P22: 41024 | Q22: 41024
B23: 7 | C23: ミスミ | D23: ミスミ | E23: KV-0.3-BE-10 | F23: 1 | G23: 780 | H23: =F23*G23 -> 780 | J23: 単芯電線 | M23: 41019 | P23: 41024 | Q23: 41024
B24: 7 | C24: ミスミ | D24: ミスミ | E24: 1.25-4 | F24: 1 | G24: 479 | H24: =F24*G24 -> 479 | J24: 裸圧着端子（丸型） | M24: 41019 | P24: 41022 | Q24: 41022
B25: 8 | C25: SET | D25: SET | E25: SV51MD | F25: 1 | H25: =F25*G25 -> 0 | J25: ﾆｰﾄﾞﾙﾊﾞﾙﾌﾞ ＭＤ
B26: 9 | C26: SET | D26: SET | E26: SDP300 | F26: 1 | H26: =F26*G26 -> 0 | J26: ﾃﾞｨｽﾍﾟﾝｻ
B27: 10 | C27: SET | D27: SET | E27: SS-6M0-2-2 | F27: 1 | H27: =F27*G27 -> 0 | J27: おすｴﾙﾎﾞｰ φ６×ＮＰＴ 1/8
B28: 11 | C28: SET | D28: SET | E28: SH23-B | H28: =F28*G28 -> 0 | J28: 23G GPﾆｰﾄﾞﾙﾉｽﾞﾙ 12.7mm(ｵﾚﾝｼﾞ）50個
B29: 12 | E29: 5 ** | H29: =F29*G29 -> 0 | J29: 残量検知付５ﾘｯﾄﾙﾀﾝｸ *ﾘｷｯﾄ *1
